Workbook
Name CAP: Sensitivity!$E$11
Name INTR: Sensitivity!$E$10
Name Lacs: Assumptions!$D$151
Name OP: Sensitivity!$E$8
Name PC: Sensitivity!$E$6
Name RM: Sensitivity!$E$7
Name SP: Sensitivity!$E$9

Sheet  
A1: Shree Ganesh
C2: IRONWELD ENGINEERING PVT. LTD | D2: IRONWELD ENGINEERING PVT. LTD | E2: IRONWELD ENGINEERING PVT. LTD | F2: IRONWELD ENGINEERING PVT. LTD | G2: IRONWELD ENGINEERING PVT. LTD | H2: IRONWELD ENGINEERING PVT. LTD | I2: IRONWELD ENGINEERING PVT. LTD | J2: IRONWELD ENGINEERING PVT. LTD | K2: IRONWELD ENGINEERING PVT. LTD | L2: IRONWELD ENGINEERING PVT. LTD | M2: IRONWELD ENGINEERING PVT. LTD | N2: IRONWELD ENGINEERING PVT. LTD | O2: IRONWELD ENGINEERING PVT. LTD | P2: IRONWELD ENGINEERING PVT. LTD | Q2: IRONWELD ENGINEERING PVT. LTD | R2: IRONWELD ENGINEERING PVT. LTD
C3: Financial Appraisal
C13: FINANCIAL MODEL OF IEPL
C15: Setting up of 3600 TPA Electroforged Steel Grating Manufacturing Facility
C16: at Pimpalgoan Phata , Post Markal ,Tal- Khed Dist.
C17: PUNE -412 105
C22: Greenweld Engineering Pvt. Ltd. (‘GEPL’ or ‘Company’) was incorporated on January 7, 2020, as a private limited company in Pune, Maharashtra. The Company is engaged in Design & Engineering Manufacturing and Supply of quality Electroforged /Manual Gratings, Stair Treads, Clamps & Handrails.
C23: The Company has embarked on a project for manufacturing 3600 TPA of electroforged gratings at a rented facility in Markal, Pune (‘Project’).
C24: The hard cost of the Project is estimated at INR 148.70 Lakh is proposed to be funded at a debt to equity ratio of 1.855 :1. The equity requirement is proposed to be met by fresh infusion of funds from the promoters and Unsecured Loans from the Promoters to the extent of INR 20.00 Lakh. The total debt requirement is to be funded by way of rupee term loans from banks & financial institutions.
C25: The Project is envisaged to commence operations from January 1, 2021. In the meantime ongoing operations are planned to support the Project.
C26: The Company also proposes to raise Working Capital fund based finance of INR 115 Lakh from Banks/Financial Institutions to kick start the operations post commencement.

Sheet Snapshot
C2: IRONWELD ENGINEERING PVT. LTD GREENFIELD PROJECT
M5: INR Lacs
C6: Project Details
C7: Project Cost | E7: ='Project Cost'!C21 -> 178.18624 | H7: Start of Construction | L7: =Assumptions!E6 -> 44044
C8: Means of Finance | H8: Construction Period (months) | L8: =Assumptions!E7 -> 5
C9: Debt | E9: =Assumptions!E35 -> 115 | H9: Completion Date | L9: =Assumptions!E8 -> 44196
C10: Equity | E10: =E11+E12 -> 63.186241 | H10: Commercial production | L10: =Assumptions!E9 -> 44197
C11: Share Capital | E11: =Assumptions!E33 -> 43.186241 | H11: Moratorium (months) | L11: =Assumptions!E45 -> 6
C12: Unsecured Loan | E12: =Assumptions!E34 -> 20 | H12: Repayment Start Date | L12: =Assumptions!E46 -> 44408
C13: Debt Equity Ratio | E13: =Assumptions!E37 -> 1.8200165 | H13: Repayment Ends Date | L13: =Assumptions!E47 -> 46934
C14: Working Capital Borrowing | E14: =WC!E20 -> 78.571222 | H14: No. of Repayments (months) | L14: =Assumptions!E48 -> 84
H15: Door to Door Tenor (years) | L15: =Assumptions!E49 -> 7.9138889
C16: Projected Financials
C17: Particulars | D17: =PL!D4 -> 44286 | E17: =PL!E4 -> 44651 | F17: =PL!F4 -> 45016 | G17: =PL!G4 -> 45382 | H17: =PL!H4 -> 45747 | I17: =PL!I4 -> 46112 | J17: =PL!J4 -> 46477 | K17: =PL!K4 -> 46843 | ... M17: =PL!M4 -> 47573
C18: Installed Capacity (TPA) | D18: =CoP!E7 -> 3600 | E18: =CoP!F7 -> 3600 | F18: =CoP!G7 -> 3600 | G18: =CoP!H7 -> 3600 | H18: =CoP!I7 -> 3600 | I18: =CoP!J7 -> 3600 | J18: =CoP!K7 -> 3600 | K18: =CoP!L7 -> 3600 | ... M18: =CoP!N7 -> 3600
C19: No. of Months of Operation | D19: =CoP!E5 -> 3 | E19: =CoP!F5 -> 12 | F19: =CoP!G5 -> 12 | G19: =CoP!H5 -> 12 | H19: =CoP!I5 -> 12 | I19: =CoP!J5 -> 12 | J19: =CoP!K5 -> 12 | K19: =CoP!L5 -> 12 | ... M19: =CoP!N5 -> 12
C20: Capacity Utilization | D20: =CoP!E9 -> 0.3 | E20: =CoP!F9 -> 0.35 | F20: =CoP!G9 -> 0.45 | G20: =CoP!H9 -> 0.55 | H20: =CoP!I9 -> 0.65 | I20: =CoP!J9 -> 0.75 | J20: =CoP!K9 -> 0.75 | K20: =CoP!L9 -> 0.75 | ... M20: =CoP!N9 -> 0.75
C21: Net Sales | D21: =PL!D10 -> 160.89192 | E21: =PL!E10 -> 984.71646 | F21: =PL!F10 -> 1259.8765 | G21: =PL!G10 -> 1543.6991 | H21: =PL!H10 -> 1827.5216 | I21: =PL!I10 -> 2111.3442 | J21: =PL!J10 -> 2128.6692 | K21: =PL!K10 -> 2128.6692 | ... M21: =PL!M10 -> 2128.6692
C22: EBITDA | D22: =PL!D31 -> 7.4629124 | E22: =PL!E31 -> 82.094516 | F22: =PL!F31 -> 117.18738 | G22: =PL!G31 -> 154.04325 | H22: =PL!H31 -> 190.57715 | I22: =PL!I31 -> 226.76215 | J22: =PL!J31 -> 225.56151 | K22: =PL!K31 -> 219.83007 | ... M22: =PL!M31 -> 206.9934
C23: PBT | D23: =PL!D39 -> -1.3533471 | E23: =PL!E39 -> 46.124405 | F23: =PL!F39 -> 78.416011 | G23: =PL!G39 -> 112.37434 | H23: =PL!H39 -> 146.00913 | I23: =PL!I39 -> 179.29331 | J23: =PL!J39 -> 179.22464 | K23: =PL!K39 -> 175.05587 | ... M23: =PL!M39 -> 164.6381
C24: PAT | D24: =PL!D43 -> -1.3533471 | E24: =PL!E43 -> 34.515815 | F24: =PL!F43 -> 58.680269 | G24: =PL!G43 -> 84.091967 | H24: =PL!H43 -> 109.26155 | I24: =PL!I43 -> 134.16877 | J24: =PL!J43 -> 134.11738 | K24: =PL!K43 -> 130.99781 | ... M24: =PL!M43 -> 123.20198
C25: Cash Accruals | D25: =PL!D46 -> 1.0522074 | E25: =PL!E46 -> 49.194401 | F25: =PL!F46 -> 70.095955 | G25: =PL!G46 -> 94.857866 | H25: =PL!H46 -> 119.48675 | I25: =PL!I46 -> 143.93892 | J25: =PL!J46 -> 143.50245 | K25: =PL!K46 -> 139.94149 | ... M25: =PL!M46 -> 131.62392
C27: EBITDA Margin | D27: =PL!D32 -> 0.046384631 | E27: =PL!E32 -> 0.083368685 | F27: =PL!F32 -> 0.093014975 | G27: =PL!G32 -> 0.099788392 | H27: =PL!H32 -> 0.10428175 | I27: =PL!I32 -> 0.10740179 | J27: =PL!J32 -> 0.10596363 | K27: =PL!K32 -> 0.10327113 | ... M27: =PL!M32 -> 0.097240753
C28: PAT Margin | D28: =PL!D44 -> 0 | E28: =PL!E44 -> 0 | F28: =PL!F44 -> 0 | G28: =PL!G44 -> 0 | H28: =PL!H44 -> 0 | I28: =PL!I44 -> 0 | J28: =PL!J44 -> 0 | K28: =PL!K44 -> 0 | ... M28: =PL!M44 -> 0
C29: DSCR | D29: =Ratio!D14 -> 1.3659852 | E29: =Ratio!E14 -> 2.755873 | F29: =Ratio!F14 -> 3.3141734 | G29: =Ratio!G14 -> 4.5547988 | H29: =Ratio!H14 -> 5.9573709 | I29: =Ratio!I14 -> 7.5550124 | J29: =Ratio!J14 -> 8.0453168 | K29: =Ratio!K14 -> 8.4340941 | ... M29: =Ratio!M14 -> 9.0557497
C30: Average DSCR | D30: =Ratio!D15 -> 0
C31: Minimum DSCR | D31: =Ratio!D16 -> 0
C33: Critical Ratios
C34: Current Ratio > 1.33 | D34: =KFR!D28 -> 1.1216275 | E34: =KFR!E28 -> 1.2775176 | F34: =KFR!F28 -> 1.4604606 | G34: =KFR!G28 -> 1.6677538 | H34: =KFR!H28 -> 1.8888873 | I34: =KFR!I28 -> 2.1180442 | J34: =KFR!J28 -> 2.4531751 | K34: =KFR!K28 -> 2.7830654 | ... M34: =KFR!M28 -> 3.5727391
D35: =KFR!D29 -> 0 | E35: =KFR!E29 -> 0 | F35: =KFR!F29 -> 0 | G35: =KFR!G29 -> 0 | H35: =KFR!H29 -> 0 | I35: =KFR!I29 -> 0 | J35: =KFR!J29 -> 0 | K35: =KFR!K29 -> 0 | ... M35: =KFR!M29 -> 0
C36: Debt Equity Ratio | D36: =KFR!D40 -> 1.8598515 | E36: =KFR!E40 -> 1.0816829 | F36: =KFR!F40 -> 0.57952875 | G36: =KFR!G40 -> 0.31560912 | H36: =KFR!H40 -> 0.17536401 | I36: =KFR!I40 -> 0.096816138 | J36: =KFR!J40 -> 0.052449156 | K36: =KFR!K40 -> 0.02403311 | ... M36: =KFR!M40 -> 3.4252912e-17
C37: TOL/TNW | D37: =KFR!D39 -> 0 | E37: =KFR!E39 -> 0 | F37: =KFR!F39 -> 0 | G37: =KFR!G39 -> 0 | H37: =KFR!H39 -> 0 | I37: =KFR!I39 -> 0 | J37: =KFR!J39 -> 0 | K37: =KFR!K39 -> 0 | ... M37: =KFR!M39 -> 0
C38: FACR | D38: =KFR!D34 -> 1.300785 | E38: =KFR!E34 -> 1.3430219 | F38: =KFR!F34 -> 1.4508059 | G38: =KFR!G34 -> 1.5996505 | H38: =KFR!H34 -> 1.8185396 | I38: =KFR!I34 -> 2.1721298 | J38: =KFR!J34 -> 2.8400223 | K38: =KFR!K34 -> 4.5850695 | ... M38: =KFR!M34 -> 1.8561851e+15
C39: ACR | D39: =KFR!D35 -> 0 | E39: =KFR!E35 -> 0 | F39: =KFR!F35 -> 0 | G39: =KFR!G35 -> 0 | H39: =KFR!H35 -> 0 | I39: =KFR!I35 -> 0 | J39: =KFR!J35 -> 0 | K39: =KFR!K35 -> 0 | ... M39: =KFR!M35 -> 0
C40: Interest Coverage | D40: =KFR!D30 -> 0.78889262 | E40: =KFR!E30 -> 2.7505918 | F40: =KFR!F30 -> 3.6901642 | G40: =KFR!G30 -> 4.5065818 | H40: =KFR!H30 -> 5.1781592 | I40: =KFR!I30 -> 5.7373661 | J40: =KFR!J30 -> 5.8815568 | K40: =KFR!K30 -> 5.9583597 | ... M40: =KFR!M30 -> 6.0046052
C42: Cash Balance | D42: =CF!D21 -> 1.0522074 | E42: =CF!E21 -> 23.288573 | F42: =CF!F21 -> 67.359974 | G42: =CF!G21 -> 135.80107 | H42: =CF!H21 -> 228.86668 | I42: =CF!I21 -> 346.37971 | J42: =CF!J21 -> 474.65847 | K42: =CF!K21 -> 600.14705 | ... M42: =CF!M21 -> 849.72261

Sheet Assumptions
C2: Assumptions
C4: Key Dates
C5: Financial Closure | E5: 44043
C6: Start of Construction | E6: 44044
C7: Construction Period (months) | E7: 5
C8: Completion Date | E8: =EDATE(E6,E7)-1 -> 44196
C9: Commercial production | E9: =E8+1 -> 44197
C10: End of First Year of Operations | E10: =DATE(IF(MONTH(E9)>3,(YEAR(E9)+1),YEAR(E9)),3,31) -> 44286
C11: No. of months of operation in first year | E11: =ROUND(((E10-E9)/30),0) -> 3
C12: Year End of First Year of Construction | E12: =DATE(IF(MONTH(E6)>3,(YEAR(E6)+1),YEAR(E6)),3,31) -> 44286
C13: 1st Quarter Ending after Start of Construction | E13: =EOMONTH(DATE(YEAR(E6),CEILING(MONTH(E6),3),0),1) -> 44104
C14: 1st Quarter Ending after Start of Operation | E14: =EOMONTH(DATE(YEAR(E9),CEILING(MONTH(E9),3),0),1) -> 44286
C16: Capex Schedule | E16: =EOMONTH(E6,0) -> 44074 | F16: =EOMONTH(E16,1) -> 44104 | G16: =EOMONTH(F16,1) -> 44135 | H16: =EOMONTH(G16,1) -> 44165 | I16: =EOMONTH(H16,1) -> 44196
C17: Land and Site Development | D17: =SUM(E17:I17) -> 1 | E17: 0.8 | F17: 0.2 | G17: 0 | H17: 0 | I17: =1-SUM(E17:H17) -> 0
C18: Factory Building | D18: =SUM(E18:I18) -> 1 | E18: 0.3 | F18: 0.3 | G18: 0.2 | H18: 0.2 | I18: =1-SUM(E18:H18) -> 0
C19: Non-Factory Building | D19: =SUM(E19:I19) -> 1 | E19: 0.3 | F19: 0.3 | G19: 0.2 | H19: 0.2 | I19: =1-SUM(E19:H19) -> 0
C20: Plant & Machinery | D20: =SUM(E20:I20) -> 1 | E20: 0.2 | F20: 0.4 | G20: 0.1 | H20: 0.3 | I20: =1-SUM(E20:H20) -> 0
C21: Utilities & Electrical Equipments | D21: =SUM(E21:I21) -> 1 | E21: 0.2 | F21: 0.2 | G21: 0.2 | H21: 0.2 | I21: =1-SUM(E21:H21) -> 0.2
C22: Misc Fixed Assets | D22: =SUM(E22:I22) -> 1 | E22: 0.2 | F22: 0.2 | G22: 0.2 | H22: 0.2 | I22: =1-SUM(E22:H22) -> 0.2
C23: Vehicle | D23: =SUM(E23:I23) -> 1 | E23: 0 | F23: 0 | G23: 0 | H23: 0.5 | I23: =1-SUM(E23:H23) -> 0.5
C24: Computer | D24: =SUM(E24:I24) -> 1 | E24: 0 | F24: 0 | G24: 0.2 | H24: 0.3 | I24: =1-SUM(E24:H24) -> 0.5
C25: Furniture | D25: =SUM(E25:I25) -> 1 | E25: 0 | F25: 0 | G25: 0.2 | H25: 0.3 | I25: =1-SUM(E25:H25) -> 0.5
C26: Preliminary & Preoperative Expenses | D26: =SUM(E26:I26) -> 1 | E26: 0.2 | F26: 0.2 | G26: 0.2 | H26: 0.2 | I26: =1-SUM(E26:H26) -> 0.2
C27: Contingency | D27: =SUM(E27:I27) -> 1 | E27: 0 | F27: 0 | G27: 0 | H27: 0 | I27: =1-SUM(E27:H27) -> 1
C28: Margin Money for Working Capital | D28: =SUM(E28:I28) -> 1 | E28: 0 | F28: 0 | G28: 0 | H28: 0 | I28: =1-SUM(E28:H28) -> 1
C30: Contingency | D30: 0.015
C32: Means of Finance | E32: INR Lacs
C33: Equity | E33: ='Project Cost'!C21-Assumptions!E35-Assumptions!E34 -> 43.186241
C34: Unsecured Loan | E34: 20
C35: Term Loan | E35: 115
C36: Total | E36: =SUM(E33:E35) -> 178.18624
C37: D/E Ratio | E37: =(E35)/(E33+E34) -> 1.8200165
C38: %Debt | E38: =E37/(1+E37)*100% -> 0.64539214
C40: Upfront Equity | E40: 0.1
C42: Term Loan Assumptions
C43: Effective Interest Rate | E43: =10%+INTR -> 0.1
C44: Upfront Fee | E44: 0
C45: Moratorium (months) | E45: 6
C46: Repayment Start Date | E46: =EOMONTH(EDATE(E9,E45),0) -> 44408
C47: Repayment Ends Date | E47: =EOMONTH(E46,E48-1) -> 46934
C48: No. of Repayments (months) | E48: =7*12 -> 84
C49: Door to Door Tenor (years) | E49: =YEARFRAC(E6,E47) -> 7.9138889
C52: Important milestones | D52: Date | E52: Qtr. | F52: FY | G52: FY Ending on
C53: End of Construction | D53: =E8 -> 44196 | E53: =DATE(YEAR(D53),((INT((MONTH(D53)-1)/3)+1)*3)+1,1)-1 -> 44196 | F53: =YEAR(DATE(IF(MONTH(D53)>3,YEAR(D53)+1,YEAR(D53)),3,31)) -> 2021 | G53: =DATE(IF(MONTH(D53)>3,YEAR(D53)+1,YEAR(D53)),3,31) -> 44286
C54: COD | D54: =E9 -> 44197 | E54: =DATE(YEAR(D54),((INT((MONTH(D54)-1)/3)+1)*3)+1,1)-1 -> 44286 | F54: =YEAR(DATE(IF(MONTH(D54)>3,YEAR(D54)+1,YEAR(D54)),3,31)) -> 2021 | G54: =DATE(IF(MONTH(D54)>3,YEAR(D54)+1,YEAR(D54)),3,31) -> 44286
C55: Loan Drawl starts | D55: =E6 -> 44044 | E55: =DATE(YEAR(D55),((INT((MONTH(D55)-1)/3)+1)*3)+1,1)-1 -> 44104 | F55: =YEAR(DATE(IF(MONTH(D55)>3,YEAR(D55)+1,YEAR(D55)),3,31)) -> 2021 | G55: =DATE(IF(MONTH(D55)>3,YEAR(D55)+1,YEAR(D55)),3,31) -> 44286
C56: Loan Drawl ends | D56: =E8 -> 44196 | E56: =DATE(YEAR(D56),((INT((MONTH(D56)-1)/3)+1)*3)+1,1)-1 -> 44196 | F56: =YEAR(DATE(IF(MONTH(D56)>3,YEAR(D56)+1,YEAR(D56)),3,31)) -> 2021 | G56: =DATE(IF(MONTH(D56)>3,YEAR(D56)+1,YEAR(D56)),3,31) -> 44286
C57: Repayment Commences from | D57: =E46 -> 44408 | E57: =DATE(YEAR(D57),((INT((MONTH(D57)-1)/3)+1)*3)+1,1)-1 -> 44469 | F57: =YEAR(DATE(IF(MONTH(D57)>3,YEAR(D57)+1,YEAR(D57)),3,31)) -> 2022 | G57: =DATE(IF(MONTH(D57)>3,YEAR(D57)+1,YEAR(D57)),3,31) -> 44651
C58: Repayment ends on | D58: =E47 -> 46934 | E58: =DATE(YEAR(D58),((INT((MONTH(D58)-1)/3)+1)*3)+1,1)-1 -> 46934 | F58: =YEAR(DATE(IF(MONTH(D58)>3,YEAR(D58)+1,YEAR(D58)),3,31)) -> 2029 | G58: =DATE(IF(MONTH(D58)>3,YEAR(D58)+1,YEAR(D58)),3,31) -> 47208
C61: Loan Repayment Schedule
C63: FY | D63: Q1 | E63: Q2 | F63: Q3 | G63: Q4 | H63: Total | I63: DSCR factor
C64: 2021 | H64: =SUM(D64:G64) -> 0 | I64: 1
C65: =C64+1 -> 2022 | E65: =F65 -> 0.03125 | F65: 0.03125 | G65: 0.03125 | H65: =SUM(D65:G65) -> 0.09375 | I65: 1
C66: =C65+1 -> 2023 | D66: 0.03125 | E66: 0.03125 | F66: 0.03125 | G66: 0.03125 | H66: =SUM(D66:G66) -> 0.125 | I66: 1
C67: =C66+1 -> 2024 | D67: 0.03125 | E67: 0.03125 | F67: 0.03125 | G67: 0.03125 | H67: =SUM(D67:G67) -> 0.125 | I67: 1
C68: =C67+1 -> 2025 | D68: 0.03125 | E68: 0.03125 | F68: 0.03125 | G68: 0.03125 | H68: =SUM(D68:G68) -> 0.125 | I68: =COUNTA(D68:G68)/4 -> 1
C69: =C68+1 -> 2026 | D69: 0.03125 | E69: 0.03125 | F69: 0.03125 | G69: 0.03125 | H69: =SUM(D69:G69) -> 0.125 | I69: =COUNTA(D69:G69)/4 -> 1
C70: =C69+1 -> 2027 | D70: 0.03125 | E70: 0.03125 | F70: 0.03125 | G70: 0.03125 | H70: =SUM(D70:G70) -> 0.125 | I70: =COUNTA(D70:G70)/4 -> 1
C71: =C70+1 -> 2028 | D71: 0.03125 | E71: 0.03125 | F71: 0.03125 | G71: 0.03125 | H71: =SUM(D71:G71) -> 0.125 | I71: =COUNTA(D71:G71)/4 -> 1
C72: =C71+1 -> 2029 | D72: 0.03125 | E72: 0.03125 | F72: 0.03125 | G72: 0.03125 | H72: =SUM(D72:G72) -> 0.125 | I72: =COUNTA(D72:G72)/4 -> 1
C73: =C72+1 -> 2030 | D73: 0.03125 | H73: =SUM(D73:G73) -> 0.03125 | I73: =COUNTA(D73:G73)/4 -> 0.25
C74: =C73+1 -> 2031 | H74: =SUM(D74:G74) -> 0 | I74: =COUNTA(D74:G74)/4 -> 0
C75: =C74+1 -> 2032 | H75: =SUM(D75:G75) -> 0 | I75: =COUNTA(D75:G75)/4 -> 0
C76: =C75+1 -> 2033 | H76: =SUM(D76:G76) -> 0 | I76: =COUNTA(D76:G76)/4 -> 0
C77: =C76+1 -> 2034 | H77: =SUM(D77:G77) -> 0 | I77: =COUNTA(D77:G77)/4 -> 0
H78: =SUM(H64:H77) -> 1
G79: Check | H79: =IF(H78-1>0,"ERROR","OK") -> OK
C81: Operating Assumptions
C82: FY Ending | E82: =E10 -> 44286 | F82: =EOMONTH(E82,12) -> 44651 | G82: =EOMONTH(F82,12) -> 45016 | H82: =EOMONTH(G82,12) -> 45382 | I82: =EOMONTH(H82,12) -> 45747 | J82: =EOMONTH(I82,12) -> 46112 | K82: =EOMONTH(J82,12) -> 46477 | L82: =EOMONTH(K82,12) -> 46843 | M82: =EOMONTH(L82,12) -> 47208 | N82: =EOMONTH(M82,12) -> 47573
C83: No. of Months of Operation | E83: =ROUNDDOWN((E82-E9+1)/30,0) -> 3 | F83: =ROUNDDOWN((F82-E82)/30,0) -> 12 | G83: =ROUNDDOWN((G82-F82)/30,0) -> 12 | H83: =ROUNDDOWN((H82-G82)/30,0) -> 12 | I83: =ROUNDDOWN((I82-H82)/30,0) -> 12 | J83: =ROUNDDOWN((J82-I82)/30,0) -> 12 | K83: =ROUNDDOWN((K82-J82)/30,0) -> 12 | L83: =ROUNDDOWN((L82-K82)/30,0) -> 12 | M83: =ROUNDDOWN((M82-L82)/30,0) -> 12 | N83: =ROUNDDOWN((N82-M82)/30,0) -> 12
C84: No. of Days of Operation | E84: =IF(E83=12,360,360*E83/12) -> 90 | F84: =IF(F83=12,360,360*F83/12) -> 360 | G84: =IF(G83=12,360,360*G83/12) -> 360 | H84: =IF(H83=12,360,360*H83/12) -> 360 | I84: =IF(I83=12,360,360*I83/12) -> 360 | J84: =IF(J83=12,360,360*J83/12) -> 360 | K84: =IF(K83=12,360,360*K83/12) -> 360 | L84: =IF(L83=12,360,360*L83/12) -> 360 | ... N84: =IF(N83=12,360,360*N83/12) -> 360
C85: Expansion Capacity (Ton Per Annum) | D85: =360*10 -> 3600 | E85: =D85 -> 3600 | F85: =E85 -> 3600 | G85: =F85 -> 3600 | H85: =G85 -> 3600 | I85: =H85 -> 3600 | J85: =I85 -> 3600 | K85: =J85 -> 3600 | L85: =K85 -> 3600 | ... N85: =M85 -> 3600
C86: Capacity Utilization (%) | E86: =30%+CAP -> 0.3 | F86: =35%+CAP -> 0.35 | G86: =45%+CAP -> 0.45 | H86: =55%+CAP -> 0.55 | I86: =65%+CAP -> 0.65 | J86: =75%+CAP -> 0.75 | K86: =J86 -> 0.75 | L86: =K86 -> 0.75 | M86: =L86 -> 0.75 | N86: =M86 -> 0.75
C88: Operating Costs
C89: Raw Materials Requirements | D89: Unit | E89: INR/Unit | F89: Cost/Ton
C90: Steel | D90: 1.12 | E90: =36500*(1+RM) -> 36500 | F90: =D90*E90 -> 40880
C91: Other Manufacturing Expenses
C92: Galv. Charges | D92: 1 | E92: =16940*(1+OP) -> 16940 | F92: =E92 -> 16940
C93: MSEB Electricity | D93: 160 | E93: =12*(1+OP) -> 12 | F93: =D93*E93 -> 1920
C94: Fabrication Cost | D94: 1 | E94: =3000*(1+OP) -> 3000 | F94: =D94*E94 -> 3000
C95: Consumable | F95: =1540*(1+OP) -> 1540
C96: Testing & Maint | F96: =770*(1+OP) -> 770
C98: Other Costs | D98: in Lacs
C99: Factory Rent | D99: 18 | E99: 0.1
C101: FY | E101: =E82 -> 44286 | F101: =F82 -> 44651 | G101: =G82 -> 45016 | H101: =H82 -> 45382 | I101: =I82 -> 45747 | J101: =J82 -> 46112 | K101: =K82 -> 46477 | L101: =L82 -> 46843 | ... N101: =N82 -> 47573
C102: Salaries & Wages | D102: lacs per month | E102: =(10*23000+10*15000+4*50000)/Lacs*55% -> 3.19 | F102: =E102*(1+5%) -> 3.3495 | G102: =F102*(1+5%) -> 3.516975 | H102: =G102*(1+5%) -> 3.6928238 | I102: =H102*(1+5%) -> 3.8774649 | J102: =I102*(1+5%) -> 4.0713382 | K102: =J102*(1+5%) -> 4.2749051 | L102: =K102*(1+5%) -> 4.4886503 | M102: =L102*(1+5%) -> 4.7130829 | N102: =M102*(1+5%) -> 4.948737
C104: Admin & Selling Expenses | D104: % of sales | E104: 0.03 | F104: 0.03 | G104: 0.03 | H104: 0.03 | I104: 0.03 | J104: 0.03 | K104: 0.03 | L104: 0.03 | M104: 0.03 | N104: 0.03
C107: Net Selling Prices | D107: INR per Ton
C108: Electroforged Gratings | D108: =77000*(1+SP) -> 77000
C109: Scrap Sales | D109: =E90*50% -> 18250
C112: Other Sales | D112: INR Lacs per Month
C113: Clamp & Hardware Sales | D113: 1
C114: Margin | D114: 0.5
C116: Woking Capital Norms | D116: Months
C117: Raw Material | D117: 0.75
C118: Work In Process (WIP) | D118: 0.5
C119: Finished Goods | D119: 0.25
C120: Sundry Debtors | D120: 1.5
C121: Stores & Spares | D121: 0.01 | E121: of Net Sales
C122: Creditors on Consumables | D122: 1
...

Sheet Project Cost
B2: Project Cost
J3: Soft Cost Allocation
B4: Particulars | C4: Amount | K4: =C14+C16+C18 -> 5.4958333
B5: Land and Site Development | C5: =D27*(1+PC) -> 9.5 | J5: =C5/SUM($C$5:$C$13) -> 0.064846416 | K5: =$K$4*J5 -> 0.3563851 | L5: =C5+K5 -> 9.8563851
B6: Factory Building | C6: =D32*(1+PC) -> 0 | J6: =C6/SUM($C$5:$C$13) -> 0 | K6: =$K$4*J6 -> 0 | L6: =C6+K6 -> 0
B7: Non-Factory Building | C7: =D37*(1+PC) -> 0 | J7: =C7/SUM($C$5:$C$13) -> 0 | K7: =$K$4*J7 -> 0 | L7: =C7+K7 -> 0
B8: Plant & Machinery | C8: =E55*(1+PC) -> 120 | J8: =C8/SUM($C$5:$C$13) -> 0.81911263 | K8: =$K$4*J8 -> 4.5017065 | L8: =C8+K8 -> 124.50171
B9: Utilities & Electrical Equipments | C9: =E60*(1+PC) -> 14 | J9: =C9/SUM($C$5:$C$13) -> 0.09556314 | K9: =$K$4*J9 -> 0.52519909 | L9: =C9+K9 -> 14.525199
B10: Misc Fixed Assets | C10: =E64*(1+PC) -> 0 | J10: =C10/SUM($C$5:$C$13) -> 0 | K10: =$K$4*J10 -> 0 | L10: =C10+K10 -> 0
B11: Vehicle | C11: =E68*(1+PC) -> 0 | J11: =C11/SUM($C$5:$C$13) -> 0 | K11: =$K$4*J11 -> 0 | L11: =C11+K11 -> 0
B12: Computer | C12: =E72*(1+PC) -> 1 | J12: =C12/SUM($C$5:$C$13) -> 0.0068259386 | K12: =$K$4*J12 -> 0.037514221 | L12: =C12+K12 -> 1.0375142
B13: Furniture | C13: =E76*(1+PC) -> 2 | J13: =C13/SUM($C$5:$C$13) -> 0.013651877 | K13: =$K$4*J13 -> 0.075028441 | L13: =C13+K13 -> 2.0750284
B14: Contingency | C14: =SUM(C5:C13)*Assumptions!D30 -> 2.1975 | L14: =SUM(L5:L13) -> 151.99583
B15: Total Hard Cost | C15: =SUM(C5:C14) -> 148.6975 | K15: Check | L15: =L14+C17-C21 -> 0
B16: Preliminery & Pre Operative Expenses | C16: =D82 -> 0.5
B17: Margin Money for Working Capital | C17: =WC!E18 -> 26.190407
B18: Interest During Construction | C18: ='Capex, Debt'!C114 -> 2.7983333
B19: Total Soft Cost | C19: =SUM(C16:C18) -> 29.488741
B21: Total Project Cost | C21: =C15+C19 -> 178.18624
B23: Land & Site Development | D23: INR Lacs
B25: Deposit for the Rented facilities | D25: 4.5
B26: Site Development | D26: 5
D27: =D25+D26 -> 9.5
B29: Factory Building | D29: INR Lacs
B31: Factory Building | D31: 0
D32: =D31 -> 0
B34: Non-Factory Building | D34: INR Lacs
B36: Non-Factory Building | D36: 0
D37: =D36 -> 0
B39: Plant & Machinery | C39: Qty | D39: Supplier | E39: INR Lacs
B41: Electroforged Grating welding Unit -400 KVA  Bearing bar feeding mechanism-for forward feeding of 40x 5 to 60x100 MS. Flat smoothly at the adjustment of 30mm to 100mm space. Capacity – 250 Mt/Month  Conveyor for exit grating panel of size of 1mtr x 6mtr  Cropping m/c to shear the 8mm dia. of twisted or round bar at the speed of 30 stroke/min. | C41: 1 | D41: Aditya Mech. | E41: 70
B42: Circular Cutting m/c to cut the M.S. grating panel of size max. of 8mm x100mm flat at the speed of 1mtr/min. | C42: 2 | D42: Dattatraya Enterprises | E42: 14
B43: Air screw compressor 50 CFM | C43: 1 | D43: Atlas Capco | E43: 2
B44: Water Chilling Plant 5MT | C44: 1 | D44: Bhagwan | E44: 4
B45: E.O.T. Crane 3Ton -20mtr span double gurder ,10mtrs H. | C45: 1 | D45: Microtek | E45: 9
B46: Jib crane with 2 MT Hoist | C46: 3 | E46: 6
B47: Hydraulic Stamping Machine 50T ( Hard Punch) | C47: 1 | D47: Hydrotek | E47: 3
B48: Cutting Wheel Sharpening Machine | C48: 1 | D48: Fabtech | E48: 2
B49: Material handling Trolley’s & Crane | C49: 2 | D49: GBM | E49: 2
B50: Bench Drilling Machine | C50: 1 | D50: Jwala | E50: 2
B51: Plate Bending Machine | C51: 1 | D51: Jwala | E51: 1
B52: CO2 Welding machine -15 kva | C52: 4 | D52: Mukund | E52: 2
B53: Arc welding generator -30 kva | C53: 2 | D53: Mukund | E53: 1
B54: Cost of Machinery installation | C54: Lump sum | E54: 2
E55: =SUM(E41:E54) -> 120
B57: Utilities & Electrical Equipments | C57: Qty | D57: Supplier | E57: INR Lacs
B58: Power transformer- 400 KVA, 33KV/440V | C58: 1 | D58: Transfab | E58: 8
B59: Electrical cabling & Distribution system | C59: Lump sum | D59: A.G.Carpo. | E59: 6
E60: =E58+E59 -> 14
B62: Miscellaneous Fixed Assets | C62: Qty | D62: Supplier | E62: INR Lacs
B63: Miscellaneous Fixed Assets
E64: =E63 -> 0
B66: Vehicles | C66: Qty | D66: Supplier | E66: INR Lacs
B67: Vehicles
E68: =E67 -> 0
B70: Computers | C70: Qty | D70: Supplier | E70: INR Lacs
B71: Computers | C71: Lump sum | D71: Local | E71: 1
E72: =E71 -> 1
B74: Furniture | C74: Qty | D74: Supplier | E74: INR Lacs
B75: Office Furniture | C75: Lump sum | D75: Local | E75: 2
E76: =E75 -> 2
B79: Preliminary & Pre-operative Expenses | D79: INR Lacs
B81: Preliminary & Pre-operative Expenses | D81: 0.5
D82: =D81 -> 0.5

Sheet Capex, Debt
B2: Capital Expenditure
B4: Capex - Monthly | D4: Till | E4: =DATE(IF(MONTH(E5)>3,YEAR(E5)+1,YEAR(E5)),3,31) -> 44286 | F4: =DATE(IF(MONTH(F5)>3,YEAR(F5)+1,YEAR(F5)),3,31) -> 44286 | G4: =DATE(IF(MONTH(G5)>3,YEAR(G5)+1,YEAR(G5)),3,31) -> 44286 | H4: =DATE(IF(MONTH(H5)>3,YEAR(H5)+1,YEAR(H5)),3,31) -> 44286 | I4: =DATE(IF(MONTH(I5)>3,YEAR(I5)+1,YEAR(I5)),3,31) -> 44286 | J4: TOTAL
D5: =EOMONTH(E5,-2) -> 44012 | E5: =Assumptions!E16 -> 44074 | F5: =Assumptions!F16 -> 44104 | G5: =Assumptions!G16 -> 44135 | H5: =Assumptions!H16 -> 44165 | I5: =Assumptions!I16 -> 44196
B6: Land and Site Development | C6: ='Project Cost'!C5 -> 9.5 | E6: =$C$6*Assumptions!E17 -> 7.6 | F6: =$C$6*Assumptions!F17 -> 1.9 | G6: =$C$6*Assumptions!G17 -> 0 | H6: =$C$6*Assumptions!H17 -> 0 | I6: =$C$6*Assumptions!I17 -> 0 | J6: =SUM(E6:I6) -> 9.5 | K6: =IF(J6=C6,"OK","ERROR") -> OK
B7: Factory Building | C7: ='Project Cost'!C6 -> 0 | K7: =IF(J7=C7,"OK","ERROR") -> OK
B8: Non-Factory Building | C8: ='Project Cost'!C7 -> 0 | K8: =IF(J8=C8,"OK","ERROR") -> OK
B9: Plant & Machinery | C9: ='Project Cost'!C8 -> 120 | E9: =$C$9*Assumptions!E20 -> 24 | F9: =$C$9*Assumptions!F20 -> 48 | G9: =$C$9*Assumptions!G20 -> 12 | H9: =$C$9*Assumptions!H20 -> 36 | I9: =$C$9*Assumptions!I20 -> 0 | J9: =SUM(E9:I9) -> 120 | K9: =IF(J9=C9,"OK","ERROR") -> OK
B10: Utilities & Electrical Equipments | C10: ='Project Cost'!C9 -> 14 | E10: =$C$10*Assumptions!E21 -> 2.8 | F10: =$C$10*Assumptions!F21 -> 2.8 | G10: =$C$10*Assumptions!G21 -> 2.8 | H10: =$C$10*Assumptions!H21 -> 2.8 | I10: =$C$10*Assumptions!I21 -> 2.8 | J10: =SUM(E10:I10) -> 14 | K10: =IF(J10=C10,"OK","ERROR") -> OK
B11: Misc Fixed Assets | C11: ='Project Cost'!C10 -> 0 | K11: =IF(J11=C11,"OK","ERROR") -> OK
B12: Vehicle | C12: ='Project Cost'!C11 -> 0 | K12: =IF(J12=C12,"OK","ERROR") -> OK
B13: Computer | C13: ='Project Cost'!C12 -> 1 | E13: =$C$13*Assumptions!E24 -> 0 | F13: =$C$13*Assumptions!F24 -> 0 | G13: =$C$13*Assumptions!G24 -> 0.2 | H13: =$C$13*Assumptions!H24 -> 0.3 | I13: =$C$13*Assumptions!I24 -> 0.5 | J13: =SUM(E13:I13) -> 1 | K13: =IF(J13=C13,"OK","ERROR") -> OK
B14: Furniture | C14: ='Project Cost'!C13 -> 2 | E14: =$C$14*Assumptions!E25 -> 0 | F14: =$C$14*Assumptions!F25 -> 0 | G14: =$C$14*Assumptions!G25 -> 0.4 | H14: =$C$14*Assumptions!H25 -> 0.6 | I14: =$C$14*Assumptions!I25 -> 1 | J14: =SUM(E14:I14) -> 2 | K14: =IF(J14=C14,"OK","ERROR") -> OK
B15: Contingency | C15: ='Project Cost'!C14 -> 2.1975 | E15: =$C$15*Assumptions!E27 -> 0 | F15: =$C$15*Assumptions!F27 -> 0 | G15: =$C$15*Assumptions!G27 -> 0 | H15: =$C$15*Assumptions!H27 -> 0 | I15: =$C$15*Assumptions!I27 -> 2.1975 | J15: =SUM(E15:I15) -> 2.1975 | K15: =IF(J15=C15,"OK","ERROR") -> OK
B16: Preliminary & Preoperative Expenses | C16: ='Project Cost'!C16 -> 0.5 | E16: =$C$16*Assumptions!E26 -> 0.1 | F16: =$C$16*Assumptions!F26 -> 0.1 | G16: =$C$16*Assumptions!G26 -> 0.1 | H16: =$C$16*Assumptions!H26 -> 0.1 | I16: =$C$16*Assumptions!I26 -> 0.1 | J16: =SUM(E16:I16) -> 0.5 | K16: =IF(J16=C16,"OK","ERROR") -> OK
B17: Margin Money for Working Capital | C17: ='Project Cost'!C17 -> 26.190407 | E17: =$C$17*Assumptions!E28 -> 0 | F17: =$C$17*Assumptions!F28 -> 0 | G17: =$C$17*Assumptions!G28 -> 0 | H17: =$C$17*Assumptions!H28 -> 0 | I17: =$C$17*Assumptions!I28 -> 26.190407 | J17: =SUM(E17:I17) -> 26.190407 | K17: =IF(J17=C17,"OK","ERROR") -> OK
B18: Interest During Construction | C18: ='Project Cost'!C18 -> 2.7983333 | E18: =E71 -> 0.11979167 | F18: =F71 -> 0.40729167 | G18: =G71 -> 0.62291667 | H18: =H71 -> 0.75229167 | I18: =I71 -> 0.89604167 | J18: =SUM(E18:I18) -> 2.7983333 | K18: =IF(J18=C18,"OK","ERROR") -> OK
B19: Total Project Cost | C19: =SUM(C6:C18) -> 178.18624 | D19: =SUM(D6:D18) -> 0 | E19: =SUM(E6:E18) -> 34.619792 | F19: =SUM(F6:F18) -> 53.207292 | G19: =SUM(G6:G18) -> 16.122917 | H19: =SUM(H6:H18) -> 40.552292 | I19: =SUM(I6:I18) -> 33.683949 | J19: =SUM(J6:J18) -> 178.18624
C20: =IF(C19='Project Cost'!C21,"Ok","ERROR") -> Ok
B23: Capex - Monthly | D23: Till | E23: =DATE(IF(MONTH(E24)>3,YEAR(E24)+1,YEAR(E24)),3,31) -> 44286 | F23: =DATE(IF(MONTH(F24)>3,YEAR(F24)+1,YEAR(F24)),3,31) -> 44286 | G23: =DATE(IF(MONTH(G24)>3,YEAR(G24)+1,YEAR(G24)),3,31) -> 44286 | H23: =DATE(IF(MONTH(H24)>3,YEAR(H24)+1,YEAR(H24)),3,31) -> 44286 | I23: =DATE(IF(MONTH(I24)>3,YEAR(I24)+1,YEAR(I24)),3,31) -> 44286 | J23: TOTAL
D24: =EOMONTH(E24,-2) -> 44012 | E24: =E5 -> 44074 | F24: =F5 -> 44104 | G24: =G5 -> 44135 | H24: =H5 -> 44165 | I24: =I5 -> 44196
B26: Total Funds Requirement | C26: =C19 -> 178.18624 | D26: =D19 -> 0 | E26: =E19 -> 34.619792 | F26: =F19 -> 53.207292 | G26: =G19 -> 16.122917 | H26: =H19 -> 40.552292 | I26: =I19 -> 33.683949 | J26: =SUM(D26:I26) -> 178.18624
B28: Upfront Equity | C28: =Assumptions!E33*Assumptions!E40 -> 4.3186241
B30: Upfront Equity Drawl | E30: =C28 -> 4.3186241
B31: Net Drawl Required | E31: =E26-E33-E30 -> 1.5511676 | F31: =F26-F33-F30 -> 12.957292 | G31: =G26-G33-G30 -> 4.6229167 | H31: =H26-H33-H30 -> 21.002292 | I31: =I26-I33-I30 -> 18.733949 | J31: =SUM(E31:I31) -> 58.867617
B33: Debt | E33: =Assumptions!$E$35*'Capex, Debt'!E37 -> 28.75 | F33: =Assumptions!$E$35*'Capex, Debt'!F37 -> 40.25 | G33: =Assumptions!$E$35*'Capex, Debt'!G37 -> 11.5 | H33: =Assumptions!$E$35*'Capex, Debt'!H37 -> 19.55 | I33: =Assumptions!$E$35*'Capex, Debt'!I37 -> 14.95 | J33: =SUM(E33:I33) -> 115
B34: Equity Drawl | E34: =E31+E30 -> 5.8697917 | F34: =F31+F30 -> 12.957292 | G34: =G31+G30 -> 4.6229167 | H34: =H31+H30 -> 21.002292 | I34: =I31+I30 -> 18.733949 | J34: =SUM(E34:I34) -> 63.186241
B35: Check | C35: =C33+C34-C26 -> -178.18624 | E35: =E33+E34-E26 -> 0 | F35: =F33+F34-F26 -> 0 | G35: =G33+G34-G26 -> 0 | H35: =H33+H34-H26 -> 0 | I35: =I33+I34-I26 -> 0
B37: Debt Drawl % | C37: =SUM(E37:I37) -> 1 | E37: 0.25 | F37: 0.35 | G37: 0.1 | H37: 0.17 | I37: =1-SUM(E37:H37) -> 0.13
B41: Quarterly
B42: FY | C42: Q1 | D42: Q2 | E42: Q3 | F42: Q4 | G42: Total | I42: FY | J42: Apr | K42: May | L42: Jun | M42: Jul | N42: Aug | O42: Sep | P42: Oct | Q42: Nov | R42: Dec | S42: Jan | T42: Feb | U42: Mar | V42: Total
B43: 2021 | C43: =Assumptions!D64 -> 0 | D43: =Assumptions!E64 -> 0 | E43: =Assumptions!F64 -> 0 | F43: =Assumptions!G64 -> 0 | G43: =SUM(C43:F43) -> 0 | I43: =B43 -> 2021 | J43: =C43/3 -> 0 | K43: =J43 -> 0 | L43: =K43 -> 0 | M43: =D43/3 -> 0 | N43: =M43 -> 0 | O43: =N43 -> 0 | P43: =E43/3 -> 0 | Q43: =P43 -> 0 | R43: =Q43 -> 0 | S43: =F43/3 -> 0 | T43: =S43 -> 0 | U43: =T43 -> 0 | V43: =SUM(J43:U43) -> 0
B44: =B43+1 -> 2022 | C44: =Assumptions!D65 -> 0 | D44: =Assumptions!E65 -> 0.03125 | E44: =Assumptions!F65 -> 0.03125 | F44: =Assumptions!G65 -> 0.03125 | G44: =SUM(C44:F44) -> 0.09375 | I44: =B44 -> 2022 | J44: =C44/3 -> 0 | K44: =J44 -> 0 | L44: =K44 -> 0 | M44: =D44/3 -> 0.010416667 | N44: =M44 -> 0.010416667 | O44: =N44 -> 0.010416667 | P44: =E44/3 -> 0.010416667 | Q44: =P44 -> 0.010416667 | R44: =Q44 -> 0.010416667 | S44: =F44/3 -> 0.010416667 | T44: =S44 -> 0.010416667 | U44: =T44 -> 0.010416667 | V44: =SUM(J44:U44) -> 0.09375
B45: =B44+1 -> 2023 | C45: =Assumptions!D66 -> 0.03125 | D45: =Assumptions!E66 -> 0.03125 | E45: =Assumptions!F66 -> 0.03125 | F45: =Assumptions!G66 -> 0.03125 | G45: =SUM(C45:F45) -> 0.125 | I45: =B45 -> 2023 | J45: =C45/3 -> 0.010416667 | K45: =J45 -> 0.010416667 | L45: =K45 -> 0.010416667 | M45: =D45/3 -> 0.010416667 | N45: =M45 -> 0.010416667 | O45: =N45 -> 0.010416667 | P45: =E45/3 -> 0.010416667 | Q45: =P45 -> 0.010416667 | R45: =Q45 -> 0.010416667 | S45: =F45/3 -> 0.010416667 | T45: =S45 -> 0.010416667 | U45: =T45 -> 0.010416667 | V45: =SUM(J45:U45) -> 0.125
B46: =B45+1 -> 2024 | C46: =Assumptions!D67 -> 0.03125 | D46: =Assumptions!E67 -> 0.03125 | E46: =Assumptions!F67 -> 0.03125 | F46: =Assumptions!G67 -> 0.03125 | G46: =SUM(C46:F46) -> 0.125 | I46: =B46 -> 2024 | J46: =C46/3 -> 0.010416667 | K46: =J46 -> 0.010416667 | L46: =K46 -> 0.010416667 | M46: =D46/3 -> 0.010416667 | N46: =M46 -> 0.010416667 | O46: =N46 -> 0.010416667 | P46: =E46/3 -> 0.010416667 | Q46: =P46 -> 0.010416667 | R46: =Q46 -> 0.010416667 | S46: =F46/3 -> 0.010416667 | T46: =S46 -> 0.010416667 | U46: =T46 -> 0.010416667 | V46: =SUM(J46:U46) -> 0.125
B47: =B46+1 -> 2025 | C47: =Assumptions!D68 -> 0.03125 | D47: =Assumptions!E68 -> 0.03125 | E47: =Assumptions!F68 -> 0.03125 | F47: =Assumptions!G68 -> 0.03125 | G47: =SUM(C47:F47) -> 0.125 | I47: =B47 -> 2025 | J47: =C47/3 -> 0.010416667 | K47: =J47 -> 0.010416667 | L47: =K47 -> 0.010416667 | M47: =D47/3 -> 0.010416667 | N47: =M47 -> 0.010416667 | O47: =N47 -> 0.010416667 | P47: =E47/3 -> 0.010416667 | Q47: =P47 -> 0.010416667 | R47: =Q47 -> 0.010416667 | S47: =F47/3 -> 0.010416667 | T47: =S47 -> 0.010416667 | U47: =T47 -> 0.010416667 | V47: =SUM(J47:U47) -> 0.125
B48: =B47+1 -> 2026 | C48: =Assumptions!D69 -> 0.03125 | D48: =Assumptions!E69 -> 0.03125 | E48: =Assumptions!F69 -> 0.03125 | F48: =Assumptions!G69 -> 0.03125 | G48: =SUM(C48:F48) -> 0.125 | I48: =B48 -> 2026 | J48: =C48/3 -> 0.010416667 | K48: =J48 -> 0.010416667 | L48: =K48 -> 0.010416667 | M48: =D48/3 -> 0.010416667 | N48: =M48 -> 0.010416667 | O48: =N48 -> 0.010416667 | P48: =E48/3 -> 0.010416667 | Q48: =P48 -> 0.010416667 | R48: =Q48 -> 0.010416667 | S48: =F48/3 -> 0.010416667 | T48: =S48 -> 0.010416667 | U48: =T48 -> 0.010416667 | V48: =SUM(J48:U48) -> 0.125
B49: =B48+1 -> 2027 | C49: =Assumptions!D70 -> 0.03125 | D49: =Assumptions!E70 -> 0.03125 | E49: =Assumptions!F70 -> 0.03125 | F49: =Assumptions!G70 -> 0.03125 | G49: =SUM(C49:F49) -> 0.125 | I49: =B49 -> 2027 | J49: =C49/3 -> 0.010416667 | K49: =J49 -> 0.010416667 | L49: =K49 -> 0.010416667 | M49: =D49/3 -> 0.010416667 | N49: =M49 -> 0.010416667 | O49: =N49 -> 0.010416667 | P49: =E49/3 -> 0.010416667 | Q49: =P49 -> 0.010416667 | R49: =Q49 -> 0.010416667 | S49: =F49/3 -> 0.010416667 | T49: =S49 -> 0.010416667 | U49: =T49 -> 0.010416667 | V49: =SUM(J49:U49) -> 0.125
B50: =B49+1 -> 2028 | C50: =Assumptions!D71 -> 0.03125 | D50: =Assumptions!E71 -> 0.03125 | E50: =Assumptions!F71 -> 0.03125 | F50: =Assumptions!G71 -> 0.03125 | G50: =SUM(C50:F50) -> 0.125 | I50: =B50 -> 2028 | J50: =C50/3 -> 0.010416667 | K50: =J50 -> 0.010416667 | L50: =K50 -> 0.010416667 | M50: =D50/3 -> 0.010416667 | N50: =M50 -> 0.010416667 | O50: =N50 -> 0.010416667 | P50: =E50/3 -> 0.010416667 | Q50: =P50 -> 0.010416667 | R50: =Q50 -> 0.010416667 | S50: =F50/3 -> 0.010416667 | T50: =S50 -> 0.010416667 | U50: =T50 -> 0.010416667 | V50: =SUM(J50:U50) -> 0.125
B51: =B50+1 -> 2029 | C51: =Assumptions!D72 -> 0.03125 | D51: =Assumptions!E72 -> 0.03125 | E51: =Assumptions!F72 -> 0.03125 | F51: =Assumptions!G72 -> 0.03125 | G51: =SUM(C51:F51) -> 0.125 | I51: =B51 -> 2029 | J51: =C51/3 -> 0.010416667 | K51: =J51 -> 0.010416667 | L51: =K51 -> 0.010416667 | M51: =D51/3 -> 0.010416667 | N51: =M51 -> 0.010416667 | O51: =N51 -> 0.010416667 | P51: =E51/3 -> 0.010416667 | Q51: =P51 -> 0.010416667 | R51: =Q51 -> 0.010416667 | S51: =F51/3 -> 0.010416667 | T51: =S51 -> 0.010416667 | U51: =T51 -> 0.010416667 | V51: =SUM(J51:U51) -> 0.125
B52: =B51+1 -> 2030 | C52: =Assumptions!D73 -> 0.03125 | D52: =Assumptions!E73 -> 0 | E52: =Assumptions!F73 -> 0 | F52: =Assumptions!G73 -> 0 | G52: =SUM(C52:F52) -> 0.03125 | I52: =B52 -> 2030 | J52: =C52/3 -> 0.010416667 | K52: =J52 -> 0.010416667 | L52: =K52 -> 0.010416667 | M52: =D52/3 -> 0 | N52: =M52 -> 0 | O52: =N52 -> 0 | P52: =E52/3 -> 0 | Q52: =P52 -> 0 | R52: =Q52 -> 0 | S52: =F52/3 -> 0 | T52: =S52 -> 0 | U52: =T52 -> 0 | V52: =SUM(J52:U52) -> 0.03125
B53: =B52+1 -> 2031 | C53: =Assumptions!D74 -> 0 | D53: =Assumptions!E74 -> 0 | E53: =Assumptions!F74 -> 0 | F53: =Assumptions!G74 -> 0 | G53: =SUM(C53:F53) -> 0 | I53: =B53 -> 2031 | J53: =C53/3 -> 0 | K53: =J53 -> 0 | L53: =K53 -> 0 | M53: =D53/3 -> 0 | N53: =M53 -> 0 | O53: =N53 -> 0 | P53: =E53/3 -> 0 | Q53: =P53 -> 0 | R53: =Q53 -> 0 | S53: =F53/3 -> 0 | T53: =S53 -> 0 | U53: =T53 -> 0 | V53: =SUM(J53:U53) -> 0
B54: =B53+1 -> 2032 | C54: =Assumptions!D75 -> 0 | D54: =Assumptions!E75 -> 0 | E54: =Assumptions!F75 -> 0 | F54: =Assumptions!G75 -> 0 | G54: =SUM(C54:F54) -> 0 | I54: =B54 -> 2032 | J54: =C54/3 -> 0 | K54: =J54 -> 0 | L54: =K54 -> 0 | M54: =D54/3 -> 0 | N54: =M54 -> 0 | O54: =N54 -> 0 | P54: =E54/3 -> 0 | Q54: =P54 -> 0 | R54: =Q54 -> 0 | S54: =F54/3 -> 0 | T54: =S54 -> 0 | U54: =T54 -> 0 | V54: =SUM(J54:U54) -> 0
B55: =B54+1 -> 2033 | C55: =Assumptions!D76 -> 0 | D55: =Assumptions!E76 -> 0 | E55: =Assumptions!F76 -> 0 | F55: =Assumptions!G76 -> 0 | G55: =SUM(C55:F55) -> 0 | I55: =B55 -> 2033 | J55: =C55/3 -> 0 | K55: =J55 -> 0 | L55: =K55 -> 0 | M55: =D55/3 -> 0 | N55: =M55 -> 0 | O55: =N55 -> 0 | P55: =E55/3 -> 0 | Q55: =P55 -> 0 | R55: =Q55 -> 0 | S55: =F55/3 -> 0 | T55: =S55 -> 0 | U55: =T55 -> 0 | V55: =SUM(J55:U55) -> 0
B56: =B55+1 -> 2034 | C56: =Assumptions!D77 -> 0 | D56: =Assumptions!E77 -> 0 | E56: =Assumptions!F77 -> 0 | F56: =Assumptions!G77 -> 0 | G56: =SUM(C56:F56) -> 0 | I56: =B56 -> 2034 | J56: =C56/3 -> 0 | K56: =J56 -> 0 | L56: =K56 -> 0 | M56: =D56/3 -> 0 | N56: =M56 -> 0 | O56: =N56 -> 0 | P56: =E56/3 -> 0 | Q56: =P56 -> 0 | R56: =Q56 -> 0 | S56: =F56/3 -> 0 | T56: =S56 -> 0 | U56: =T56 -> 0 | V56: =SUM(J56:U56) -> 0
G57: =SUM(G43:G56) -> 1 | V57: =SUM(V43:V56) -> 1
B61: Debt Schedule - Quarterly | E61: =DATE(IF(MONTH(E62)>3,YEAR(E62)+1,YEAR(E62)),3,31) -> 44286 | F61: =DATE(IF(MONTH(F62)>3,YEAR(F62)+1,YEAR(F62)),3,31) -> 44286 | G61: =DATE(IF(MONTH(G62)>3,YEAR(G62)+1,YEAR(G62)),3,31) -> 44286 | H61: =DATE(IF(MONTH(H62)>3,YEAR(H62)+1,YEAR(H62)),3,31) -> 44286 | I61: =DATE(IF(MONTH(I62)>3,YEAR(I62)+1,YEAR(I62)),3,31) -> 44286 | J61: =DATE(IF(MONTH(J62)>3,YEAR(J62)+1,YEAR(J62)),3,31) -> 44286 | K61: =DATE(IF(MONTH(K62)>3,YEAR(K62)+1,YEAR(K62)),3,31) -> 44286 | L61: =DATE(IF(MONTH(L62)>3,YEAR(L62)+1,YEAR(L62)),3,31) -> 44286 | ... EZ61: =DATE(IF(MONTH(EZ62)>3,YEAR(EZ62)+1,YEAR(EZ62)),3,31) -> 48669
E62: =E24 -> 44074 | F62: =EOMONTH(E62,1) -> 44104 | G62: =EOMONTH(F62,1) -> 44135 | H62: =EOMONTH(G62,1) -> 44165 | I62: =EOMONTH(H62,1) -> 44196 | J62: =EOMONTH(I62,1) -> 44227 | K62: =EOMONTH(J62,1) -> 44255 | L62: =EOMONTH(K62,1) -> 44286 | M62: =EOMONTH(L62,1) -> 44316 | ... EZ62: =EOMONTH(EY62,1) -> 48669
B64: Opening Balance | C64: 0 | E64: 0 | F64: =E67 -> 28.75 | G64: =F67 -> 69 | H64: =G67 -> 80.5 | I64: =H67 -> 100.05 | J64: =I67 -> 115 | K64: =J67 -> 115 | L64: =K67 -> 115 | M64: =L67 -> 115 | ... DP64: =DO67 -> -1.438849e-13
B65: Debt Drawl | C65: =SUM(E65:AI65) -> 115 | E65: =E33 -> 28.75 | F65: =F33 -> 40.25 | G65: =G33 -> 11.5 | H65: =H33 -> 19.55 | I65: =I33 -> 14.95
B66: Debt Repayment | C66: =SUM(E66:EZ66) -> 115 | E66: =$C$65*N43 -> 0 | F66: =$C$65*O43 -> 0 | G66: =$C$65*P43 -> 0 | H66: =$C$65*Q43 -> 0 | I66: =$C$65*R43 -> 0 | J66: =$C$65*S43 -> 0 | K66: =$C$65*T43 -> 0 | L66: =$C$65*U43 -> 0 | M66: =$C$65*J44 -> 0 | N66: =$C$65*K44 -> 0 | O66: =$C$65*L44 -> 0 | P66: =$C$65*M44 -> 1.1979167 | Q66: =$C$65*N44 -> 1.1979167 | R66: =$C$65*O44 -> 1.1979167 | S66: =$C$65*P44 -> 1.1979167 | T66: =$C$65*Q44 -> 1.1979167 | ... X66: =$C$65*U44 -> 1.1979167 | Y66: =$C$65*J45 -> 1.1979167 | Z66: =$C$65*K45 -> 1.1979167 | AA66: =$C$65*L45 -> 1.1979167 | AB66: =$C$65*M45 -> 1.1979167 | AC66: =$C$65*N45 -> 1.1979167 | AD66: =$C$65*O45 -> 1.1979167 | AE66: =$C$65*P45 -> 1.1979167 | AF66: =$C$65*Q45 -> 1.1979167 | ... AJ66: =$C$65*U45 -> 1.1979167 | AK66: =$C$65*J46 -> 1.1979167 | AL66: =$C$65*K46 -> 1.1979167 | AM66: =$C$65*L46 -> 1.1979167 | AN66: =$C$65*M46 -> 1.1979167 | AO66: =$C$65*N46 -> 1.1979167 | AP66: =$C$65*O46 -> 1.1979167 | AQ66: =$C$65*P46 -> 1.1979167 | AR66: =$C$65*Q46 -> 1.1979167 | ... AV66: =$C$65*U46 -> 1.1979167 | AW66: =$C$65*J47 -> 1.1979167 | AX66: =$C$65*K47 -> 1.1979167 | AY66: =$C$65*L47 -> 1.1979167 | AZ66: =$C$65*M47 -> 1.1979167 | BA66: =$C$65*N47 -> 1.1979167 | BB66: =$C$65*O47 -> 1.1979167 | BC66: =$C$65*P47 -> 1.1979167 | BD66: =$C$65*Q47 -> 1.1979167 | ... BH66: =$C$65*U47 -> 1.1979167 | BI66: =$C$65*J48 -> 1.1979167 | BJ66: =$C$65*K48 -> 1.1979167 | BK66: =$C$65*L48 -> 1.1979167 | BL66: =$C$65*M48 -> 1.1979167 | BM66: =$C$65*N48 -> 1.1979167 | BN66: =$C$65*O48 -> 1.1979167 | BO66: =$C$65*P48 -> 1.1979167 | BP66: =$C$65*Q48 -> 1.1979167 | ... BT66: =$C$65*U48 -> 1.1979167 | BU66: =$C$65*J49 -> 1.1979167 | BV66: =$C$65*K49 -> 1.1979167 | BW66: =$C$65*L49 -> 1.1979167 | BX66: =$C$65*M49 -> 1.1979167 | BY66: =$C$65*N49 -> 1.1979167 | BZ66: =$C$65*O49 -> 1.1979167 | CA66: =$C$65*P49 -> 1.1979167 | CB66: =$C$65*Q49 -> 1.1979167 | ... CF66: =$C$65*U49 -> 1.1979167 | CG66: =$C$65*J50 -> 1.1979167 | CH66: =$C$65*K50 -> 1.1979167 | CI66: =$C$65*L50 -> 1.1979167 | CJ66: =$C$65*M50 -> 1.1979167 | CK66: =$C$65*N50 -> 1.1979167 | CL66: =$C$65*O50 -> 1.1979167 | CM66: =$C$65*P50 -> 1.1979167 | CN66: =$C$65*Q50 -> 1.1979167 | ... CR66: =$C$65*U50 -> 1.1979167 | CS66: =$C$65*J51 -> 1.1979167 | CT66: =$C$65*K51 -> 1.1979167 | CU66: =$C$65*L51 -> 1.1979167 | CV66: =$C$65*M51 -> 1.1979167 | CW66: =$C$65*N51 -> 1.1979167 | CX66: =$C$65*O51 -> 1.1979167 | CY66: =$C$65*P51 -> 1.1979167 | CZ66: =$C$65*Q51 -> 1.1979167 | ... DD66: =$C$65*U51 -> 1.1979167 | DE66: =$C$65*J52 -> 1.1979167 | DF66: =$C$65*K52 -> 1.1979167 | DG66: =$C$65*L52 -> 1.1979167 | DH66: =$C$65*M52 -> 0 | DI66: =$C$65*N52 -> 0 | DJ66: =$C$65*O52 -> 0 | DK66: =$C$65*P52 -> 0 | DL66: =$C$65*Q52 -> 0 | ... DP66: =$C$65*U52 -> 0
B67: Closing Balance | C67: 0 | E67: =E64+E65-E66 -> 28.75 | F67: =F64+F65-F66 -> 69 | G67: =G64+G65-G66 -> 80.5 | H67: =H64+H65-H66 -> 100.05 | I67: =I64+I65-I66 -> 115 | J67: =J64+J65-J66 -> 115 | K67: =K64+K65-K66 -> 115 | L67: =L64+L65-L66 -> 115 | ... DP67: =DP64+DP65-DP66 -> -1.438849e-13
B69: IDC Flag | E69: =IF(E62<Assumptions!$E$9,1,0) -> 1 | F69: =IF(F62<Assumptions!$E$9,1,0) -> 1 | G69: =IF(G62<Assumptions!$E$9,1,0) -> 1 | H69: =IF(H62<Assumptions!$E$9,1,0) -> 1 | I69: =IF(I62<Assumptions!$E$9,1,0) -> 1 | J69: =IF(J62<Assumptions!$E$9,1,0) -> 0 | K69: =IF(K62<Assumptions!$E$9,1,0) -> 0 | L69: =IF(L62<Assumptions!$E$9,1,0) -> 0 | ... DP69: =IF(DP62<Assumptions!$E$9,1,0) -> 0
B70: Interest | C70: =Assumptions!$E$43 -> 0.1 | E70: =AVERAGE(E64,E67)*$C$70/12 -> 0.11979167 | F70: =AVERAGE(F64,F67)*$C$70/12 -> 0.40729167 | G70: =AVERAGE(G64,G67)*$C$70/12 -> 0.62291667 | H70: =AVERAGE(H64,H67)*$C$70/12 -> 0.75229167 | I70: =AVERAGE(I64,I67)*$C$70/12 -> 0.89604167 | J70: =AVERAGE(J64,J67)*$C$70/12 -> 0.95833333 | K70: =AVERAGE(K64,K67)*$C$70/12 -> 0.95833333 | L70: =AVERAGE(L64,L67)*$C$70/12 -> 0.95833333 | ... DP70: =AVERAGE(DP64,DP67)*$C$70/12 -> -1.1990409e-15
B71: IDC | C71: =SUM(E71:EZ71) -> 2.7983333 | E71: =IF(E69=1,E70,0) -> 0.11979167 | F71: =IF(F69=1,F70,0) -> 0.40729167 | G71: =IF(G69=1,G70,0) -> 0.62291667 | H71: =IF(H69=1,H70,0) -> 0.75229167 | I71: =IF(I69=1,I70,0) -> 0.89604167 | J71: =IF(J69=1,J70,0) -> 0 | K71: =IF(K69=1,K70,0) -> 0 | L71: =IF(L69=1,L70,0) -> 0 | ... DP71: =IF(DP69=1,DP70,0) -> 0
B72: P&L | C72: =SUM(E72:EZ72) -> 51.75 | E72: =E70-E71 -> 0 | F72: =F70-F71 -> 0 | G72: =G70-G71 -> 0 | H72: =H70-H71 -> 0 | I72: =I70-I71 -> 0 | J72: =J70-J71 -> 0.95833333 | K72: =K70-K71 -> 0.95833333 | L72: =L70-L71 -> 0.95833333 | ... DP72: =DP70-DP71 -> -1.1990409e-15
B75: Capex - Yearly | E75: =Assumptions!E12 -> 44286
B77: Land and Site Development | E77: =SUMIF($E$4:$I$4,$E$75,E6:I6) -> 9.5 | F77: =_xlfn.FORMULATEXT(E77) -> =SUMIF($E$4:$I$4,$E$75,E6:I6)
B78: Factory Building | E78: =SUMIF($E$4:$I$4,$E$75,E7:I7) -> 0
B79: Non-Factory Building | E79: =SUMIF($E$4:$I$4,$E$75,E8:I8) -> 0
B80: Plant & Machinery | E80: =SUMIF($E$4:$I$4,$E$75,E9:I9) -> 120
B81: Utilities & Electrical Equipments | E81: =SUMIF($E$4:$I$4,$E$75,E10:I10) -> 14
B82: Misc Fixed Assets | E82: =SUMIF($E$4:$I$4,$E$75,E11:I11) -> 0
B83: Vehicle | E83: =SUMIF($E$4:$I$4,$E$75,E12:I12) -> 0
B84: Computer | E84: =SUMIF($E$4:$I$4,$E$75,E13:I13) -> 1
B85: Furniture | E85: =SUMIF($E$4:$I$4,$E$75,E14:I14) -> 2
B86: Contingency | E86: =SUMIF($E$4:$I$4,$E$75,E15:I15) -> 2.1975
B87: Preliminary & Preoperative Expenses | E87: =SUMIF($E$4:$I$4,$E$75,E16:I16) -> 0.5
B88: Margin Money for Working Capital | E88: =SUMIF($E$4:$I$4,$E$75,E17:I17) -> 26.190407
B89: Interest During Construction | E89: =SUMIF($E$4:$I$4,$E$75,E18:I18) -> 2.7983333
B90: Total Project Cost | E90: =SUM(E77:E89) -> 178.18624
B93: Fund Phasing - Yearly | E93: =E75 -> 44286
B94: Total Funds Requirement | E94: =SUMIF($E$23:$I$23,$E$93,E26:I26) -> 178.18624 | F94: =_xlfn.FORMULATEXT(E94) -> =SUMIF($E$23:$I$23,$E$93,E26:I26)
B96: Upfront Equity
B98: Upfront Equity Drawl | E98: =SUMIF($E$23:$I$23,$E$93,E30:I30) -> 4.3186241 | F98: =_xlfn.FORMULATEXT(E98) -> =SUMIF($E$23:$I$23,$E$93,E30:I30)
B99: Net Drawl Required | E99: =SUMIF($E$23:$I$23,$E$93,E31:I31) -> 58.867617 | F99: =_xlfn.FORMULATEXT(E99) -> =SUMIF($E$23:$I$23,$E$93,E31:I31)
B101: Debt | E101: =SUMIF($E$23:$I$23,$E$93,E33:I33) -> 115 | F101: =_xlfn.FORMULATEXT(E101) -> =SUMIF($E$23:$I$23,$E$93,E33:I33)
B102: Equity Drawl | E102: =SUMIF($E$23:$I$23,$E$93,E34:I34) -> 63.186241 | F102: =_xlfn.FORMULATEXT(E102) -> =SUMIF($E$23:$I$23,$E$93,E34:I34)
B103: Total Funding | E103: =E101+E102 -> 178.18624
B106: Debt Schedule - Yearly | E106: =E93 -> 44286 | F106: =EOMONTH(E106,12) -> 44651 | G106: =EOMONTH(F106,12) -> 45016 | H106: =EOMONTH(G106,12) -> 45382 | I106: =EOMONTH(H106,12) -> 45747 | J106: =EOMONTH(I106,12) -> 46112 | K106: =EOMONTH(J106,12) -> 46477 | L106: =EOMONTH(K106,12) -> 46843 | M106: =EOMONTH(L106,12) -> 47208 | ... Q106: =EOMONTH(P106,12) -> 48669
B107: Repayment Months | E107: =COUNTIFS($E$61:$EZ$61,E106,$E$66:$EZ$66,">0") -> 0 | F107: =COUNTIFS($E$61:$EZ$61,F106,$E$66:$EZ$66,">0") -> 9 | G107: =COUNTIFS($E$61:$EZ$61,G106,$E$66:$EZ$66,">0") -> 12 | H107: =COUNTIFS($E$61:$EZ$61,H106,$E$66:$EZ$66,">0") -> 12 | I107: =COUNTIFS($E$61:$EZ$61,I106,$E$66:$EZ$66,">0") -> 12 | J107: =COUNTIFS($E$61:$EZ$61,J106,$E$66:$EZ$66,">0") -> 12 | K107: =COUNTIFS($E$61:$EZ$61,K106,$E$66:$EZ$66,">0") -> 12 | L107: =COUNTIFS($E$61:$EZ$61,L106,$E$66:$EZ$66,">0") -> 12 | ... Q107: =COUNTIFS($E$61:$EZ$61,Q106,$E$66:$EZ$66,">0") -> 0
B108: Opening Balance | E108: =0 -> 0 | F108: =E111 -> 115 | G108: =F111 -> 104.21875 | H108: =G111 -> 89.84375 | I108: =H111 -> 75.46875 | J108: =I111 -> 61.09375 | K108: =J111 -> 46.71875 | L108: =K111 -> 32.34375 | M108: =L111 -> 17.96875 | ... Q108: =P111 -> 3.4194869e-14
B109: Debt Drawl | C109: =SUM(E109:Q109) -> 115 | E109: =SUMIF($E$61:$EZ$61,E106,$E$65:$EZ$65) -> 115 | F109: =SUMIF($E$61:$EZ$61,F106,$E$65:$EZ$65) -> 0 | G109: =SUMIF($E$61:$EZ$61,G106,$E$65:$EZ$65) -> 0 | H109: =SUMIF($E$61:$EZ$61,H106,$E$65:$EZ$65) -> 0 | I109: =SUMIF($E$61:$EZ$61,I106,$E$65:$EZ$65) -> 0 | J109: =SUMIF($E$61:$EZ$61,J106,$E$65:$EZ$65) -> 0 | K109: =SUMIF($E$61:$EZ$61,K106,$E$65:$EZ$65) -> 0 | L109: =SUMIF($E$61:$EZ$61,L106,$E$65:$EZ$65) -> 0 | ... Q109: =SUMIF($E$61:$EZ$61,Q106,$E$65:$EZ$65) -> 0
B110: Debt Repayment | C110: =SUM(E110:Q110) -> 115 | E110: =SUMIF($E$61:$EZ$61,E106,$E$66:$EZ$66) -> 0 | F110: =SUMIF($E$61:$EZ$61,F106,$E$66:$EZ$66) -> 10.78125 | G110: =SUMIF($E$61:$EZ$61,G106,$E$66:$EZ$66) -> 14.375 | H110: =SUMIF($E$61:$EZ$61,H106,$E$66:$EZ$66) -> 14.375 | I110: =SUMIF($E$61:$EZ$61,I106,$E$66:$EZ$66) -> 14.375 | J110: =SUMIF($E$61:$EZ$61,J106,$E$66:$EZ$66) -> 14.375 | K110: =SUMIF($E$61:$EZ$61,K106,$E$66:$EZ$66) -> 14.375 | L110: =SUMIF($E$61:$EZ$61,L106,$E$66:$EZ$66) -> 14.375 | ... Q110: =SUMIF($E$61:$EZ$61,Q106,$E$66:$EZ$66) -> 0
B111: Closing Balance | E111: =E108+E109-E110 -> 115 | F111: =F108+F109-F110 -> 104.21875 | G111: =G108+G109-G110 -> 89.84375 | H111: =H108+H109-H110 -> 75.46875 | I111: =I108+I109-I110 -> 61.09375 | J111: =J108+J109-J110 -> 46.71875 | K111: =K108+K109-K110 -> 32.34375 | L111: =L108+L109-L110 -> 17.96875 | ... Q111: =Q108+Q109-Q110 -> 3.4194869e-14
B113: Interest | C113: =SUM(E113:Q113) -> 54.548333 | E113: =SUMIF($E$61:$EZ$61,E106,$E$70:$EZ$70) -> 5.6733333 | F113: =SUMIF($E$61:$EZ$61,F106,$E$70:$EZ$70) -> 11.095703 | G113: =SUMIF($E$61:$EZ$61,G106,$E$70:$EZ$70) -> 9.703125 | H113: =SUMIF($E$61:$EZ$61,H106,$E$70:$EZ$70) -> 8.265625 | I113: =SUMIF($E$61:$EZ$61,I106,$E$70:$EZ$70) -> 6.828125 | J113: =SUMIF($E$61:$EZ$61,J106,$E$70:$EZ$70) -> 5.390625 | K113: =SUMIF($E$61:$EZ$61,K106,$E$70:$EZ$70) -> 3.953125 | L113: =SUMIF($E$61:$EZ$61,L106,$E$70:$EZ$70) -> 2.515625 | ... Q113: =SUMIF($E$61:$EZ$61,Q106,$E$70:$EZ$70) -> 0
B114: IDC | C114: =SUM(E114:Q114) -> 2.7983333 | E114: =SUMIF($E$61:$EZ$61,E106,$E$71:$EZ$71) -> 2.7983333 | F114: =SUMIF($E$61:$EZ$61,F106,$E$71:$EZ$71) -> 0 | G114: =SUMIF($E$61:$EZ$61,G106,$E$71:$EZ$71) -> 0 | H114: =SUMIF($E$61:$EZ$61,H106,$E$71:$EZ$71) -> 0 | I114: =SUMIF($E$61:$EZ$61,I106,$E$71:$EZ$71) -> 0 | J114: =SUMIF($E$61:$EZ$61,J106,$E$71:$EZ$71) -> 0 | K114: =SUMIF($E$61:$EZ$61,K106,$E$71:$EZ$71) -> 0 | L114: =SUMIF($E$61:$EZ$61,L106,$E$71:$EZ$71) -> 0 | ... Q114: =SUMIF($E$61:$EZ$61,Q106,$E$71:$EZ$71) -> 0
B115: P&L | C115: =SUM(E115:Q115) -> 51.75 | E115: =SUMIF($E$61:$EZ$61,E106,$E$72:$EZ$72) -> 2.875 | F115: =SUMIF($E$61:$EZ$61,F106,$E$72:$EZ$72) -> 11.095703 | G115: =SUMIF($E$61:$EZ$61,G106,$E$72:$EZ$72) -> 9.703125 | H115: =SUMIF($E$61:$EZ$61,H106,$E$72:$EZ$72) -> 8.265625 | I115: =SUMIF($E$61:$EZ$61,I106,$E$72:$EZ$72) -> 6.828125 | J115: =SUMIF($E$61:$EZ$61,J106,$E$72:$EZ$72) -> 5.390625 | K115: =SUMIF($E$61:$EZ$61,K106,$E$72:$EZ$72) -> 3.953125 | L115: =SUMIF($E$61:$EZ$61,L106,$E$72:$EZ$72) -> 2.515625 | ... Q115: =SUMIF($E$61:$EZ$61,Q106,$E$72:$EZ$72) -> 0
B116: Installment due within one year | C116: =C113-C114-C115 -> 0 | E116: =F110 -> 10.78125 | F116: =G110 -> 14.375 | G116: =H110 -> 14.375 | H116: =I110 -> 14.375 | I116: =J110 -> 14.375 | J116: =K110 -> 14.375 | K116: =L110 -> 14.375 | L116: =M110 -> 14.375 | ... Q116: =R110 -> 0

Sheet CoP
B2: Cost of Production
B4: FY Ending | E4: =Assumptions!E82 -> 44286 | F4: =Assumptions!F82 -> 44651 | G4: =Assumptions!G82 -> 45016 | H4: =Assumptions!H82 -> 45382 | I4: =Assumptions!I82 -> 45747 | J4: =Assumptions!J82 -> 46112 | K4: =Assumptions!K82 -> 46477 | L4: =Assumptions!L82 -> 46843 | ... N4: =Assumptions!N82 -> 47573
B5: No. of Months | E5: =Assumptions!E83 -> 3 | F5: =Assumptions!F83 -> 12 | G5: =Assumptions!G83 -> 12 | H5: =Assumptions!H83 -> 12 | I5: =Assumptions!I83 -> 12 | J5: =Assumptions!J83 -> 12 | K5: =Assumptions!K83 -> 12 | L5: =Assumptions!L83 -> 12 | ... N5: =Assumptions!N83 -> 12
B7: Capacity | C7: Ton | E7: =Assumptions!E85 -> 3600 | F7: =Assumptions!F85 -> 3600 | G7: =Assumptions!G85 -> 3600 | H7: =Assumptions!H85 -> 3600 | I7: =Assumptions!I85 -> 3600 | J7: =Assumptions!J85 -> 3600 | K7: =Assumptions!K85 -> 3600 | L7: =Assumptions!L85 -> 3600 | ... N7: =Assumptions!N85 -> 3600
B9: Capacity Utilisation | E9: =Assumptions!E86 -> 0.3 | F9: =Assumptions!F86 -> 0.35 | G9: =Assumptions!G86 -> 0.45 | H9: =Assumptions!H86 -> 0.55 | I9: =Assumptions!I86 -> 0.65 | J9: =Assumptions!J86 -> 0.75 | K9: =Assumptions!K86 -> 0.75 | L9: =Assumptions!L86 -> 0.75 | ... N9: =Assumptions!N86 -> 0.75
B11: Production | C11: Ton | E11: =E7*E9*E5/12 -> 270 | F11: =F7*F9*F5/12 -> 1260 | G11: =G7*G9*G5/12 -> 1620 | H11: =H7*H9*H5/12 -> 1980 | I11: =I7*I9*I5/12 -> 2340 | J11: =J7*J9*J5/12 -> 2700 | K11: =K7*K9*K5/12 -> 2700 | L11: =L7*L9*L5/12 -> 2700 | ... N11: =N7*N9*N5/12 -> 2700
B13: WIP Inventory - Opening | E13: 0 | F13: =E14 -> 45 | G13: =F14 -> 52.5 | H13: =G14 -> 67.5 | I13: =H14 -> 82.5 | J13: =I14 -> 97.5 | K13: =J14 -> 112.5 | L13: =K14 -> 112.5 | M13: =L14 -> 112.5 | N13: =M14 -> 112.5
A14: =Assumptions!D118 -> 0.5 | B14: WIP Inventory - Closing | C14: Ton | E14: =E11/E5*$A$14 -> 45 | F14: =F11/F5*$A$14 -> 52.5 | G14: =G11/G5*$A$14 -> 67.5 | H14: =H11/H5*$A$14 -> 82.5 | I14: =I11/I5*$A$14 -> 97.5 | J14: =J11/J5*$A$14 -> 112.5 | K14: =K11/K5*$A$14 -> 112.5 | L14: =L11/L5*$A$14 -> 112.5 | ... N14: =N11/N5*$A$14 -> 112.5
B16: FG Inventory - Opening | E16: 0 | F16: =E17 -> 22.5 | G16: =F17 -> 26.25 | H16: =G17 -> 33.75 | I16: =H17 -> 41.25 | J16: =I17 -> 48.75 | K16: =J17 -> 56.25 | L16: =K17 -> 56.25 | M16: =L17 -> 56.25 | N16: =M17 -> 56.25
A17: =Assumptions!D119 -> 0.25 | B17: FG Inventory - Closing | C17: Ton | E17: =E11/E5*$A$17 -> 22.5 | F17: =F11/F5*$A$17 -> 26.25 | G17: =G11/G5*$A$17 -> 33.75 | H17: =H11/H5*$A$17 -> 41.25 | I17: =I11/I5*$A$17 -> 48.75 | J17: =J11/J5*$A$17 -> 56.25 | K17: =K11/K5*$A$17 -> 56.25 | L17: =L11/L5*$A$17 -> 56.25 | ... N17: =N11/N5*$A$17 -> 56.25
B19: Sales Quantity | C19: Ton | E19: =E11+E13-E14+E16-E17 -> 202.5 | F19: =F11+F13-F14+F16-F17 -> 1248.75 | G19: =G11+G13-G14+G16-G17 -> 1597.5 | H19: =H11+H13-H14+H16-H17 -> 1957.5 | I19: =I11+I13-I14+I16-I17 -> 2317.5 | J19: =J11+J13-J14+J16-J17 -> 2677.5 | K19: =K11+K13-K14+K16-K17 -> 2700 | L19: =L11+L13-L14+L16-L17 -> 2700 | ... N19: =N11+N13-N14+N16-N17 -> 2700
B21: Raw Material Requirement
B22: Steel | C22: Ton | E22: =E11*Assumptions!$D$90 -> 302.4 | F22: =F11*Assumptions!$D$90 -> 1411.2 | G22: =G11*Assumptions!$D$90 -> 1814.4 | H22: =H11*Assumptions!$D$90 -> 2217.6 | I22: =I11*Assumptions!$D$90 -> 2620.8 | J22: =J11*Assumptions!$D$90 -> 3024 | K22: =K11*Assumptions!$D$90 -> 3024 | L22: =L11*Assumptions!$D$90 -> 3024 | ... N22: =N11*Assumptions!$D$90 -> 3024
B23: (Scrap Generation) | C23: Ton | D23: 0.09 | E23: =E22*$D$23 -> 27.216 | F23: =F22*$D$23 -> 127.008 | G23: =G22*$D$23 -> 163.296 | H23: =H22*$D$23 -> 199.584 | I23: =I22*$D$23 -> 235.872 | J23: =J22*$D$23 -> 272.16 | K23: =K22*$D$23 -> 272.16 | L23: =L22*$D$23 -> 272.16 | ... N23: =N22*$D$23 -> 272.16
B25: Sales of Electroforged Gratings | C25: INR Lacs | E25: =E19*Assumptions!$D$108/Lacs -> 155.925 | F25: =F19*Assumptions!$D$108/Lacs -> 961.5375 | G25: =G19*Assumptions!$D$108/Lacs -> 1230.075 | H25: =H19*Assumptions!$D$108/Lacs -> 1507.275 | I25: =I19*Assumptions!$D$108/Lacs -> 1784.475 | J25: =J19*Assumptions!$D$108/Lacs -> 2061.675 | K25: =K19*Assumptions!$D$108/Lacs -> 2079 | L25: =L19*Assumptions!$D$108/Lacs -> 2079 | ... N25: =N19*Assumptions!$D$108/Lacs -> 2079
B26: Scrap Sales | C26: INR Lacs | E26: =E23*Assumptions!$D$109/Lacs -> 4.96692 | F26: =F23*Assumptions!$D$109/Lacs -> 23.17896 | G26: =G23*Assumptions!$D$109/Lacs -> 29.80152 | H26: =H23*Assumptions!$D$109/Lacs -> 36.42408 | I26: =I23*Assumptions!$D$109/Lacs -> 43.04664 | J26: =J23*Assumptions!$D$109/Lacs -> 49.6692 | K26: =K23*Assumptions!$D$109/Lacs -> 49.6692 | L26: =L23*Assumptions!$D$109/Lacs -> 49.6692 | ... N26: =N23*Assumptions!$D$109/Lacs -> 49.6692
B27: Clamp and Hardware Sales | C27: INR Lacs
B28: Sales | C28: INR Lacs | E28: =SUM(E25:E27) -> 160.89192 | F28: =SUM(F25:F27) -> 984.71646 | G28: =SUM(G25:G27) -> 1259.8765 | H28: =SUM(H25:H27) -> 1543.6991 | I28: =SUM(I25:I27) -> 1827.5216 | J28: =SUM(J25:J27) -> 2111.3442 | K28: =SUM(K25:K27) -> 2128.6692 | L28: =SUM(L25:L27) -> 2128.6692 | ... N28: =SUM(N25:N27) -> 2128.6692
B30: Raw Material Cost | C30: INR Lacs | E30: =E22*Assumptions!$E$90/Lacs -> 110.376 | F30: =F22*Assumptions!$E$90/Lacs -> 515.088 | G30: =G22*Assumptions!$E$90/Lacs -> 662.256 | H30: =H22*Assumptions!$E$90/Lacs -> 809.424 | I30: =I22*Assumptions!$E$90/Lacs -> 956.592 | J30: =J22*Assumptions!$E$90/Lacs -> 1103.76 | K30: =K22*Assumptions!$E$90/Lacs -> 1103.76 | L30: =L22*Assumptions!$E$90/Lacs -> 1103.76 | ... N30: =N22*Assumptions!$E$90/Lacs -> 1103.76
B31: Galv. Charges | C31: INR Lacs | E31: =E11*Assumptions!$F$92/Lacs -> 45.738 | F31: =F11*Assumptions!$F$92/Lacs -> 213.444 | G31: =G11*Assumptions!$F$92/Lacs -> 274.428 | H31: =H11*Assumptions!$F$92/Lacs -> 335.412 | I31: =I11*Assumptions!$F$92/Lacs -> 396.396 | J31: =J11*Assumptions!$F$92/Lacs -> 457.38 | K31: =K11*Assumptions!$F$92/Lacs -> 457.38 | L31: =L11*Assumptions!$F$92/Lacs -> 457.38 | ... N31: =N11*Assumptions!$F$92/Lacs -> 457.38
B32: MSEB Electricity | C32: INR Lacs | E32: =E11*Assumptions!$F$93/Lacs -> 5.184 | F32: =F11*Assumptions!$F$93/Lacs -> 24.192 | G32: =G11*Assumptions!$F$93/Lacs -> 31.104 | H32: =H11*Assumptions!$F$93/Lacs -> 38.016 | I32: =I11*Assumptions!$F$93/Lacs -> 44.928 | J32: =J11*Assumptions!$F$93/Lacs -> 51.84 | K32: =K11*Assumptions!$F$93/Lacs -> 51.84 | L32: =L11*Assumptions!$F$93/Lacs -> 51.84 | ... N32: =N11*Assumptions!$F$93/Lacs -> 51.84
B33: Fabrication Cost | C33: INR Lacs | E33: =E11*Assumptions!$F$94/Lacs -> 8.1 | F33: =F11*Assumptions!$F$94/Lacs -> 37.8 | G33: =G11*Assumptions!$F$94/Lacs -> 48.6 | H33: =H11*Assumptions!$F$94/Lacs -> 59.4 | I33: =I11*Assumptions!$F$94/Lacs -> 70.2 | J33: =J11*Assumptions!$F$94/Lacs -> 81 | K33: =K11*Assumptions!$F$94/Lacs -> 81 | L33: =L11*Assumptions!$F$94/Lacs -> 81 | ... N33: =N11*Assumptions!$F$94/Lacs -> 81
B34: Consumable | C34: INR Lacs | E34: =E11*Assumptions!$F$95/Lacs -> 4.158 | F34: =F11*Assumptions!$F$95/Lacs -> 19.404 | G34: =G11*Assumptions!$F$95/Lacs -> 24.948 | H34: =H11*Assumptions!$F$95/Lacs -> 30.492 | I34: =I11*Assumptions!$F$95/Lacs -> 36.036 | J34: =J11*Assumptions!$F$95/Lacs -> 41.58 | K34: =K11*Assumptions!$F$95/Lacs -> 41.58 | L34: =L11*Assumptions!$F$95/Lacs -> 41.58 | ... N34: =N11*Assumptions!$F$95/Lacs -> 41.58
B35: Testing & Maint | C35: INR Lacs | E35: =E11*Assumptions!$F$96/Lacs -> 2.079 | F35: =F11*Assumptions!$F$96/Lacs -> 9.702 | G35: =G11*Assumptions!$F$96/Lacs -> 12.474 | H35: =H11*Assumptions!$F$96/Lacs -> 15.246 | I35: =I11*Assumptions!$F$96/Lacs -> 18.018 | J35: =J11*Assumptions!$F$96/Lacs -> 20.79 | K35: =K11*Assumptions!$F$96/Lacs -> 20.79 | L35: =L11*Assumptions!$F$96/Lacs -> 20.79 | ... N35: =N11*Assumptions!$F$96/Lacs -> 20.79
B36: Salaries & Wages | C36: INR Lacs | E36: =Assumptions!E102*Assumptions!E83 -> 9.57 | F36: =Assumptions!F102*Assumptions!F83 -> 40.194 | G36: =Assumptions!G102*Assumptions!G83 -> 42.2037 | H36: =Assumptions!H102*Assumptions!H83 -> 44.313885 | I36: =Assumptions!I102*Assumptions!I83 -> 46.529579 | J36: =Assumptions!J102*Assumptions!J83 -> 48.856058 | K36: =Assumptions!K102*Assumptions!K83 -> 51.298861 | L36: =Assumptions!L102*Assumptions!L83 -> 53.863804 | ... N36: =Assumptions!N102*Assumptions!N83 -> 59.384844
B37: Factory Rent | C37: INR Lacs | E37: =Assumptions!D99/12*Assumptions!E83 -> 4.5 | F37: =Assumptions!D99*(1+Assumptions!E99) -> 19.8 | G37: =F37*(1+Assumptions!$E$99) -> 21.78 | H37: =G37*(1+Assumptions!$E$99) -> 23.958 | I37: =H37*(1+Assumptions!$E$99) -> 26.3538 | J37: =I37*(1+Assumptions!$E$99) -> 28.98918 | K37: =J37*(1+Assumptions!$E$99) -> 31.888098 | L37: =K37*(1+Assumptions!$E$99) -> 35.076908 | M37: =L37*(1+Assumptions!$E$99) -> 38.584599 | N37: =M37*(1+Assumptions!$E$99) -> 42.443058
B38: Total Manufacturing Expenses | C38: INR Lacs | E38: =SUM(E30:E37) -> 189.705 | F38: =SUM(F30:F37) -> 879.624 | G38: =SUM(G30:G37) -> 1117.7937 | H38: =SUM(H30:H37) -> 1356.2619 | I38: =SUM(I30:I37) -> 1595.0534 | J38: =SUM(J30:J37) -> 1834.1952 | K38: =SUM(K30:K37) -> 1839.537 | L38: =SUM(L30:L37) -> 1845.2907 | ... N38: =SUM(N30:N37) -> 1858.1779
B39: Manufacturing Cost per Unit | C39: INR per Ton | E39: =E38*Lacs/E11 -> 70261.111 | F39: =F38*Lacs/F11 -> 69811.429 | G39: =G38*Lacs/G11 -> 68999.611 | H39: =H38*Lacs/H11 -> 68498.075 | I39: =I38*Lacs/I11 -> 68164.674 | J39: =J38*Lacs/J11 -> 67933.157 | K39: =K38*Lacs/K11 -> 68130.998 | L39: =L38*Lacs/L11 -> 68344.1 | ... N39: =N38*Lacs/N11 -> 68821.404
B41: WIP Opening | E41: 0 | F41: =E42 -> 25.294 | G41: =F42 -> 29.3208 | H41: =G42 -> 37.25979 | I41: =H42 -> 45.20873 | J41: =I42 -> 53.168446 | K41: =J42 -> 61.139841 | L41: =K42 -> 61.317899 | M41: =L42 -> 61.50969 | N41: =M42 -> 61.716386
B42: WIP Closing | E42: =E14*E39/Lacs*80% -> 25.294 | F42: =F14*F39/Lacs*80% -> 29.3208 | G42: =G14*G39/Lacs*80% -> 37.25979 | H42: =H14*H39/Lacs*80% -> 45.20873 | I42: =I14*I39/Lacs*80% -> 53.168446 | J42: =J14*J39/Lacs*80% -> 61.139841 | K42: =K14*K39/Lacs*80% -> 61.317899 | L42: =L14*L39/Lacs*80% -> 61.50969 | ... N42: =N14*N39/Lacs*80% -> 61.939263
B44: Cost of Production | C44: INR Lacs | E44: =E38+E41-E42 -> 164.411 | F44: =F38+F41-F42 -> 875.5972 | G44: =G38+G41-G42 -> 1109.8547 | H44: =H38+H41-H42 -> 1348.3129 | I44: =I38+I41-I42 -> 1587.0937 | J44: =J38+J41-J42 -> 1826.2238 | K44: =K38+K41-K42 -> 1839.3589 | L44: =L38+L41-L42 -> 1845.0989 | ... N44: =N38+N41-N42 -> 1857.955
B47: Total Expenses per Unit
B49: FG Opening | F49: =E50 -> 15.80875 | G49: =F50 -> 18.3255 | H49: =G50 -> 23.287369 | I49: =H50 -> 28.255456 | J49: =I50 -> 33.230279 | K49: =J50 -> 38.212401 | L49: =K50 -> 38.323687 | M49: =L50 -> 38.443556 | N49: =M50 -> 38.572742
B50: FG Closing | E50: =E17*E39/Lacs -> 15.80875 | F50: =F17*F39/Lacs -> 18.3255 | G50: =G17*G39/Lacs -> 23.287369 | H50: =H17*H39/Lacs -> 28.255456 | I50: =I17*I39/Lacs -> 33.230279 | J50: =J17*J39/Lacs -> 38.212401 | K50: =K17*K39/Lacs -> 38.323687 | L50: =L17*L39/Lacs -> 38.443556 | ... N50: =N17*N39/Lacs -> 38.71204
B52: Cost of Sales | C52: INR Lacs | E52: =E44+E49-E50 -> 148.60225 | F52: =F44+F49-F50 -> 873.08045 | G52: =G44+G49-G50 -> 1104.8928 | H52: =H44+H49-H50 -> 1343.3449 | I52: =I44+I49-I50 -> 1582.1188 | J52: =J44+J49-J50 -> 1821.2417 | K52: =K44+K49-K50 -> 1839.2476 | L52: =L44+L49-L50 -> 1844.9791 | ... N52: =N44+N49-N50 -> 1857.8157
B53: Admin & Selling Expenses | C53: INR Lacs | E53: =E28*Assumptions!E104 -> 4.8267576 | F53: =F28*Assumptions!F104 -> 29.541494 | G53: =G28*Assumptions!G104 -> 37.796296 | H53: =H28*Assumptions!H104 -> 46.310972 | I53: =I28*Assumptions!I104 -> 54.825649 | J53: =J28*Assumptions!J104 -> 63.340326 | K53: =K28*Assumptions!K104 -> 63.860076 | L53: =L28*Assumptions!L104 -> 63.860076 | ... N53: =N28*Assumptions!N104 -> 63.860076
B55: EBITDA | C55: INR Lacs | E55: =E28-E52-E53 -> 7.4629124 | F55: =F28-F52-F53 -> 82.094516 | G55: =G28-G52-G53 -> 117.18738 | H55: =H28-H52-H53 -> 154.04325 | I55: =I28-I52-I53 -> 190.57715 | J55: =J28-J52-J53 -> 226.76215 | K55: =K28-K52-K53 -> 225.56151 | L55: =L28-L52-L53 -> 219.83007 | ... N55: =N28-N52-N53 -> 206.9934
E56: =E55/E28 -> 0.046384631 | F56: =F55/F28 -> 0.083368685 | G56: =G55/G28 -> 0.093014975 | H56: =H55/H28 -> 0.099788392 | I56: =I55/I28 -> 0.10428175 | J56: =J55/J28 -> 0.10740179 | K56: =K55/K28 -> 0.10596363 | L56: =L55/L28 -> 0.10327113 | ... N56: =N55/N28 -> 0.097240753

Sheet Depreciation
B2: Depreciation
B4: Depreciation Rates | E4: Amount
C5: SLM (Comp Act) | D5: WDV (IT Act)
B6: Land | C6: =Assumptions!D131 -> 0 | D6: =Assumptions!E131 -> 0 | E6: ='Project Cost'!L5 -> 9.8563851
B7: Factory Building | C7: =Assumptions!D132 -> 0.0317 | D7: =Assumptions!E132 -> 0.1 | E7: ='Project Cost'!L6 -> 0
B8: Non-Factory Building | C8: =Assumptions!D133 -> 0.0317 | D8: =Assumptions!E133 -> 0.1 | E8: ='Project Cost'!L7 -> 0
B9: Plant & Machinery | C9: =Assumptions!D134 -> 0.0633 | D9: =Assumptions!E134 -> 0.15 | E9: ='Project Cost'!L8 -> 124.50171
B10: Utilities & Electrical Equipments | C10: =Assumptions!D135 -> 0.095 | D10: =Assumptions!E135 -> 0.15 | E10: ='Project Cost'!L9 -> 14.525199
B11: Miscellaneous Fixed Assets | C11: =Assumptions!D136 -> 0.095 | D11: =Assumptions!E136 -> 0.15 | E11: ='Project Cost'!L10 -> 0
B12: Vehicle | C12: =Assumptions!D137 -> 0.19 | D12: =Assumptions!E137 -> 0.15 | E12: ='Project Cost'!L11 -> 0
B13: Computer | C13: =Assumptions!D138 -> 0.1583 | D13: =Assumptions!E138 -> 0.6 | E13: ='Project Cost'!L12 -> 1.0375142
B14: Furniture | C14: =Assumptions!D139 -> 0.095 | D14: =Assumptions!E139 -> 0.1 | E14: ='Project Cost'!L13 -> 2.0750284
B15: % of value that can be depreciated | C15: =Assumptions!D140 -> 0.95 | D15: =Assumptions!E140 -> -
E16: =SUM(E6:E15) -> 151.99583
B18: Accounting Depreciation | C18: (SLM)
B19: FY Ending | E19: =Assumptions!E82 -> 44286 | F19: =Assumptions!F82 -> 44651 | G19: =Assumptions!G82 -> 45016 | H19: =Assumptions!H82 -> 45382 | I19: =Assumptions!I82 -> 45747 | J19: =Assumptions!J82 -> 46112 | K19: =Assumptions!K82 -> 46477 | L19: =Assumptions!L82 -> 46843 | ... N19: =Assumptions!N82 -> 47573
B20: No. of Months | E20: =Assumptions!E83 -> 3 | F20: =Assumptions!F83 -> 12 | G20: =Assumptions!G83 -> 12 | H20: =Assumptions!H83 -> 12 | I20: =Assumptions!I83 -> 12 | J20: =Assumptions!J83 -> 12 | K20: =Assumptions!K83 -> 12 | L20: =Assumptions!L83 -> 12 | ... N20: =Assumptions!N83 -> 12
B22: Land | C22: =C6 -> 0
B23: Opening Block | E23: 0 | F23: =E25 -> 9.8563851 | G23: =F25 -> 9.8563851 | H23: =G25 -> 9.8563851 | I23: =H25 -> 9.8563851 | J23: =I25 -> 9.8563851 | K23: =J25 -> 9.8563851 | L23: =K25 -> 9.8563851 | M23: =L25 -> 9.8563851 | N23: =M25 -> 9.8563851
B24: Additions during the year | E24: =E6 -> 9.8563851
B25: Gross Block | E25: =E23+E24 -> 9.8563851 | F25: =F23+F24 -> 9.8563851 | G25: =G23+G24 -> 9.8563851 | H25: =H23+H24 -> 9.8563851 | I25: =I23+I24 -> 9.8563851 | J25: =J23+J24 -> 9.8563851 | K25: =K23+K24 -> 9.8563851 | L25: =L23+L24 -> 9.8563851 | ... N25: =N23+N24 -> 9.8563851
B26: Block Available for Depreciation | E26: =E25/12*E20 -> 2.4640963 | F26: =F25/12*F20 -> 9.8563851 | G26: =G25/12*G20 -> 9.8563851 | H26: =H25/12*H20 -> 9.8563851 | I26: =I25/12*I20 -> 9.8563851 | J26: =J25/12*J20 -> 9.8563851 | K26: =K25/12*K20 -> 9.8563851 | L26: =L25/12*L20 -> 9.8563851 | ... N26: =N25/12*N20 -> 9.8563851
B27: Depreciation | E27: =E26*$C$6 -> 0 | F27: =F26*$C$6 -> 0 | G27: =G26*$C$6 -> 0 | H27: =H26*$C$6 -> 0 | I27: =I26*$C$6 -> 0 | J27: =J26*$C$6 -> 0 | K27: =K26*$C$6 -> 0 | L27: =L26*$C$6 -> 0 | ... N27: =N26*$C$6 -> 0
B28: Accumulated Depreciation | E28: =D28+E27 -> 0 | F28: =E28+F27 -> 0 | G28: =F28+G27 -> 0 | H28: =G28+H27 -> 0 | I28: =H28+I27 -> 0 | J28: =I28+J27 -> 0 | K28: =J28+K27 -> 0 | L28: =K28+L27 -> 0 | ... N28: =M28+N27 -> 0
B29: Net Block | E29: =E25-E28 -> 9.8563851 | F29: =F25-F28 -> 9.8563851 | G29: =G25-G28 -> 9.8563851 | H29: =H25-H28 -> 9.8563851 | I29: =I25-I28 -> 9.8563851 | J29: =J25-J28 -> 9.8563851 | K29: =K25-K28 -> 9.8563851 | L29: =L25-L28 -> 9.8563851 | ... N29: =N25-N28 -> 9.8563851
B31: Factory Building | C31: =C7 -> 0.0317
B32: Opening Block
B33: Additions during the year
B34: Gross Block
B35: Block Available for Depreciation
B36: Depreciation
B37: Accumulated Depreciation
B38: Net Block
B40: Non-Factory Building | C40: =C8 -> 0.0317
B41: Opening Block
B42: Additions during the year
B43: Gross Block
B44: Block Available for Depreciation
B45: Depreciation
B46: Accumulated Depreciation
B47: Net Block
B49: Plant & Machinery | C49: =C9 -> 0.0633
B50: Opening Block | E50: 0 | F50: =E52 -> 124.50171 | G50: =F52 -> 124.50171 | H50: =G52 -> 124.50171 | I50: =H52 -> 124.50171 | J50: =I52 -> 124.50171 | K50: =J52 -> 124.50171 | L50: =K52 -> 124.50171 | M50: =L52 -> 124.50171 | N50: =M52 -> 124.50171
B51: Additions during the year | E51: =E9 -> 124.50171
B52: Gross Block | E52: =E50+E51 -> 124.50171 | F52: =F50+F51 -> 124.50171 | G52: =G50+G51 -> 124.50171 | H52: =H50+H51 -> 124.50171 | I52: =I50+I51 -> 124.50171 | J52: =J50+J51 -> 124.50171 | K52: =K50+K51 -> 124.50171 | L52: =L50+L51 -> 124.50171 | ... N52: =N50+N51 -> 124.50171
B53: Block Available for Depreciation | E53: =E52/12*E20 -> 31.125427 | F53: =F52/12*F20 -> 124.50171 | G53: =G52/12*G20 -> 124.50171 | H53: =H52/12*H20 -> 124.50171 | I53: =I52/12*I20 -> 124.50171 | J53: =J52/12*J20 -> 124.50171 | K53: =K52/12*K20 -> 124.50171 | L53: =L52/12*L20 -> 124.50171 | ... N53: =N52/12*N20 -> 124.50171
B54: Depreciation | E54: =E53*$C$9 -> 1.9702395 | F54: =F53*$C$9 -> 7.880958 | G54: =G53*$C$9 -> 7.880958 | H54: =H53*$C$9 -> 7.880958 | I54: =I53*$C$9 -> 7.880958 | J54: =J53*$C$9 -> 7.880958 | K54: =K53*$C$9 -> 7.880958 | L54: =L53*$C$9 -> 7.880958 | ... N54: =N53*$C$9 -> 7.880958
B55: Accumulated Depreciation | E55: =D55+E54 -> 1.9702395 | F55: =E55+F54 -> 9.8511975 | G55: =F55+G54 -> 17.732156 | H55: =G55+H54 -> 25.613114 | I55: =H55+I54 -> 33.494072 | J55: =I55+J54 -> 41.37503 | K55: =J55+K54 -> 49.255988 | L55: =K55+L54 -> 57.136946 | ... N55: =M55+N54 -> 72.898862
B56: Net Block | E56: =E52-E55 -> 122.53147 | F56: =F52-F55 -> 114.65051 | G56: =G52-G55 -> 106.76955 | H56: =H52-H55 -> 98.888593 | I56: =I52-I55 -> 91.007635 | J56: =J52-J55 -> 83.126677 | K56: =K52-K55 -> 75.245719 | L56: =L52-L55 -> 67.364761 | ... N56: =N52-N55 -> 51.602845
B59: Utilities & Electrical Equipments | C59: =C10 -> 0.095
B60: Opening Block | E60: 0 | F60: =E62 -> 14.525199 | G60: =F62 -> 14.525199 | H60: =G62 -> 14.525199 | I60: =H62 -> 14.525199 | J60: =I62 -> 14.525199 | K60: =J62 -> 14.525199 | L60: =K62 -> 14.525199 | M60: =L62 -> 14.525199 | N60: =M62 -> 14.525199
B61: Additions during the year | E61: =E10 -> 14.525199
B62: Gross Block | E62: =E60+E61 -> 14.525199 | F62: =F60+F61 -> 14.525199 | G62: =G60+G61 -> 14.525199 | H62: =H60+H61 -> 14.525199 | I62: =I60+I61 -> 14.525199 | J62: =J60+J61 -> 14.525199 | K62: =K60+K61 -> 14.525199 | L62: =L60+L61 -> 14.525199 | ... N62: =N60+N61 -> 14.525199
B63: Block Available for Depreciation | E63: =E62/12*E20 -> 3.6312998 | F63: =F62/12*F20 -> 14.525199 | G63: =G62/12*G20 -> 14.525199 | H63: =H62/12*H20 -> 14.525199 | I63: =I62/12*I20 -> 14.525199 | J63: =J62/12*J20 -> 14.525199 | K63: =K62/12*K20 -> 14.525199 | L63: =L62/12*L20 -> 14.525199 | ... N63: =N62/12*N20 -> 14.525199
B64: Depreciation | E64: =E63*$C$59 -> 0.34497348 | F64: =F63*$C$59 -> 1.3798939 | G64: =G63*$C$59 -> 1.3798939 | H64: =H63*$C$59 -> 1.3798939 | I64: =I63*$C$59 -> 1.3798939 | J64: =J63*$C$59 -> 1.3798939 | K64: =K63*$C$59 -> 1.3798939 | L64: =L63*$C$59 -> 1.3798939 | ... N64: =N63*$C$59 -> 1.3798939
B65: Accumulated Depreciation | E65: =D65+E64 -> 0.34497348 | F65: =E65+F64 -> 1.7248674 | G65: =F65+G64 -> 3.1047613 | H65: =G65+H64 -> 4.4846552 | I65: =H65+I64 -> 5.8645491 | J65: =I65+J64 -> 7.244443 | K65: =J65+K64 -> 8.624337 | L65: =K65+L64 -> 10.004231 | ... N65: =M65+N64 -> 12.764019
B66: Net Block | E66: =E62-E65 -> 14.180226 | F66: =F62-F65 -> 12.800332 | G66: =G62-G65 -> 11.420438 | H66: =H62-H65 -> 10.040544 | I66: =I62-I65 -> 8.66065 | J66: =J62-J65 -> 7.280756 | K66: =K62-K65 -> 5.9008621 | L66: =L62-L65 -> 4.5209682 | ... N66: =N62-N65 -> 1.7611804
B68: Miscellaneous Fixed Assets | C68: =C11 -> 0.095
B69: Opening Block
B70: Additions during the year
B71: Gross Block
B72: Block Available for Depreciation
B73: Depreciation
B74: Accumulated Depreciation
B75: Net Block
B77: Vehicle | C77: =C12 -> 0.19
B78: Opening Block
B79: Additions during the year
B80: Gross Block
B81: Block Available for Depreciation
B82: Depreciation
B83: Accumulated Depreciation
B84: Net Block
B87: Computer | C87: =C13 -> 0.1583
B88: Opening Block | E88: 0 | F88: =E90 -> 1.0375142 | G88: =F90 -> 1.0375142 | H88: =G90 -> 1.0375142 | I88: =H90 -> 1.0375142 | J88: =I90 -> 1.0375142 | K88: =J90 -> 1.0375142 | L88: =K90 -> 1.0375142 | M88: =L90 -> 1.0375142 | N88: =M90 -> 1.0375142
B89: Additions during the year | E89: =E13 -> 1.0375142
B90: Gross Block | E90: =E88+E89 -> 1.0375142 | F90: =F88+F89 -> 1.0375142 | G90: =G88+G89 -> 1.0375142 | H90: =H88+H89 -> 1.0375142 | I90: =I88+I89 -> 1.0375142 | J90: =J88+J89 -> 1.0375142 | K90: =K88+K89 -> 1.0375142 | L90: =L88+L89 -> 1.0375142 | ... N90: =N88+N89 -> 1.0375142
B91: Block Available for Depreciation | E91: =E90/12*E20 -> 0.25937856 | F91: =F90/12*F20 -> 1.0375142 | G91: =G90/12*G20 -> 1.0375142 | H91: =H90/12*H20 -> 1.0375142 | I91: =I90/12*I20 -> 1.0375142 | J91: =J90/12*J20 -> 1.0375142 | K91: =K90/12*K20 -> 1.0375142 | L91: =L90/12*L20 -> 1.0375142 | ... N91: =N90/12*N20 -> 1.0375142
B92: Depreciation | E92: =E91*$C$87 -> 0.041059625 | F92: =F91*$C$87 -> 0.1642385 | G92: =G91*$C$87 -> 0.1642385 | H92: =H91*$C$87 -> 0.1642385 | I92: =I91*$C$87 -> 0.1642385 | J92: =J91*$C$87 -> 0.1642385 | K92: =K91*$C$87 -> 0.1642385 | L92: =MIN(L91*$C$87,K94) -> 0.011023589 | M92: =MIN(M91*$C$87,L94) -> 0 | N92: =MIN(N91*$C$87,M94) -> 0
B93: Accumulated Depreciation | E93: =D93+E92 -> 0.041059625 | F93: =E93+F92 -> 0.20529813 | G93: =F93+G92 -> 0.36953663 | H93: =G93+H92 -> 0.53377513 | I93: =H93+I92 -> 0.69801363 | J93: =I93+J92 -> 0.86225213 | K93: =J93+K92 -> 1.0264906 | L93: =K93+L92 -> 1.0375142 | ... N93: =M93+N92 -> 1.0375142
B94: Net Block | E94: =E90-E93 -> 0.9964546 | F94: =F90-F93 -> 0.83221609 | G94: =G90-G93 -> 0.66797759 | H94: =H90-H93 -> 0.50373909 | I94: =I90-I93 -> 0.33950059 | J94: =J90-J93 -> 0.17526209 | K94: =K90-K93 -> 0.011023589 | L94: =L90-L93 -> 0 | ... N94: =N90-N93 -> 0
B97: Furniture | C97: =C14 -> 0.095
B98: Opening Block | E98: 0 | F98: =E100 -> 2.0750284 | G98: =F100 -> 2.0750284 | H98: =G100 -> 2.0750284 | I98: =H100 -> 2.0750284 | J98: =I100 -> 2.0750284 | K98: =J100 -> 2.0750284 | L98: =K100 -> 2.0750284 | M98: =L100 -> 2.0750284 | N98: =M100 -> 2.0750284
B99: Additions during the year | E99: =E14 -> 2.0750284
B100: Gross Block | E100: =E98+E99 -> 2.0750284 | F100: =F98+F99 -> 2.0750284 | G100: =G98+G99 -> 2.0750284 | H100: =H98+H99 -> 2.0750284 | I100: =I98+I99 -> 2.0750284 | J100: =J98+J99 -> 2.0750284 | K100: =K98+K99 -> 2.0750284 | L100: =L98+L99 -> 2.0750284 | ... N100: =N98+N99 -> 2.0750284
B101: Block Available for Depreciation | E101: =E100/12*E20 -> 0.51875711 | F101: =F100/12*F20 -> 2.0750284 | G101: =G100/12*G20 -> 2.0750284 | H101: =H100/12*H20 -> 2.0750284 | I101: =I100/12*I20 -> 2.0750284 | J101: =J100/12*J20 -> 2.0750284 | K101: =K100/12*K20 -> 2.0750284 | L101: =L100/12*L20 -> 2.0750284 | ... N101: =N100/12*N20 -> 2.0750284
B102: Depreciation | E102: =E101*$C$97 -> 0.049281925 | F102: =F101*$C$97 -> 0.1971277 | G102: =G101*$C$97 -> 0.1971277 | H102: =H101*$C$97 -> 0.1971277 | I102: =I101*$C$97 -> 0.1971277 | J102: =J101*$C$97 -> 0.1971277 | K102: =K101*$C$97 -> 0.1971277 | L102: =L101*$C$97 -> 0.1971277 | ... N102: =N101*$C$97 -> 0.1971277
B103: Accumulated Depreciation | E103: =D103+E102 -> 0.049281925 | F103: =E103+F102 -> 0.24640963 | G103: =F103+G102 -> 0.44353733 | H103: =G103+H102 -> 0.64066503 | I103: =H103+I102 -> 0.83779273 | J103: =I103+J102 -> 1.0349204 | K103: =J103+K102 -> 1.2320481 | L103: =K103+L102 -> 1.4291758 | ... N103: =M103+N102 -> 1.8234312
B104: Net Block | E104: =E100-E103 -> 2.0257465 | F104: =F100-F103 -> 1.8286188 | G104: =G100-G103 -> 1.6314911 | H104: =H100-H103 -> 1.4343634 | I104: =I100-I103 -> 1.2372357 | J104: =J100-J103 -> 1.040108 | K104: =K100-K103 -> 0.8429803 | L104: =L100-L103 -> 0.6458526 | ... N104: =N100-N103 -> 0.2515972
B107: All Assets
B108: Opening Block | E108: =E98+E88+E60+E50+E23 -> 0 | F108: =F98+F88+F60+F50+F23 -> 151.99583 | G108: =G98+G88+G60+G50+G23 -> 151.99583 | H108: =H98+H88+H60+H50+H23 -> 151.99583 | I108: =I98+I88+I60+I50+I23 -> 151.99583 | J108: =J98+J88+J60+J50+J23 -> 151.99583 | K108: =K98+K88+K60+K50+K23 -> 151.99583 | L108: =L98+L88+L60+L50+L23 -> 151.99583 | ... N108: =N98+N88+N60+N50+N23 -> 151.99583
B109: Additions during the year | E109: =E99+E89+E61+E51+E24 -> 151.99583 | F109: =F99+F89+F61+F51+F24 -> 0 | G109: =G99+G89+G61+G51+G24 -> 0 | H109: =H99+H89+H61+H51+H24 -> 0 | I109: =I99+I89+I61+I51+I24 -> 0 | J109: =J99+J89+J61+J51+J24 -> 0 | K109: =K99+K89+K61+K51+K24 -> 0 | L109: =L99+L89+L61+L51+L24 -> 0 | ... N109: =N99+N89+N61+N51+N24 -> 0
B110: Gross Block | E110: =E100+E90+E62+E52+E25 -> 151.99583 | F110: =F100+F90+F62+F52+F25 -> 151.99583 | G110: =G100+G90+G62+G52+G25 -> 151.99583 | H110: =H100+H90+H62+H52+H25 -> 151.99583 | I110: =I100+I90+I62+I52+I25 -> 151.99583 | J110: =J100+J90+J62+J52+J25 -> 151.99583 | K110: =K100+K90+K62+K52+K25 -> 151.99583 | L110: =L100+L90+L62+L52+L25 -> 151.99583 | ... N110: =N100+N90+N62+N52+N25 -> 151.99583
B111: Block Available for Depreciation | E111: =E101+E91+E63+E53+E26 -> 37.998958 | F111: =F101+F91+F63+F53+F26 -> 151.99583 | G111: =G101+G91+G63+G53+G26 -> 151.99583 | H111: =H101+H91+H63+H53+H26 -> 151.99583 | I111: =I101+I91+I63+I53+I26 -> 151.99583 | J111: =J101+J91+J63+J53+J26 -> 151.99583 | K111: =K101+K91+K63+K53+K26 -> 151.99583 | L111: =L101+L91+L63+L53+L26 -> 151.99583 | ... N111: =N101+N91+N63+N53+N26 -> 151.99583
B112: Depreciation | E112: =E102+E92+E64+E54+E27 -> 2.4055545 | F112: =F102+F92+F64+F54+F27 -> 9.6222181 | G112: =G102+G92+G64+G54+G27 -> 9.6222181 | H112: =H102+H92+H64+H54+H27 -> 9.6222181 | I112: =I102+I92+I64+I54+I27 -> 9.6222181 | J112: =J102+J92+J64+J54+J27 -> 9.6222181 | K112: =K102+K92+K64+K54+K27 -> 9.6222181 | L112: =L102+L92+L64+L54+L27 -> 9.4690032 | ... N112: =N102+N92+N64+N54+N27 -> 9.4579796
B113: Accumulated Depreciation | E113: =E103+E93+E65+E55+E28 -> 2.4055545 | F113: =F103+F93+F65+F55+F28 -> 12.027773 | G113: =G103+G93+G65+G55+G28 -> 21.649991 | H113: =H103+H93+H65+H55+H28 -> 31.272209 | I113: =I103+I93+I65+I55+I28 -> 40.894427 | J113: =J103+J93+J65+J55+J28 -> 50.516645 | K113: =K103+K93+K65+K55+K28 -> 60.138863 | L113: =L103+L93+L65+L55+L28 -> 69.607867 | ... N113: =N103+N93+N65+N55+N28 -> 88.523826
B114: Net Block | D114: =D29+D38+D47+D56 -> 0 | E114: =E104+E94+E66+E56+E29 -> 149.59028 | F114: =F104+F94+F66+F56+F29 -> 139.96806 | G114: =G104+G94+G66+G56+G29 -> 130.34584 | H114: =H104+H94+H66+H56+H29 -> 120.72362 | I114: =I104+I94+I66+I56+I29 -> 111.10141 | J114: =J104+J94+J66+J56+J29 -> 101.47919 | K114: =K104+K94+K66+K56+K29 -> 91.85697 | L114: =L104+L94+L66+L56+L29 -> 82.387967 | ... N114: =N104+N94+N66+N56+N29 -> 63.472007
B115: Check | E115: =$E$110-SUM(E103,E93,E83,E74,E65,E55,E46,E37,E28)-E114 -> 0 | F115: =$E$110-SUM(F103,F93,F83,F74,F65,F55,F46,F37,F28)-F114 -> 0 | G115: =$E$110-SUM(G103,G93,G83,G74,G65,G55,G46,G37,G28)-G114 -> 0 | H115: =$E$110-SUM(H103,H93,H83,H74,H65,H55,H46,H37,H28)-H114 -> 0 | I115: =$E$110-SUM(I103,I93,I83,I74,I65,I55,I46,I37,I28)-I114 -> 0 | J115: =$E$110-SUM(J103,J93,J83,J74,J65,J55,J46,J37,J28)-J114 -> 0 | K115: =$E$110-SUM(K103,K93,K83,K74,K65,K55,K46,K37,K28)-K114 -> 0 | L115: =$E$110-SUM(L103,L93,L83,L74,L65,L55,L46,L37,L28)-L114 -> 0 | ... N115: =$E$110-SUM(N103,N93,N83,N74,N65,N55,N46,N37,N28)-N114 -> 0
B118: IT Depreciation
B119: FY Ending | E119: =E19 -> 44286 | F119: =F19 -> 44651 | G119: =G19 -> 45016 | H119: =H19 -> 45382 | I119: =I19 -> 45747 | J119: =J19 -> 46112 | K119: =K19 -> 46477 | L119: =L19 -> 46843 | ... N119: =N19 -> 47573
...

Sheet WC
B2: Working Capital
B4: FY Ending | C4: Norm | E4: =Assumptions!E82 -> 44286 | F4: =Assumptions!F82 -> 44651 | G4: =Assumptions!G82 -> 45016 | H4: =Assumptions!H82 -> 45382 | I4: =Assumptions!I82 -> 45747 | J4: =Assumptions!J82 -> 46112 | K4: =Assumptions!K82 -> 46477 | L4: =Assumptions!L82 -> 46843 | ... N4: =Assumptions!N82 -> 47573
B5: No of months | E5: =Assumptions!E83 -> 3 | F5: =Assumptions!F83 -> 12 | G5: =Assumptions!G83 -> 12 | H5: =Assumptions!H83 -> 12 | I5: =Assumptions!I83 -> 12 | J5: =Assumptions!J83 -> 12 | K5: =Assumptions!K83 -> 12 | L5: =Assumptions!L83 -> 12 | ... N5: =Assumptions!N83 -> 12
B6: Current Assets
B7: Raw Material Inventory | C7: =Assumptions!D117 -> 0.75 | E7: =PL!D14/WC!E5*WC!$C$7 -> 27.594 | F7: =PL!E14/WC!F5*WC!$C$7 -> 32.193 | G7: =PL!F14/WC!G5*WC!$C$7 -> 41.391 | H7: =PL!G14/WC!H5*WC!$C$7 -> 50.589 | I7: =PL!H14/WC!I5*WC!$C$7 -> 59.787 | J7: =PL!I14/WC!J5*WC!$C$7 -> 68.985 | K7: =PL!J14/WC!K5*WC!$C$7 -> 68.985 | L7: =PL!K14/WC!L5*WC!$C$7 -> 68.985 | ... N7: =PL!M14/WC!N5*WC!$C$7 -> 68.985
B8: WIP Inventory | C8: =Assumptions!D118 -> 0.5 | E8: =CoP!E42 -> 25.294 | F8: =CoP!F42 -> 29.3208 | G8: =CoP!G42 -> 37.25979 | H8: =CoP!H42 -> 45.20873 | I8: =CoP!I42 -> 53.168446 | J8: =CoP!J42 -> 61.139841 | K8: =CoP!K42 -> 61.317899 | L8: =CoP!L42 -> 61.50969 | ... N8: =CoP!N42 -> 61.939263
B9: FG Inventory | C9: =Assumptions!D119 -> 0.25 | E9: =CoP!E50 -> 15.80875 | F9: =CoP!F50 -> 18.3255 | G9: =CoP!G50 -> 23.287369 | H9: =CoP!H50 -> 28.255456 | I9: =CoP!I50 -> 33.230279 | J9: =CoP!J50 -> 38.212401 | K9: =CoP!K50 -> 38.323687 | L9: =CoP!L50 -> 38.443556 | ... N9: =CoP!N50 -> 38.71204
B10: Sundry Debtors | C10: =Assumptions!D120 -> 1.5 | E10: =PL!D10/WC!E5*$C$10 -> 80.44596 | F10: =PL!E10/WC!F5*$C$10 -> 123.08956 | G10: =PL!F10/WC!G5*$C$10 -> 157.48457 | H10: =PL!G10/WC!H5*$C$10 -> 192.96239 | I10: =PL!H10/WC!I5*$C$10 -> 228.4402 | J10: =PL!I10/WC!J5*$C$10 -> 263.91803 | K10: =PL!J10/WC!K5*$C$10 -> 266.08365 | L10: =PL!K10/WC!L5*$C$10 -> 266.08365 | ... N10: =PL!M10/WC!N5*$C$10 -> 266.08365
B11: Stores & Spares | C11: =Assumptions!D121 -> 0.01 | E11: =PL!D10*WC!$C$11 -> 1.6089192 | F11: =PL!E10*WC!$C$11 -> 9.8471646 | G11: =PL!F10*WC!$C$11 -> 12.598765 | H11: =PL!G10*WC!$C$11 -> 15.436991 | I11: =PL!H10*WC!$C$11 -> 18.275216 | J11: =PL!I10*WC!$C$11 -> 21.113442 | K11: =PL!J10*WC!$C$11 -> 21.286692 | L11: =PL!K10*WC!$C$11 -> 21.286692 | ... N11: =PL!M10*WC!$C$11 -> 21.286692
B12: Total Current Assets | E12: =SUM(E7:E11) -> 150.75163 | F12: =SUM(F7:F11) -> 212.77602 | G12: =SUM(G7:G11) -> 272.02149 | H12: =SUM(H7:H11) -> 332.45256 | I12: =SUM(I7:I11) -> 392.90115 | J12: =SUM(J7:J11) -> 453.36871 | K12: =SUM(K7:K11) -> 455.99693 | L12: =SUM(L7:L11) -> 456.30859 | ... N12: =SUM(N7:N11) -> 457.00665
B13: Current Liabilities
B14: Creditors on Consumables | C14: =Assumptions!D122 -> 1 | E14: =E27/E5*$C$14 -> 45.99 | F14: =F27/F5*$C$14 -> 43.30725 | G14: =G27/G5*$C$14 -> 55.9545 | H14: =H27/H5*$C$14 -> 68.2185 | I14: =I27/I5*$C$14 -> 80.4825 | J14: =J27/J5*$C$14 -> 92.7465 | K14: =K27/K5*$C$14 -> 91.98 | L14: =L27/L5*$C$14 -> 91.98 | ... N14: =N27/N5*$C$14 -> 91.98
B15: Other Current Liabilities (advance from customers)
B16: Total Current Liabilities | E16: =E14+E15 -> 45.99 | F16: =F14+F15 -> 43.30725 | G16: =G14+G15 -> 55.9545 | H16: =H14+H15 -> 68.2185 | I16: =I14+I15 -> 80.4825 | J16: =J14+J15 -> 92.7465 | K16: =K14+K15 -> 91.98 | L16: =L14+L15 -> 91.98 | ... N16: =N14+N15 -> 91.98
B17: Net Working Capital Gap | E17: =E12-E16 -> 104.76163 | F17: =F12-F16 -> 169.46877 | G17: =G12-G16 -> 216.06699 | H17: =H12-H16 -> 264.23406 | I17: =I12-I16 -> 312.41865 | J17: =J12-J16 -> 360.62221 | K17: =K12-K16 -> 364.01693 | L17: =L12-L16 -> 364.32859 | ... N17: =N12-N16 -> 365.02665
B18: Margin Money for WC | C18: =Assumptions!D126 -> 0.25 | E18: =E17*$C$18 -> 26.190407 | F18: =F17*$C$18 -> 42.367193 | G18: =G17*$C$18 -> 54.016747 | H18: =H17*$C$18 -> 66.058515 | I18: =I17*$C$18 -> 78.104662 | J18: =J17*$C$18 -> 90.155552 | K18: =K17*$C$18 -> 91.004232 | L18: =L17*$C$18 -> 91.082147 | ... N18: =N17*$C$18 -> 91.256661
B19: Bank Finance Available | E19: =E17-E18 -> 78.571222 | F19: =F17-F18 -> 127.10158 | G19: =G17-G18 -> 162.05024 | H19: =H17-H18 -> 198.17555 | I19: =I17-I18 -> 234.31398 | J19: =J17-J18 -> 270.46666 | K19: =K17-K18 -> 273.0127 | L19: =L17-L18 -> 273.24644 | ... N19: =N17-N18 -> 273.76998
B20: Bank Borrowings | E20: =E19 -> 78.571222 | F20: =F19 -> 127.10158 | G20: =G19 -> 162.05024 | H20: =H19 -> 198.17555 | I20: =I19 -> 234.31398 | J20: =J19 -> 270.46666 | K20: =K19 -> 273.0127 | L20: =L19 -> 273.24644 | ... N20: =N19 -> 273.76998
B22: WC Interest | C22: =Assumptions!D125 -> 0.1 | E22: =E20*$C$22/12*E5 -> 1.9642805 | F22: =F20*$C$22/12*F5 -> 12.710158 | G22: =G20*$C$22/12*G5 -> 16.205024 | H22: =H20*$C$22/12*H5 -> 19.817555 | I22: =I20*$C$22/12*I5 -> 23.431398 | J22: =J20*$C$22/12*J5 -> 27.046666 | K22: =K20*$C$22/12*K5 -> 27.30127 | L22: =L20*$C$22/12*L5 -> 27.324644 | ... N22: =N20*$C$22/12*N5 -> 27.376998
B23: Bank Charges | C23: =Assumptions!D124 -> 0.02 | E23: =E20*$C$23 -> 1.5714244 | F23: =F20*$C$23 -> 2.5420316 | G23: =G20*$C$23 -> 3.2410048 | H23: =H20*$C$23 -> 3.9635109 | I23: =I20*$C$23 -> 4.6862797 | J23: =J20*$C$23 -> 5.4093331 | K23: =K20*$C$23 -> 5.4602539 | L23: =L20*$C$23 -> 5.4649288 | ... N23: =N20*$C$23 -> 5.4753997
B25: Raw Material Purchase | E25: =E4 -> 44286 | F25: =F4 -> 44651 | G25: =G4 -> 45016 | H25: =H4 -> 45382 | I25: =I4 -> 45747 | J25: =J4 -> 46112 | K25: =K4 -> 46477 | L25: =L4 -> 46843 | ... N25: =N4 -> 47573
B26: Opening Stock | E26: 0 | F26: =E28 -> 27.594 | G26: =F28 -> 32.193 | H26: =G28 -> 41.391 | I26: =H28 -> 50.589 | J26: =I28 -> 59.787 | K26: =J28 -> 68.985 | L26: =K28 -> 68.985 | M26: =L28 -> 68.985 | N26: =M28 -> 68.985
B27: Purchase | E27: =E29+E28-E26 -> 137.97 | F27: =F29+F28-F26 -> 519.687 | G27: =G29+G28-G26 -> 671.454 | H27: =H29+H28-H26 -> 818.622 | I27: =I29+I28-I26 -> 965.79 | J27: =J29+J28-J26 -> 1112.958 | K27: =K29+K28-K26 -> 1103.76 | L27: =L29+L28-L26 -> 1103.76 | ... N27: =N29+N28-N26 -> 1103.76
B28: Closing Stock | E28: =E7 -> 27.594 | F28: =F7 -> 32.193 | G28: =G7 -> 41.391 | H28: =H7 -> 50.589 | I28: =I7 -> 59.787 | J28: =J7 -> 68.985 | K28: =K7 -> 68.985 | L28: =L7 -> 68.985 | ... N28: =N7 -> 68.985
B29: Consumption | E29: =PL!D14 -> 110.376 | F29: =PL!E14 -> 515.088 | G29: =PL!F14 -> 662.256 | H29: =PL!G14 -> 809.424 | I29: =PL!H14 -> 956.592 | J29: =PL!I14 -> 1103.76 | K29: =PL!J14 -> 1103.76 | L29: =PL!K14 -> 1103.76 | ... N29: =PL!M14 -> 1103.76
B32: Turnover Method of Working Capital Assessment
B33: NWC
B34: 8% of Gross Sales
B35: Max of Both
B37: 33% of Gross Sales
B38: Bank Borrowing
B40: MPBF as per CMA

Sheet PL
B2: Profit & Loss
M3: INR Lacs
B4: FY Ending | C4: =EOMONTH(D4,-12) -> 43921 | D4: =Assumptions!E82 -> 44286 | E4: =Assumptions!F82 -> 44651 | F4: =Assumptions!G82 -> 45016 | G4: =Assumptions!H82 -> 45382 | H4: =Assumptions!I82 -> 45747 | I4: =Assumptions!J82 -> 46112 | J4: =Assumptions!K82 -> 46477 | K4: =Assumptions!L82 -> 46843 | ... M4: =Assumptions!N82 -> 47573
B5: No of months | D5: =Assumptions!E83 -> 3 | E5: =Assumptions!F83 -> 12 | F5: =Assumptions!G83 -> 12 | G5: =Assumptions!H83 -> 12 | H5: =Assumptions!I83 -> 12 | I5: =Assumptions!J83 -> 12 | J5: =Assumptions!K83 -> 12 | K5: =Assumptions!L83 -> 12 | ... M5: =Assumptions!N83 -> 12
B6: Sales of Electroforged Gratings | D6: =CoP!E25 -> 155.925 | E6: =CoP!F25 -> 961.5375 | F6: =CoP!G25 -> 1230.075 | G6: =CoP!H25 -> 1507.275 | H6: =CoP!I25 -> 1784.475 | I6: =CoP!J25 -> 2061.675 | J6: =CoP!K25 -> 2079 | K6: =CoP!L25 -> 2079 | ... M6: =CoP!N25 -> 2079
B7: Scrap Sales | D7: =CoP!E26 -> 4.96692 | E7: =CoP!F26 -> 23.17896 | F7: =CoP!G26 -> 29.80152 | G7: =CoP!H26 -> 36.42408 | H7: =CoP!I26 -> 43.04664 | I7: =CoP!J26 -> 49.6692 | J7: =CoP!K26 -> 49.6692 | K7: =CoP!L26 -> 49.6692 | ... M7: =CoP!N26 -> 49.6692
B8: Clamp and Hardware Sales | D8: =CoP!E27 -> 0 | E8: =CoP!F27 -> 0 | F8: =CoP!G27 -> 0 | G8: =CoP!H27 -> 0 | H8: =CoP!I27 -> 0 | I8: =CoP!J27 -> 0 | J8: =CoP!K27 -> 0 | K8: =CoP!L27 -> 0 | ... M8: =CoP!N27 -> 0
B9: Other Operating Income
B10: Net Sales | D10: =SUM(D6:D9) -> 160.89192 | E10: =SUM(E6:E9) -> 984.71646 | F10: =SUM(F6:F9) -> 1259.8765 | G10: =SUM(G6:G9) -> 1543.6991 | H10: =SUM(H6:H9) -> 1827.5216 | I10: =SUM(I6:I9) -> 2111.3442 | J10: =SUM(J6:J9) -> 2128.6692 | K10: =SUM(K6:K9) -> 2128.6692 | ... M10: =SUM(M6:M9) -> 2128.6692
B11: GST | C11: 0.18
B12: Gross Sales
B13: Expenses
B14: Raw Material Cost | D14: =CoP!E30 -> 110.376 | E14: =CoP!F30 -> 515.088 | F14: =CoP!G30 -> 662.256 | G14: =CoP!H30 -> 809.424 | H14: =CoP!I30 -> 956.592 | I14: =CoP!J30 -> 1103.76 | J14: =CoP!K30 -> 1103.76 | K14: =CoP!L30 -> 1103.76 | ... M14: =CoP!N30 -> 1103.76
B15: Galv. Charges | D15: =CoP!E31 -> 45.738 | E15: =CoP!F31 -> 213.444 | F15: =CoP!G31 -> 274.428 | G15: =CoP!H31 -> 335.412 | H15: =CoP!I31 -> 396.396 | I15: =CoP!J31 -> 457.38 | J15: =CoP!K31 -> 457.38 | K15: =CoP!L31 -> 457.38 | ... M15: =CoP!N31 -> 457.38
B16: Power Cost | D16: =CoP!E32 -> 5.184 | E16: =CoP!F32 -> 24.192 | F16: =CoP!G32 -> 31.104 | G16: =CoP!H32 -> 38.016 | H16: =CoP!I32 -> 44.928 | I16: =CoP!J32 -> 51.84 | J16: =CoP!K32 -> 51.84 | K16: =CoP!L32 -> 51.84 | ... M16: =CoP!N32 -> 51.84
B17: Fabrication Cost | D17: =CoP!E33 -> 8.1 | E17: =CoP!F33 -> 37.8 | F17: =CoP!G33 -> 48.6 | G17: =CoP!H33 -> 59.4 | H17: =CoP!I33 -> 70.2 | I17: =CoP!J33 -> 81 | J17: =CoP!K33 -> 81 | K17: =CoP!L33 -> 81 | ... M17: =CoP!N33 -> 81
B18: Consumable | D18: =CoP!E34 -> 4.158 | E18: =CoP!F34 -> 19.404 | F18: =CoP!G34 -> 24.948 | G18: =CoP!H34 -> 30.492 | H18: =CoP!I34 -> 36.036 | I18: =CoP!J34 -> 41.58 | J18: =CoP!K34 -> 41.58 | K18: =CoP!L34 -> 41.58 | ... M18: =CoP!N34 -> 41.58
B19: Testing & Maint | D19: =CoP!E35 -> 2.079 | E19: =CoP!F35 -> 9.702 | F19: =CoP!G35 -> 12.474 | G19: =CoP!H35 -> 15.246 | H19: =CoP!I35 -> 18.018 | I19: =CoP!J35 -> 20.79 | J19: =CoP!K35 -> 20.79 | K19: =CoP!L35 -> 20.79 | ... M19: =CoP!N35 -> 20.79
B20: Salaries & Wages | D20: =CoP!E36 -> 9.57 | E20: =CoP!F36 -> 40.194 | F20: =CoP!G36 -> 42.2037 | G20: =CoP!H36 -> 44.313885 | H20: =CoP!I36 -> 46.529579 | I20: =CoP!J36 -> 48.856058 | J20: =CoP!K36 -> 51.298861 | K20: =CoP!L36 -> 53.863804 | ... M20: =CoP!N36 -> 59.384844
B21: Factory Rent | D21: =CoP!E37 -> 4.5 | E21: =CoP!F37 -> 19.8 | F21: =CoP!G37 -> 21.78 | G21: =CoP!H37 -> 23.958 | H21: =CoP!I37 -> 26.3538 | I21: =CoP!J37 -> 28.98918 | J21: =CoP!K37 -> 31.888098 | K21: =CoP!L37 -> 35.076908 | ... M21: =CoP!N37 -> 42.443058
B22: Other Operating Expenses
B23: Total Manufacturing Expenses | D23: =SUM(D14:D22) -> 189.705 | E23: =SUM(E14:E22) -> 879.624 | F23: =SUM(F14:F22) -> 1117.7937 | G23: =SUM(G14:G22) -> 1356.2619 | H23: =SUM(H14:H22) -> 1595.0534 | I23: =SUM(I14:I22) -> 1834.1952 | J23: =SUM(J14:J22) -> 1839.537 | K23: =SUM(K14:K22) -> 1845.2907 | ... M23: =SUM(M14:M22) -> 1858.1779
B24: WIP Opening | D24: =CoP!E41 -> 0 | E24: =CoP!F41 -> 25.294 | F24: =CoP!G41 -> 29.3208 | G24: =CoP!H41 -> 37.25979 | H24: =CoP!I41 -> 45.20873 | I24: =CoP!J41 -> 53.168446 | J24: =CoP!K41 -> 61.139841 | K24: =CoP!L41 -> 61.317899 | ... M24: =CoP!N41 -> 61.716386
B25: WIP Closing | D25: =CoP!E42 -> 25.294 | E25: =CoP!F42 -> 29.3208 | F25: =CoP!G42 -> 37.25979 | G25: =CoP!H42 -> 45.20873 | H25: =CoP!I42 -> 53.168446 | I25: =CoP!J42 -> 61.139841 | J25: =CoP!K42 -> 61.317899 | K25: =CoP!L42 -> 61.50969 | ... M25: =CoP!N42 -> 61.939263
B26: Cost of Production | D26: =D23+D24-D25 -> 164.411 | E26: =E23+E24-E25 -> 875.5972 | F26: =F23+F24-F25 -> 1109.8547 | G26: =G23+G24-G25 -> 1348.3129 | H26: =H23+H24-H25 -> 1587.0937 | I26: =I23+I24-I25 -> 1826.2238 | J26: =J23+J24-J25 -> 1839.3589 | K26: =K23+K24-K25 -> 1845.0989 | ... M26: =M23+M24-M25 -> 1857.955
B27: Admin & Selling Expenses | D27: =CoP!E53 -> 4.8267576 | E27: =CoP!F53 -> 29.541494 | F27: =CoP!G53 -> 37.796296 | G27: =CoP!H53 -> 46.310972 | H27: =CoP!I53 -> 54.825649 | I27: =CoP!J53 -> 63.340326 | J27: =CoP!K53 -> 63.860076 | K27: =CoP!L53 -> 63.860076 | ... M27: =CoP!N53 -> 63.860076
B28: FG Opening | D28: =CoP!E49 -> 0 | E28: =CoP!F49 -> 15.80875 | F28: =CoP!G49 -> 18.3255 | G28: =CoP!H49 -> 23.287369 | H28: =CoP!I49 -> 28.255456 | I28: =CoP!J49 -> 33.230279 | J28: =CoP!K49 -> 38.212401 | K28: =CoP!L49 -> 38.323687 | ... M28: =CoP!N49 -> 38.572742
B29: FG Closing | D29: =CoP!E50 -> 15.80875 | E29: =CoP!F50 -> 18.3255 | F29: =CoP!G50 -> 23.287369 | G29: =CoP!H50 -> 28.255456 | H29: =CoP!I50 -> 33.230279 | I29: =CoP!J50 -> 38.212401 | J29: =CoP!K50 -> 38.323687 | K29: =CoP!L50 -> 38.443556 | ... M29: =CoP!N50 -> 38.71204
B30: Cost of Goods Sold | D30: =D26+D27+D28-D29 -> 153.42901 | E30: =E26+E27+E28-E29 -> 902.62194 | F30: =F26+F27+F28-F29 -> 1142.6891 | G30: =G26+G27+G28-G29 -> 1389.6558 | H30: =H26+H27+H28-H29 -> 1636.9445 | I30: =I26+I27+I28-I29 -> 1884.582 | J30: =J26+J27+J28-J29 -> 1903.1077 | K30: =K26+K27+K28-K29 -> 1908.8391 | ... M30: =M26+M27+M28-M29 -> 1921.6758
B31: EBITDA | D31: =D10-D30 -> 7.4629124 | E31: =E10-E30 -> 82.094516 | F31: =F10-F30 -> 117.18738 | G31: =G10-G30 -> 154.04325 | H31: =H10-H30 -> 190.57715 | I31: =I10-I30 -> 226.76215 | J31: =J10-J30 -> 225.56151 | K31: =K10-K30 -> 219.83007 | ... M31: =M10-M30 -> 206.9934
B32: EBITDA Margin | D32: =D31/D10 -> 0.046384631 | E32: =E31/E10 -> 0.083368685 | F32: =F31/F10 -> 0.093014975 | G32: =G31/G10 -> 0.099788392 | H32: =H31/H10 -> 0.10428175 | I32: =I31/I10 -> 0.10740179 | J32: =J31/J10 -> 0.10596363 | K32: =K31/K10 -> 0.10327113 | ... M32: =M31/M10 -> 0.097240753
B33: Depreciation | D33: =Depreciation!E193 -> 2.4055545 | E33: =Depreciation!F193 -> 9.6222181 | F33: =Depreciation!G193 -> 9.6222181 | G33: =Depreciation!H193 -> 9.6222181 | H33: =Depreciation!I193 -> 9.6222181 | I33: =Depreciation!J193 -> 9.6222181 | J33: =Depreciation!K193 -> 9.6222181 | K33: =Depreciation!L193 -> 9.4690032 | ... M33: =Depreciation!N193 -> 9.4579796
B34: EBIT | D34: =D31-D33 -> 5.0573579 | E34: =E31-E33 -> 72.472298 | F34: =F31-F33 -> 107.56517 | G34: =G31-G33 -> 144.42103 | H34: =H31-H33 -> 180.95493 | I34: =I31-I33 -> 217.13994 | J34: =J31-J33 -> 215.93929 | K34: =K31-K33 -> 210.36107 | ... M34: =M31-M33 -> 197.53542
B35: Interest Cost
B36: TL Interest | D36: ='Capex, Debt'!E115 -> 2.875 | E36: ='Capex, Debt'!F115 -> 11.095703 | F36: ='Capex, Debt'!G115 -> 9.703125 | G36: ='Capex, Debt'!H115 -> 8.265625 | H36: ='Capex, Debt'!I115 -> 6.828125 | I36: ='Capex, Debt'!J115 -> 5.390625 | J36: ='Capex, Debt'!K115 -> 3.953125 | K36: ='Capex, Debt'!L115 -> 2.515625 | ... M36: ='Capex, Debt'!N115 -> 0.044921875
B37: WC Interest | D37: =WC!E22 -> 1.9642805 | E37: =WC!F22 -> 12.710158 | F37: =WC!G22 -> 16.205024 | G37: =WC!H22 -> 19.817555 | H37: =WC!I22 -> 23.431398 | I37: =WC!J22 -> 27.046666 | J37: =WC!K22 -> 27.30127 | K37: =WC!L22 -> 27.324644 | ... M37: =WC!N22 -> 27.376998
B38: Bank Charges | D38: =WC!E23 -> 1.5714244 | E38: =WC!F23 -> 2.5420316 | F38: =WC!G23 -> 3.2410048 | G38: =WC!H23 -> 3.9635109 | H38: =WC!I23 -> 4.6862797 | I38: =WC!J23 -> 5.4093331 | J38: =WC!K23 -> 5.4602539 | K38: =WC!L23 -> 5.4649288 | ... M38: =WC!N23 -> 5.4753997
B39: PBT | D39: =D34-SUM(D36:D38) -> -1.3533471 | E39: =E34-SUM(E36:E38) -> 46.124405 | F39: =F34-SUM(F36:F38) -> 78.416011 | G39: =G34-SUM(G36:G38) -> 112.37434 | H39: =H34-SUM(H36:H38) -> 146.00913 | I39: =I34-SUM(I36:I38) -> 179.29331 | J39: =J34-SUM(J36:J38) -> 179.22464 | K39: =K34-SUM(K36:K38) -> 175.05587 | ... M39: =M34-SUM(M36:M38) -> 164.6381
B40: Provision for Tax
B41: Current Tax | D41: =D63 -> 0 | E41: =E63 -> 6.5522222 | F41: =F63 -> 17.942274 | G41: =G63 -> 27.138693 | H41: =H63 -> 36.144593 | I41: =I63 -> 44.976612 | J41: =J63 -> 45.344412 | K41: =K63 -> 44.583381 | ... M41: =M63 -> 42.472157
B42: Deferred Tax | D42: =D61-D63 -> 0 | E42: =E61-E63 -> 5.0563682 | F42: =F61-F63 -> 1.7934679 | G42: =G61-G63 -> 1.1436815 | H42: =H61-H63 -> 0.60298432 | I42: =I61-I63 -> 0.14792856 | J42: =J61-J63 -> -0.23715456 | K42: =K61-K63 -> -0.52531878 | ... M42: =M61-M63 -> -1.0360406
B43: PAT | D43: =D39-D41-D42 -> -1.3533471 | E43: =E39-E41-E42 -> 34.515815 | F43: =F39-F41-F42 -> 58.680269 | G43: =G39-G41-G42 -> 84.091967 | H43: =H39-H41-H42 -> 109.26155 | I43: =I39-I41-I42 -> 134.16877 | J43: =J39-J41-J42 -> 134.11738 | K43: =K39-K41-K42 -> 130.99781 | ... M43: =M39-M41-M42 -> 123.20198
B44: PAT Margins
B46: Cash Accruals | D46: =D43+D33+D42 -> 1.0522074 | E46: =E43+E33+E42 -> 49.194401 | F46: =F43+F33+F42 -> 70.095955 | G46: =G43+G33+G42 -> 94.857866 | H46: =H43+H33+H42 -> 119.48675 | I46: =I43+I33+I42 -> 143.93892 | J46: =J43+J33+J42 -> 143.50245 | K46: =K43+K33+K42 -> 139.94149 | ... M46: =M43+M33+M42 -> 131.62392
B48: Tax Calculation | D48: =D4 -> 44286 | E48: =E4 -> 44651 | F48: =F4 -> 45016 | G48: =G4 -> 45382 | H48: =H4 -> 45747 | I48: =I4 -> 46112 | J48: =J4 -> 46477 | K48: =K4 -> 46843 | ... M48: =M4 -> 47573
B50: PBT | D50: =D39 -> -1.3533471 | E50: =E39 -> 46.124405 | F50: =F39 -> 78.416011 | G50: =G39 -> 112.37434 | H50: =H39 -> 146.00913 | I50: =I39 -> 179.29331 | J50: =J39 -> 179.22464 | K50: =K39 -> 175.05587 | ... M50: =M39 -> 164.6381
B52: Depr as per books | D52: =Depreciation!E193 -> 2.4055545 | E52: =Depreciation!F193 -> 9.6222181 | F52: =Depreciation!G193 -> 9.6222181 | G52: =Depreciation!H193 -> 9.6222181 | H52: =Depreciation!I193 -> 9.6222181 | I52: =Depreciation!J193 -> 9.6222181 | J52: =Depreciation!K193 -> 9.6222181 | K52: =Depreciation!L193 -> 9.4690032 | ... M52: =Depreciation!N193 -> 9.4579796
B53: Depr as per IT | D53: =Depreciation!E194 -> 10.842024 | E53: =Depreciation!F194 -> 19.922867 | F53: =Depreciation!G194 -> 16.748203 | G53: =Depreciation!H194 -> 14.166407 | H53: =Depreciation!I194 -> 12.018055 | I53: =Depreciation!J194 -> 10.209983 | J53: =Depreciation!K194 -> 8.6799321 | K53: =Depreciation!L194 -> 7.3817544 | ... M53: =Depreciation!N194 -> 5.3414802
B55: PBT as per IT | D55: =D50+D52-D53 -> -9.7898162 | E55: =E50+E52-E53 -> 35.823757 | F55: =F50+F52-F53 -> 71.290026 | G55: =G50+G52-G53 -> 107.83015 | H55: =H50+H52-H53 -> 143.61329 | I55: =I50+I52-I53 -> 178.70555 | J55: =J50+J52-J53 -> 180.16693 | K55: =K50+K52-K53 -> 177.14312 | ... M55: =M50+M52-M53 -> 168.7546
B57: Losses carry forward | E57: =MIN(D55+D57,0) -> -9.7898162 | F57: =MIN(E55+E57,0) -> 0 | G57: =MIN(F55+F57,0) -> 0 | H57: =MIN(G55+G57,0) -> 0 | I57: =MIN(H55+H57,0) -> 0 | J57: =MIN(I55+I57,0) -> 0 | K57: =MIN(J55+J57,0) -> 0 | L57: =MIN(K55+K57,0) -> 0 | M57: =MIN(L55+L57,0) -> 0
B59: Taxable Profit under IT Act | D59: =MAX(D55+D57,0) -> 0 | E59: =MAX(E55+E57,0) -> 26.033941 | F59: =MAX(F55+F57,0) -> 71.290026 | G59: =MAX(G55+G57,0) -> 107.83015 | H59: =MAX(H55+H57,0) -> 143.61329 | I59: =MAX(I55+I57,0) -> 178.70555 | J59: =MAX(J55+J57,0) -> 180.16693 | K59: =MAX(K55+K57,0) -> 177.14312 | ... M59: =MAX(M55+M57,0) -> 168.7546
B61: Tax - Corporate (Companys Act) | D61: =IF(D50>0,D50*Assumptions!$D$148,0) -> 0 | E61: =IF(E50>0,E50*Assumptions!$D$148,0) -> 11.60859 | F61: =IF(F50>0,F50*Assumptions!$D$148,0) -> 19.735742 | G61: =IF(G50>0,G50*Assumptions!$D$148,0) -> 28.282374 | H61: =IF(H50>0,H50*Assumptions!$D$148,0) -> 36.747578 | I61: =IF(I50>0,I50*Assumptions!$D$148,0) -> 45.124541 | J61: =IF(J50>0,J50*Assumptions!$D$148,0) -> 45.107258 | K61: =IF(K50>0,K50*Assumptions!$D$148,0) -> 44.058062 | ... M61: =IF(M50>0,M50*Assumptions!$D$148,0) -> 41.436116
B62: MAT
B63: Tax - Leviable (IT Act) | D63: =IF(D59>0,D59*Assumptions!$D$148,0) -> 0 | E63: =IF(E59>0,E59*Assumptions!$D$148,0) -> 6.5522222 | F63: =IF(F59>0,F59*Assumptions!$D$148,0) -> 17.942274 | G63: =IF(G59>0,G59*Assumptions!$D$148,0) -> 27.138693 | H63: =IF(H59>0,H59*Assumptions!$D$148,0) -> 36.144593 | I63: =IF(I59>0,I59*Assumptions!$D$148,0) -> 44.976612 | J63: =IF(J59>0,J59*Assumptions!$D$148,0) -> 45.344412 | K63: =IF(K59>0,K59*Assumptions!$D$148,0) -> 44.583381 | ... M63: =IF(M59>0,M59*Assumptions!$D$148,0) -> 42.472157
D64: =D61-D63 -> 0 | E64: =E61-E63 -> 5.0563682 | F64: =F61-F63 -> 1.7934679 | G64: =G61-G63 -> 1.1436815 | H64: =H61-H63 -> 0.60298432 | I64: =I61-I63 -> 0.14792856 | J64: =J61-J63 -> -0.23715456 | K64: =K61-K63 -> -0.52531878 | ... M64: =M61-M63 -> -1.0360406
B65: MAT - Credit
B66: Op Credit
B67: MAT Credit
B68: Utilised
B69: CL Credit
B71: Deferred Tax Calculation
B72: PBT
B73: Normal Tax
B74: Tax Leviable
B75: Deferred Tax for the Year
B77: Op Deferred Tax
B78: Deferred Tax Charge
B79: Cl Deferred Tax

Sheet CF
B2: Cash Flows
M3: INR Lacs
B4: FY Ending | D4: =PL!D4 -> 44286 | E4: =PL!E4 -> 44651 | F4: =PL!F4 -> 45016 | G4: =PL!G4 -> 45382 | H4: =PL!H4 -> 45747 | I4: =PL!I4 -> 46112 | J4: =PL!J4 -> 46477 | K4: =PL!K4 -> 46843 | ... M4: =PL!M4 -> 47573
B5: PAT | D5: =PL!D43 -> -1.3533471 | E5: =PL!E43 -> 34.515815 | F5: =PL!F43 -> 58.680269 | G5: =PL!G43 -> 84.091967 | H5: =PL!H43 -> 109.26155 | I5: =PL!I43 -> 134.16877 | J5: =PL!J43 -> 134.11738 | K5: =PL!K43 -> 130.99781 | ... M5: =PL!M43 -> 123.20198
B6: Depreciation | D6: =PL!D33 -> 2.4055545 | E6: =PL!E33 -> 9.6222181 | F6: =PL!F33 -> 9.6222181 | G6: =PL!G33 -> 9.6222181 | H6: =PL!H33 -> 9.6222181 | I6: =PL!I33 -> 9.6222181 | J6: =PL!J33 -> 9.6222181 | K6: =PL!K33 -> 9.4690032 | ... M6: =PL!M33 -> 9.4579796
B7: Deferred Tax Liability/(Asset) | D7: =PL!D42 -> 0 | E7: =PL!E42 -> 5.0563682 | F7: =PL!F42 -> 1.7934679 | G7: =PL!G42 -> 1.1436815 | H7: =PL!H42 -> 0.60298432 | I7: =PL!I42 -> 0.14792856 | J7: =PL!J42 -> -0.23715456 | K7: =PL!K42 -> -0.52531878 | ... M7: =PL!M42 -> -1.0360406
B8: Increase in Current Liability | D8: =WC!E16-WC!D16 -> 45.99 | E8: =WC!F16-WC!E16 -> -2.68275 | F8: =WC!G16-WC!F16 -> 12.64725 | G8: =WC!H16-WC!G16 -> 12.264 | H8: =WC!I16-WC!H16 -> 12.264 | I8: =WC!J16-WC!I16 -> 12.264 | J8: =WC!K16-WC!J16 -> -0.7665 | K8: =WC!L16-WC!K16 -> 0 | ... M8: =WC!N16-WC!M16 -> 0
B9: Increase in Equity - Share Capital | D9: ='Capex, Debt'!E102 -> 63.186241
B10: Increase in Unsecured Loan
B11: Increase in Term Loan | D11: ='Capex, Debt'!E101 -> 115
B12: Increase/ (Decrease in WC Borrowing) | D12: =WC!E20-WC!D20 -> 78.571222 | E12: =WC!F20-WC!E20 -> 48.530357 | F12: =WC!G20-WC!F20 -> 34.948663 | G12: =WC!H20-WC!G20 -> 36.125304 | H12: =WC!I20-WC!H20 -> 36.138439 | I12: =WC!J20-WC!I20 -> 36.152672 | J12: =WC!K20-WC!J20 -> 2.5460387 | K12: =WC!L20-WC!K20 -> 0.23374621 | ... M12: =WC!N20-WC!M20 -> 0.27163133
B13: Total Inflow | D13: =SUM(D5:D12) -> 303.79967 | E13: =SUM(E5:E12) -> 95.042009 | F13: =SUM(F5:F12) -> 117.69187 | G13: =SUM(G5:G12) -> 143.24717 | H13: =SUM(H5:H12) -> 167.88919 | I13: =SUM(I5:I12) -> 192.35559 | J13: =SUM(J5:J12) -> 145.28199 | K13: =SUM(K5:K12) -> 140.17524 | ... M13: =SUM(M5:M12) -> 131.89555
B14: Capex | D14: =Depreciation!E16 -> 151.99583
B15: Preliminary Expenses
B16: Increase in Current Assets | D16: =WC!E12-WC!D12 -> 150.75163 | E16: =WC!F12-WC!E12 -> 62.024393 | F16: =WC!G12-WC!F12 -> 59.245467 | G16: =WC!H12-WC!G12 -> 60.431072 | H16: =WC!I12-WC!H12 -> 60.448585 | I16: =WC!J12-WC!I12 -> 60.467563 | J16: =WC!K12-WC!J12 -> 2.6282182 | K16: =WC!L12-WC!K12 -> 0.31166161 | ... M16: =WC!N12-WC!M12 -> 0.3621751
B17: Repayment of Term Loan | D17: ='Capex, Debt'!E110 -> 0 | E17: ='Capex, Debt'!F110 -> 10.78125 | F17: ='Capex, Debt'!G110 -> 14.375 | G17: ='Capex, Debt'!H110 -> 14.375 | H17: ='Capex, Debt'!I110 -> 14.375 | I17: ='Capex, Debt'!J110 -> 14.375 | J17: ='Capex, Debt'!K110 -> 14.375 | K17: ='Capex, Debt'!L110 -> 14.375 | ... M17: ='Capex, Debt'!N110 -> 3.59375
B18: Total Outflow | D18: =SUM(D14:D17) -> 302.74746 | E18: =SUM(E14:E17) -> 72.805643 | F18: =SUM(F14:F17) -> 73.620467 | G18: =SUM(G14:G17) -> 74.806072 | H18: =SUM(H14:H17) -> 74.823585 | I18: =SUM(I14:I17) -> 74.842563 | J18: =SUM(J14:J17) -> 17.003218 | K18: =SUM(K14:K17) -> 14.686662 | ... M18: =SUM(M14:M17) -> 3.9559251
B19: Opening Cash Balance | D19: 0 | E19: =D21 -> 1.0522074 | F19: =E21 -> 23.288573 | G19: =F21 -> 67.359974 | H19: =G21 -> 135.80107 | I19: =H21 -> 228.86668 | J19: =I21 -> 346.37971 | K19: =J21 -> 474.65847 | L19: =K21 -> 600.14705 | M19: =L21 -> 721.78299
B20: Surplus/ (Deficit) during the year | D20: =D13-D18 -> 1.0522074 | E20: =E13-E18 -> 22.236366 | F20: =F13-F18 -> 44.071401 | G20: =G13-G18 -> 68.441098 | H20: =H13-H18 -> 93.065608 | I20: =I13-I18 -> 117.51303 | J20: =J13-J18 -> 128.27877 | K20: =K13-K18 -> 125.48858 | ... M20: =M13-M18 -> 127.93963
B21: Closing Balance | D21: =D19+D20 -> 1.0522074 | E21: =E19+E20 -> 23.288573 | F21: =F19+F20 -> 67.359974 | G21: =G19+G20 -> 135.80107 | H21: =H19+H20 -> 228.86668 | I21: =I19+I20 -> 346.37971 | J21: =J19+J20 -> 474.65847 | K21: =K19+K20 -> 600.14705 | ... M21: =M19+M20 -> 849.72261
D23: =SUM(D5:M7)-'Capex, Debt'!C110-(WC!N18-WC!E18) -> 849.72261

Sheet BS
B2: Balance Sheet
B4: FY Ending | C4: =EOMONTH(D4,-12) -> 43921 | D4: =CF!D4 -> 44286 | E4: =CF!E4 -> 44651 | F4: =CF!F4 -> 45016 | G4: =CF!G4 -> 45382 | H4: =CF!H4 -> 45747 | I4: =CF!I4 -> 46112 | J4: =CF!J4 -> 46477 | K4: =CF!K4 -> 46843 | ... M4: =CF!M4 -> 47573
B6: Shareholders Funds | D6: =SUM(D7:D9) -> 61.832894 | E6: =SUM(E7:E9) -> 96.348709 | F6: =SUM(F7:F9) -> 155.02898 | G6: =SUM(G7:G9) -> 239.12094 | H6: =SUM(H7:H9) -> 348.3825 | I6: =SUM(I7:I9) -> 482.55127 | J6: =SUM(J7:J9) -> 616.66865 | K6: =SUM(K7:K9) -> 747.66646 | ... M6: =SUM(M7:M9) -> 998.30547
B7: Share Capital | D7: =C7+CF!D9 -> 63.186241 | E7: =D7+CF!E9 -> 63.186241 | F7: =E7+CF!F9 -> 63.186241 | G7: =F7+CF!G9 -> 63.186241 | H7: =G7+CF!H9 -> 63.186241 | I7: =H7+CF!I9 -> 63.186241 | J7: =I7+CF!J9 -> 63.186241 | K7: =J7+CF!K9 -> 63.186241 | ... M7: =L7+CF!M9 -> 63.186241
B8: Reserves & Surplus | D8: =C8+CF!D5 -> -1.3533471 | E8: =D8+CF!E5 -> 33.162468 | F8: =E8+CF!F5 -> 91.842737 | G8: =F8+CF!G5 -> 175.9347 | H8: =G8+CF!H5 -> 285.19626 | I8: =H8+CF!I5 -> 419.36503 | J8: =I8+CF!J5 -> 553.48241 | K8: =J8+CF!K5 -> 684.48022 | ... M8: =L8+CF!M5 -> 935.11923
B9: Unsecured Loan
B10: Long Term Liabilities | D10: =SUM(D11:D12) -> 104.21875 | E10: =SUM(E11:E12) -> 94.900118 | F10: =SUM(F11:F12) -> 82.318586 | G10: =SUM(G11:G12) -> 69.087268 | H10: =SUM(H11:H12) -> 55.315252 | I10: =SUM(I11:I12) -> 41.08818 | J10: =SUM(J11:J12) -> 26.476026 | K10: =SUM(K11:K12) -> 11.575707 | ... M10: =SUM(M11:M12) -> 6.1458124
B11: Term Loan | D11: ='Capex, Debt'!E111-D16 -> 104.21875 | E11: ='Capex, Debt'!F111-E16 -> 89.84375 | F11: ='Capex, Debt'!G111-F16 -> 75.46875 | G11: ='Capex, Debt'!H111-G16 -> 61.09375 | H11: ='Capex, Debt'!I111-H16 -> 46.71875 | I11: ='Capex, Debt'!J111-I16 -> 32.34375 | J11: ='Capex, Debt'!K111-J16 -> 17.96875 | K11: ='Capex, Debt'!L111-K16 -> 3.59375 | ... M11: ='Capex, Debt'!N111-M16 -> 3.4194869e-14
B12: Deferred Tax Liability (net) | D12: =C12+CF!D7 -> 0 | E12: =D12+CF!E7 -> 5.0563682 | F12: =E12+CF!F7 -> 6.8498361 | G12: =F12+CF!G7 -> 7.9935176 | H12: =G12+CF!H7 -> 8.5965019 | I12: =H12+CF!I7 -> 8.7444305 | J12: =I12+CF!J7 -> 8.5072759 | K12: =J12+CF!K7 -> 7.9819571 | ... M12: =L12+CF!M7 -> 6.1458124
B13: Current Liabilities | D13: =SUM(D14:D17) -> 135.34247 | E13: =SUM(E14:E17) -> 184.78383 | F13: =SUM(F14:F17) -> 232.37974 | G13: =SUM(G14:G17) -> 280.76905 | H13: =SUM(H14:H17) -> 329.17148 | I13: =SUM(I14:I17) -> 377.58816 | J13: =SUM(J14:J17) -> 379.3677 | K13: =SUM(K14:K17) -> 379.60144 | ... M13: =SUM(M14:M17) -> 365.74998
B14: Creditors | D14: =WC!E14 -> 45.99 | E14: =WC!F14 -> 43.30725 | F14: =WC!G14 -> 55.9545 | G14: =WC!H14 -> 68.2185 | H14: =WC!I14 -> 80.4825 | I14: =WC!J14 -> 92.7465 | J14: =WC!K14 -> 91.98 | K14: =WC!L14 -> 91.98 | ... M14: =WC!N14 -> 91.98
B15: Other Current Liabilities | D15: =WC!E15 -> 0 | E15: =WC!F15 -> 0 | F15: =WC!G15 -> 0 | G15: =WC!H15 -> 0 | H15: =WC!I15 -> 0 | I15: =WC!J15 -> 0 | J15: =WC!K15 -> 0 | K15: =WC!L15 -> 0 | ... M15: =WC!N15 -> 0
B16: Current Maturities of LTB | D16: ='Capex, Debt'!F110 -> 10.78125 | E16: ='Capex, Debt'!G110 -> 14.375 | F16: ='Capex, Debt'!H110 -> 14.375 | G16: ='Capex, Debt'!I110 -> 14.375 | H16: ='Capex, Debt'!J110 -> 14.375 | I16: ='Capex, Debt'!K110 -> 14.375 | J16: ='Capex, Debt'!L110 -> 14.375 | K16: ='Capex, Debt'!M110 -> 14.375 | ... M16: ='Capex, Debt'!O110 -> 0
B17: Short Term Borrowings | D17: =WC!E20 -> 78.571222 | E17: =WC!F20 -> 127.10158 | F17: =WC!G20 -> 162.05024 | G17: =WC!H20 -> 198.17555 | H17: =WC!I20 -> 234.31398 | I17: =WC!J20 -> 270.46666 | J17: =WC!K20 -> 273.0127 | K17: =WC!L20 -> 273.24644 | ... M17: =WC!N20 -> 273.76998
B18: Total Equity and Liabilities | D18: =D6+D10+D13 -> 301.39412 | E18: =E6+E10+E13 -> 376.03266 | F18: =F6+F10+F13 -> 469.72731 | G18: =G6+G10+G13 -> 588.97726 | H18: =H6+H10+H13 -> 732.86923 | I18: =I6+I10+I13 -> 901.2276 | J18: =J6+J10+J13 -> 1022.5124 | K18: =K6+K10+K13 -> 1138.8436 | ... M18: =M6+M10+M13 -> 1370.2013
B19: Fixed Assets
B20: Gross Block | D20: =Depreciation!E110 -> 151.99583 | E20: =Depreciation!F110 -> 151.99583 | F20: =Depreciation!G110 -> 151.99583 | G20: =Depreciation!H110 -> 151.99583 | H20: =Depreciation!I110 -> 151.99583 | I20: =Depreciation!J110 -> 151.99583 | J20: =Depreciation!K110 -> 151.99583 | K20: =Depreciation!L110 -> 151.99583 | ... M20: =Depreciation!N110 -> 151.99583
B21: Less: Accumulated Depreciation | D21: =Depreciation!E113 -> 2.4055545 | E21: =Depreciation!F113 -> 12.027773 | F21: =Depreciation!G113 -> 21.649991 | G21: =Depreciation!H113 -> 31.272209 | H21: =Depreciation!I113 -> 40.894427 | I21: =Depreciation!J113 -> 50.516645 | J21: =Depreciation!K113 -> 60.138863 | K21: =Depreciation!L113 -> 69.607867 | ... M21: =Depreciation!N113 -> 88.523826
B22: Net Fixed Assets | D22: =D20-D21 -> 149.59028 | E22: =E20-E21 -> 139.96806 | F22: =F20-F21 -> 130.34584 | G22: =G20-G21 -> 120.72362 | H22: =H20-H21 -> 111.10141 | I22: =I20-I21 -> 101.47919 | J22: =J20-J21 -> 91.85697 | K22: =K20-K21 -> 82.387967 | ... M22: =M20-M21 -> 63.472007
B23: Current Assets | D23: =SUM(D24:D29) -> 151.80384 | E23: =SUM(E24:E29) -> 236.0646 | F23: =SUM(F24:F29) -> 339.38146 | G23: =SUM(G24:G29) -> 468.25363 | H23: =SUM(H24:H29) -> 621.76783 | I23: =SUM(I24:I29) -> 799.74842 | J23: =SUM(J24:J29) -> 930.6554 | K23: =SUM(K24:K29) -> 1056.4556 | ... M23: =SUM(M24:M29) -> 1306.7293
B24: Raw Material Inventory | D24: =WC!E7 -> 27.594 | E24: =WC!F7 -> 32.193 | F24: =WC!G7 -> 41.391 | G24: =WC!H7 -> 50.589 | H24: =WC!I7 -> 59.787 | I24: =WC!J7 -> 68.985 | J24: =WC!K7 -> 68.985 | K24: =WC!L7 -> 68.985 | ... M24: =WC!N7 -> 68.985
B25: WIP Inventory | D25: =WC!E8 -> 25.294 | E25: =WC!F8 -> 29.3208 | F25: =WC!G8 -> 37.25979 | G25: =WC!H8 -> 45.20873 | H25: =WC!I8 -> 53.168446 | I25: =WC!J8 -> 61.139841 | J25: =WC!K8 -> 61.317899 | K25: =WC!L8 -> 61.50969 | ... M25: =WC!N8 -> 61.939263
B26: FG Inventory | D26: =WC!E9 -> 15.80875 | E26: =WC!F9 -> 18.3255 | F26: =WC!G9 -> 23.287369 | G26: =WC!H9 -> 28.255456 | H26: =WC!I9 -> 33.230279 | I26: =WC!J9 -> 38.212401 | J26: =WC!K9 -> 38.323687 | K26: =WC!L9 -> 38.443556 | ... M26: =WC!N9 -> 38.71204
B27: Sundry Debtors | D27: =WC!E10 -> 80.44596 | E27: =WC!F10 -> 123.08956 | F27: =WC!G10 -> 157.48457 | G27: =WC!H10 -> 192.96239 | H27: =WC!I10 -> 228.4402 | I27: =WC!J10 -> 263.91803 | J27: =WC!K10 -> 266.08365 | K27: =WC!L10 -> 266.08365 | ... M27: =WC!N10 -> 266.08365
B28: Stores & Spares | D28: =WC!E11 -> 1.6089192 | E28: =WC!F11 -> 9.8471646 | F28: =WC!G11 -> 12.598765 | G28: =WC!H11 -> 15.436991 | H28: =WC!I11 -> 18.275216 | I28: =WC!J11 -> 21.113442 | J28: =WC!K11 -> 21.286692 | K28: =WC!L11 -> 21.286692 | ... M28: =WC!N11 -> 21.286692
B29: Cash & Bank Balance | D29: =CF!D21 -> 1.0522074 | E29: =CF!E21 -> 23.288573 | F29: =CF!F21 -> 67.359974 | G29: =CF!G21 -> 135.80107 | H29: =CF!H21 -> 228.86668 | I29: =CF!I21 -> 346.37971 | J29: =CF!J21 -> 474.65847 | K29: =CF!K21 -> 600.14705 | ... M29: =CF!M21 -> 849.72261
B30: Total Assets | D30: =D22+D23 -> 301.39412 | E30: =E22+E23 -> 376.03266 | F30: =F22+F23 -> 469.72731 | G30: =G22+G23 -> 588.97726 | H30: =H22+H23 -> 732.86923 | I30: =I22+I23 -> 901.2276 | J30: =J22+J23 -> 1022.5124 | K30: =K22+K23 -> 1138.8436 | ... M30: =M22+M23 -> 1370.2013
B32: Check | D32: =D18-D30 -> 0 | E32: =E18-E30 -> 0 | F32: =F18-F30 -> 0 | G32: =G18-G30 -> 0 | H32: =H18-H30 -> 0 | I32: =I18-I30 -> 0 | J32: =J18-J30 -> 0 | K32: =K18-K30 -> 0 | ... M32: =M18-M30 -> 0

Sheet Ratio
B2: DSCR Calculations
B4: FY Ending | D4: =BS!D4 -> 44286 | E4: =BS!E4 -> 44651 | F4: =BS!F4 -> 45016 | G4: =BS!G4 -> 45382 | H4: =BS!H4 -> 45747 | I4: =BS!I4 -> 46112 | J4: =BS!J4 -> 46477 | K4: =BS!K4 -> 46843 | ... M4: =BS!M4 -> 47573
B5: DSCR Factor | D5: {=TRANSPOSE(Assumptions!I64:I73)} -> 1 | E5: 1 | F5: 1 | G5: 1 | H5: 1 | I5: 1 | J5: 1 | K5: 1 | L5: 1 | M5: 0.25
B6: PAT | D6: =PL!D43*D5 -> -1.3533471 | E6: =PL!E43*E5 -> 34.515815 | F6: =PL!F43*F5 -> 58.680269 | G6: =PL!G43*G5 -> 84.091967 | H6: =PL!H43*H5 -> 109.26155 | I6: =PL!I43*I5 -> 134.16877 | J6: =PL!J43*J5 -> 134.11738 | K6: =PL!K43*K5 -> 130.99781 | ... M6: =PL!M43*M5 -> 30.800495
B7: Depreciation | D7: =PL!D33 -> 2.4055545 | E7: =PL!E33 -> 9.6222181 | F7: =PL!F33 -> 9.6222181 | G7: =PL!G33 -> 9.6222181 | H7: =PL!H33 -> 9.6222181 | I7: =PL!I33 -> 9.6222181 | J7: =PL!J33 -> 9.6222181 | K7: =PL!K33 -> 9.4690032 | L7: =PL!L33 -> 9.4579796 | M7: =PL!M33*M5 -> 2.3644949
B8: Deferred Tax Liability/(Asset) | D8: =PL!D42 -> 0 | E8: =PL!E42 -> 5.0563682 | F8: =PL!F42 -> 1.7934679 | G8: =PL!G42 -> 1.1436815 | H8: =PL!H42 -> 0.60298432 | I8: =PL!I42 -> 0.14792856 | J8: =PL!J42 -> -0.23715456 | K8: =PL!K42 -> -0.52531878 | L8: =PL!L42 -> -0.80010418 | M8: =PL!M42*M5 -> -0.25901014
B9: Term Loan Interest | D9: =PL!D36 -> 2.875 | E9: =PL!E36 -> 11.095703 | F9: =PL!F36 -> 9.703125 | G9: =PL!G36 -> 8.265625 | H9: =PL!H36 -> 6.828125 | I9: =PL!I36 -> 5.390625 | J9: =PL!J36 -> 3.953125 | K9: =PL!K36 -> 2.515625 | ... M9: =PL!M36 -> 0.044921875
B10: Total Inflow | D10: =SUM(D6:D9) -> 3.9272074 | E10: =SUM(E6:E9) -> 60.290105 | F10: =SUM(F6:F9) -> 79.79908 | G10: =SUM(G6:G9) -> 103.12349 | H10: =SUM(H6:H9) -> 126.31488 | I10: =SUM(I6:I9) -> 149.32954 | J10: =SUM(J6:J9) -> 147.45557 | K10: =SUM(K6:K9) -> 142.45712 | ... M10: =SUM(M6:M9) -> 32.950902
B11: Term Loan Repayments | D11: ='Capex, Debt'!E110 -> 0 | E11: ='Capex, Debt'!F110 -> 10.78125 | F11: ='Capex, Debt'!G110 -> 14.375 | G11: ='Capex, Debt'!H110 -> 14.375 | H11: ='Capex, Debt'!I110 -> 14.375 | I11: ='Capex, Debt'!J110 -> 14.375 | J11: ='Capex, Debt'!K110 -> 14.375 | K11: ='Capex, Debt'!L110 -> 14.375 | ... M11: ='Capex, Debt'!N110 -> 3.59375
B12: Interest | D12: =D9 -> 2.875 | E12: =E9 -> 11.095703 | F12: =F9 -> 9.703125 | G12: =G9 -> 8.265625 | H12: =H9 -> 6.828125 | I12: =I9 -> 5.390625 | J12: =J9 -> 3.953125 | K12: =K9 -> 2.515625 | ... M12: =M9 -> 0.044921875
B13: Total Outflow | D13: =D11+D12 -> 2.875 | E13: =E11+E12 -> 21.876953 | F13: =F11+F12 -> 24.078125 | G13: =G11+G12 -> 22.640625 | H13: =H11+H12 -> 21.203125 | I13: =I11+I12 -> 19.765625 | J13: =J11+J12 -> 18.328125 | K13: =K11+K12 -> 16.890625 | ... M13: =M11+M12 -> 3.6386719
B14: DSCR | D14: =D10/D13 -> 1.3659852 | E14: =E10/E13 -> 2.755873 | F14: =F10/F13 -> 3.3141734 | G14: =G10/G13 -> 4.5547988 | H14: =H10/H13 -> 5.9573709 | I14: =I10/I13 -> 7.5550124 | J14: =J10/J13 -> 8.0453168 | K14: =K10/K13 -> 8.4340941 | ... M14: =M10/M13 -> 9.0557497
B15: Average DSCR | C15: =SUM(D10:M10)/SUM(D13:M13) -> 5.8939786
B16: Minimum DSCR | C16: =MIN(D14:M14) -> 1.3659852
B18: IRR Calculations
B20: FY Ending | D20: =D4 -> 44286 | E20: =E4 -> 44651 | F20: =F4 -> 45016 | G20: =G4 -> 45382 | H20: =H4 -> 45747 | I20: =I4 -> 46112 | J20: =J4 -> 46477 | K20: =K4 -> 46843 | ... M20: =M4 -> 47573
B21: Cash Outflow
B22: Capital Expenditure | D22: =CF!D14 -> 151.99583 | E22: =CF!E14 -> 0 | F22: =CF!F14 -> 0 | G22: =CF!G14 -> 0 | H22: =CF!H14 -> 0 | I22: =CF!I14 -> 0 | J22: =CF!J14 -> 0 | K22: =CF!K14 -> 0 | ... M22: =CF!M14 -> 0
B23: Total Outflow | D23: =D22 -> 151.99583 | E23: =E22 -> 0 | F23: =F22 -> 0 | G23: =G22 -> 0 | H23: =H22 -> 0 | I23: =I22 -> 0 | J23: =J22 -> 0 | K23: =K22 -> 0 | ... M23: =M22 -> 0
B24: Cash Inflow
B25: PAT | D25: =PL!D43 -> -1.3533471 | E25: =PL!E43 -> 34.515815 | F25: =PL!F43 -> 58.680269 | G25: =PL!G43 -> 84.091967 | H25: =PL!H43 -> 109.26155 | I25: =PL!I43 -> 134.16877 | J25: =PL!J43 -> 134.11738 | K25: =PL!K43 -> 130.99781 | ... M25: =PL!M43 -> 123.20198
B26: Depreciation | D26: =PL!D33 -> 2.4055545 | E26: =PL!E33 -> 9.6222181 | F26: =PL!F33 -> 9.6222181 | G26: =PL!G33 -> 9.6222181 | H26: =PL!H33 -> 9.6222181 | I26: =PL!I33 -> 9.6222181 | J26: =PL!J33 -> 9.6222181 | K26: =PL!K33 -> 9.4690032 | ... M26: =PL!M33 -> 9.4579796
B27: Deferred Tax Liability/(Asset) | D27: =PL!D42 -> 0 | E27: =PL!E42 -> 5.0563682 | F27: =PL!F42 -> 1.7934679 | G27: =PL!G42 -> 1.1436815 | H27: =PL!H42 -> 0.60298432 | I27: =PL!I42 -> 0.14792856 | J27: =PL!J42 -> -0.23715456 | K27: =PL!K42 -> -0.52531878 | ... M27: =PL!M42 -> -1.0360406
B28: Interest Cost *(1-tax rate) | D28: =PL!D36*(1-Assumptions!$D$148) -> 2.15142 | E28: =PL!E36*(1-Assumptions!$D$148) -> 8.3031366 | F28: =PL!F36*(1-Assumptions!$D$148) -> 7.2610425 | G28: =PL!G36*(1-Assumptions!$D$148) -> 6.1853325 | H28: =PL!H36*(1-Assumptions!$D$148) -> 5.1096225 | I28: =PL!I36*(1-Assumptions!$D$148) -> 4.0339125 | J28: =PL!J36*(1-Assumptions!$D$148) -> 2.9582025 | K28: =PL!K36*(1-Assumptions!$D$148) -> 1.8824925 | ... M28: =PL!M36*(1-Assumptions!$D$148) -> 0.033615937
B29: Terminal Value | M29: =BS!M22 -> 63.472007
B30: Total Inflow | D30: =SUM(D25:D29) -> 3.2036274 | E30: =SUM(E25:E29) -> 57.497538 | F30: =SUM(F25:F29) -> 77.356998 | G30: =SUM(G25:G29) -> 101.0432 | H30: =SUM(H25:H29) -> 124.59638 | I30: =SUM(I25:I29) -> 147.97283 | J30: =SUM(J25:J29) -> 146.46065 | K30: =SUM(K25:K29) -> 141.82399 | ... M30: =SUM(M25:M29) -> 195.12954
B31: Net Cash Flows | D31: =D30-D23 -> -148.79221 | E31: =E30-E23 -> 57.497538 | F31: =F30-F23 -> 77.356998 | G31: =G30-G23 -> 101.0432 | H31: =H30-H23 -> 124.59638 | I31: =I30-I23 -> 147.97283 | J31: =J30-J23 -> 146.46065 | K31: =K30-K23 -> 141.82399 | ... M31: =M30-M23 -> 195.12954
B32: IRR | C32: =IRR(D31:M31,10%) -> 0.58365602
B34: WACC Calculations
B36: Sources of Funding | D36: Amount | E36: Proportion | F36: ROI | G36: Post Tax CoC(%) | H36: WACC
B37: Equity | D37: =Assumptions!E33 -> 43.186241 | E37: =D37/$D$40 -> 0.24236574 | F37: 0.15 | G37: =F37 -> 0.15 | H37: =G37*E37 -> 0.036354861
B38: Unsecured Loan | D38: =Assumptions!E34 -> 20 | E38: =D38/$D$40 -> 0.11224211 | F38: 0.15 | G38: =F38 -> 0.15 | H38: =G38*E38 -> 0.016836317
B39: Term Loan from Banks | D39: =Assumptions!E35 -> 115 | E39: =D39/$D$40 -> 0.64539214 | F39: =Assumptions!E43 -> 0.1 | G39: =F39*(1-Assumptions!D148) -> 0.074832 | H39: =G39*E39 -> 0.048295985
D40: =SUM(D37:D39) -> 178.18624 | H40: =SUM(H37:H39) -> 0.10148716
B42: Difference between IRR and WACC | C42: =C32-H40 -> 0.48216885
B45: Break Even Point Analysis
B47: FY Ending (INR Cr) | D47: =D20 -> 44286 | E47: =E20 -> 44651 | F47: =F20 -> 45016 | G47: =G20 -> 45382 | H47: =H20 -> 45747 | I47: =I20 -> 46112 | J47: =J20 -> 46477 | K47: =K20 -> 46843 | ... M47: =M20 -> 47573
B48: Months of Operations | D48: =CoP!E5 -> 3 | E48: =CoP!F5 -> 12 | F48: =CoP!G5 -> 12 | G48: =CoP!H5 -> 12 | H48: =CoP!I5 -> 12 | I48: =CoP!J5 -> 12 | J48: =CoP!K5 -> 12 | K48: =CoP!L5 -> 12 | ... M48: =CoP!N5 -> 12
B49: Sales | D49: =PL!D10 -> 160.89192 | E49: =PL!E10 -> 984.71646 | F49: =PL!F10 -> 1259.8765 | G49: =PL!G10 -> 1543.6991 | H49: =PL!H10 -> 1827.5216 | I49: =PL!I10 -> 2111.3442 | J49: =PL!J10 -> 2128.6692 | K49: =PL!K10 -> 2128.6692 | ... M49: =PL!M10 -> 2128.6692
B50: Variable Cost: | D50: =SUM(D51:D58) -> 138.06795 | E50: =SUM(E51:E58) -> 828.33864 | F50: =SUM(F51:F58) -> 1060.3552 | G50: =SUM(G51:G58) -> 1298.854 | H50: =SUM(H51:H58) -> 1537.3531 | I50: =SUM(I51:I58) -> 1775.8525 | J50: =SUM(J51:J58) -> 1788.8222 | K50: =SUM(K51:K58) -> 1788.8279 | ... M50: =SUM(M51:M58) -> 1788.8402
B51: Raw Material Consumed | D51: =PL!D14 -> 110.376 | E51: =PL!E14 -> 515.088 | F51: =PL!F14 -> 662.256 | G51: =PL!G14 -> 809.424 | H51: =PL!H14 -> 956.592 | I51: =PL!I14 -> 1103.76 | J51: =PL!J14 -> 1103.76 | K51: =PL!K14 -> 1103.76 | ... M51: =PL!M14 -> 1103.76
B52: Galv. Charges | D52: =PL!D15 -> 45.738 | E52: =PL!E15 -> 213.444 | F52: =PL!F15 -> 274.428 | G52: =PL!G15 -> 335.412 | H52: =PL!H15 -> 396.396 | I52: =PL!I15 -> 457.38 | J52: =PL!J15 -> 457.38 | K52: =PL!K15 -> 457.38 | ... M52: =PL!M15 -> 457.38
B53: Power Cost | D53: =PL!D16 -> 5.184 | E53: =PL!E16 -> 24.192 | F53: =PL!F16 -> 31.104 | G53: =PL!G16 -> 38.016 | H53: =PL!H16 -> 44.928 | I53: =PL!I16 -> 51.84 | J53: =PL!J16 -> 51.84 | K53: =PL!K16 -> 51.84 | ... M53: =PL!M16 -> 51.84
B54: Fabrication Cost | D54: =PL!D17 -> 8.1 | E54: =PL!E17 -> 37.8 | F54: =PL!F17 -> 48.6 | G54: =PL!G17 -> 59.4 | H54: =PL!H17 -> 70.2 | I54: =PL!I17 -> 81 | J54: =PL!J17 -> 81 | K54: =PL!K17 -> 81 | ... M54: =PL!M17 -> 81
B55: Consumable | D55: =PL!D18 -> 4.158 | E55: =PL!E18 -> 19.404 | F55: =PL!F18 -> 24.948 | G55: =PL!G18 -> 30.492 | H55: =PL!H18 -> 36.036 | I55: =PL!I18 -> 41.58 | J55: =PL!J18 -> 41.58 | K55: =PL!K18 -> 41.58 | ... M55: =PL!M18 -> 41.58
B56: Testing & Maint | D56: =PL!D19 -> 2.079 | E56: =PL!E19 -> 9.702 | F56: =PL!F19 -> 12.474 | G56: =PL!G19 -> 15.246 | H56: =PL!H19 -> 18.018 | I56: =PL!I19 -> 20.79 | J56: =PL!J19 -> 20.79 | K56: =PL!K19 -> 20.79 | ... M56: =PL!M19 -> 20.79
B57: Interest on WC | D57: =PL!D37+PL!D38 -> 3.535705 | E57: =PL!E37+PL!E38 -> 15.252189 | F57: =PL!F37+PL!F38 -> 19.446029 | G57: =PL!G37+PL!G38 -> 23.781066 | H57: =PL!H37+PL!H38 -> 28.117678 | I57: =PL!I37+PL!I38 -> 32.455999 | J57: =PL!J37+PL!J38 -> 32.761523 | K57: =PL!K37+PL!K38 -> 32.789573 | ... M57: =PL!M37+PL!M38 -> 32.852398
B58: Stock Adjustments | D58: =PL!D24-PL!D25+PL!D28-PL!D29 -> -41.10275 | E58: =PL!E24-PL!E25+PL!E28-PL!E29 -> -6.54355 | F58: =PL!F24-PL!F25+PL!F28-PL!F29 -> -12.900859 | G58: =PL!G24-PL!G25+PL!G28-PL!G29 -> -12.917027 | H58: =PL!H24-PL!H25+PL!H28-PL!H29 -> -12.934539 | I58: =PL!I24-PL!I25+PL!I28-PL!I29 -> -12.953517 | J58: =PL!J24-PL!J25+PL!J28-PL!J29 -> -0.28934322 | K58: =PL!K24-PL!K25+PL!K28-PL!K29 -> -0.31166161 | ... M58: =PL!M24-PL!M25+PL!M28-PL!M29 -> -0.3621751
B59: Contribution | D59: =D49-D50 -> 22.823965 | E59: =E49-E50 -> 156.37782 | F59: =F49-F50 -> 199.52135 | G59: =G49-G50 -> 244.84504 | H59: =H49-H50 -> 290.1685 | I59: =I49-I50 -> 335.49172 | J59: =J49-J50 -> 339.84702 | K59: =K49-K50 -> 339.84129 | ... M59: =M49-M50 -> 339.82898
B60: Fixed Cost: | D60: =SUM(D61:D65) -> 24.177312 | E60: =SUM(E61:E65) -> 110.25342 | F60: =SUM(F61:F65) -> 121.10534 | G60: =SUM(G61:G65) -> 132.4707 | H60: =SUM(H61:H65) -> 144.15937 | I60: =SUM(I61:I65) -> 156.19841 | J60: =SUM(J61:J65) -> 160.62238 | K60: =SUM(K61:K65) -> 164.78542 | ... M60: =SUM(M61:M65) -> 175.19088
B61: Salary & Wages | D61: =PL!D20 -> 9.57 | E61: =PL!E20 -> 40.194 | F61: =PL!F20 -> 42.2037 | G61: =PL!G20 -> 44.313885 | H61: =PL!H20 -> 46.529579 | I61: =PL!I20 -> 48.856058 | J61: =PL!J20 -> 51.298861 | K61: =PL!K20 -> 53.863804 | ... M61: =PL!M20 -> 59.384844
B62: Factory Rent | D62: =PL!D21 -> 4.5 | E62: =PL!E21 -> 19.8 | F62: =PL!F21 -> 21.78 | G62: =PL!G21 -> 23.958 | H62: =PL!H21 -> 26.3538 | I62: =PL!I21 -> 28.98918 | J62: =PL!J21 -> 31.888098 | K62: =PL!K21 -> 35.076908 | ... M62: =PL!M21 -> 42.443058
B63: Administrative Overheads & Selling Exp | D63: =PL!D27 -> 4.8267576 | E63: =PL!E27 -> 29.541494 | F63: =PL!F27 -> 37.796296 | G63: =PL!G27 -> 46.310972 | H63: =PL!H27 -> 54.825649 | I63: =PL!I27 -> 63.340326 | J63: =PL!J27 -> 63.860076 | K63: =PL!K27 -> 63.860076 | ... M63: =PL!M27 -> 63.860076
B64: Interest on Term Loan | D64: =PL!D36 -> 2.875 | E64: =PL!E36 -> 11.095703 | F64: =PL!F36 -> 9.703125 | G64: =PL!G36 -> 8.265625 | H64: =PL!H36 -> 6.828125 | I64: =PL!I36 -> 5.390625 | J64: =PL!J36 -> 3.953125 | K64: =PL!K36 -> 2.515625 | ... M64: =PL!M36 -> 0.044921875
B65: Depreciation | D65: =PL!D33 -> 2.4055545 | E65: =PL!E33 -> 9.6222181 | F65: =PL!F33 -> 9.6222181 | G65: =PL!G33 -> 9.6222181 | H65: =PL!H33 -> 9.6222181 | I65: =PL!I33 -> 9.6222181 | J65: =PL!J33 -> 9.6222181 | K65: =PL!K33 -> 9.4690032 | ... M65: =PL!M33 -> 9.4579796
B66: Cash Fixed Cost | D66: =D60-D65 -> 21.771758 | E66: =E60-E65 -> 100.6312 | F66: =F60-F65 -> 111.48312 | G66: =G60-G65 -> 122.84848 | H66: =H60-H65 -> 134.53715 | I66: =I60-I65 -> 146.57619 | J66: =J60-J65 -> 151.00016 | K66: =K60-K65 -> 155.31641 | ... M66: =M60-M65 -> 165.7329
B67: PV Ratio | D67: =D59/D49 -> 0.14185899 | E67: =E59/E49 -> 0.15880492 | F67: =F59/F49 -> 0.1583658 | G67: =G59/G49 -> 0.15860931 | H67: =H59/H49 -> 0.15877705 | I67: =I59/I49 -> 0.15889959 | J67: =J59/J49 -> 0.15965234 | K67: =K59/K49 -> 0.15964965 | ... M67: =M59/M49 -> 0.15964386
B68: BREAK EVEN:
B69: Sales | D69: =D60/D67 -> 170.43201 | E69: =E60/E67 -> 694.26951 | F69: =F60/F67 -> 764.71903 | G69: =G60/G67 -> 835.20131 | H69: =H60/H67 -> 907.9358 | I69: =I60/I67 -> 983.00072 | J69: =J60/J67 -> 1006.0759 | K69: =K60/K67 -> 1032.169 | ... M69: =M60/M67 -> 1097.3856
B70: Capacity | D70: =D69/D49*CoP!E9 -> 0.3177885 | E70: =E69/E49*CoP!F9 -> 0.24676578 | F70: =F69/F49*CoP!G9 -> 0.27314071 | G70: =G69/G49*CoP!H9 -> 0.29757141 | H70: =H69/H49*CoP!I9 -> 0.3229282 | I70: =I69/I49*CoP!J9 -> 0.34918539 | J70: =J69/J49*CoP!K9 -> 0.35447356 | K70: =K69/K49*CoP!L9 -> 0.363667 | ... M70: =M69/M49*CoP!N9 -> 0.38664496
B71: Average break even | D71: =AVERAGE(D70:M70) -> 0.32863272
B72: Cash Break Even:
B73: Sales | D73: =D66/D67 -> 153.47464 | E73: =E66/E67 -> 633.67807 | F73: =F66/F67 -> 703.95958 | G73: =G66/G67 -> 774.53514 | H73: =H66/H67 -> 847.33373 | I73: =I66/I67 -> 922.44538 | J73: =J66/J67 -> 945.80612 | K73: =K66/K67 -> 972.85785 | ... M73: =M66/M67 -> 1038.1414
B74: Capacity | D74: =D73/D49*CoP!E9 -> 0.2861697 | E74: =E73/E49*CoP!F9 -> 0.22522963 | F74: =F73/F49*CoP!G9 -> 0.25143878 | G74: =G73/G49*CoP!H9 -> 0.27595685 | H74: =H73/H49*CoP!I9 -> 0.30137368 | I74: =I73/I49*CoP!J9 -> 0.32767468 | J74: =J73/J49*CoP!K9 -> 0.33323853 | K74: =K73/K49*CoP!L9 -> 0.34276974 | ... M74: =M73/M49*CoP!N9 -> 0.36577127
B75: Average cash break even | D75: =AVERAGE(D74:M74) -> 0.30629112
D76: =D49-D50-D60-PL!D39 -> -1.7763568e-14 | E76: =E49-E50-E60-PL!E39 -> -6.3948846e-14 | F76: =F49-F50-F60-PL!F39 -> -2.4158453e-13 | G76: =G49-G50-G60-PL!G39 -> 0 | H76: =H49-H50-H60-PL!H39 -> 7.9580786e-13 | I76: =I49-I50-I60-PL!I39 -> 0 | J76: =J49-J50-J60-PL!J39 -> 0 | K76: =K49-K50-K60-PL!K39 -> 0 | ... M76: =M49-M50-M60-PL!M39 -> 0

Sheet KFR
B2: Key Financial Indicators
B4: FY Ending | D4: =PL!D4 -> 44286 | E4: =PL!E4 -> 44651 | F4: =PL!F4 -> 45016 | G4: =PL!G4 -> 45382 | H4: =PL!H4 -> 45747 | I4: =PL!I4 -> 46112 | J4: =PL!J4 -> 46477 | K4: =PL!K4 -> 46843 | ... M4: =PL!M4 -> 47573
B5: Net Sales | D5: =PL!D10 -> 160.89192 | E5: =PL!E10 -> 984.71646 | F5: =PL!F10 -> 1259.8765 | G5: =PL!G10 -> 1543.6991 | H5: =PL!H10 -> 1827.5216 | I5: =PL!I10 -> 2111.3442 | J5: =PL!J10 -> 2128.6692 | K5: =PL!K10 -> 2128.6692 | ... M5: =PL!M10 -> 2128.6692
B6: Gross Sales
B7: Total Expenses | D7: =PL!D30 -> 153.42901 | E7: =PL!E30 -> 902.62194 | F7: =PL!F30 -> 1142.6891 | G7: =PL!G30 -> 1389.6558 | H7: =PL!H30 -> 1636.9445 | I7: =PL!I30 -> 1884.582 | J7: =PL!J30 -> 1903.1077 | K7: =PL!K30 -> 1908.8391 | ... M7: =PL!M30 -> 1921.6758
B8: EBITDA | D8: =PL!D31 -> 7.4629124 | E8: =PL!E31 -> 82.094516 | F8: =PL!F31 -> 117.18738 | G8: =PL!G31 -> 154.04325 | H8: =PL!H31 -> 190.57715 | I8: =PL!I31 -> 226.76215 | J8: =PL!J31 -> 225.56151 | K8: =PL!K31 -> 219.83007 | ... M8: =PL!M31 -> 206.9934
B9: Depreciation | D9: =PL!D33 -> 2.4055545 | E9: =PL!E33 -> 9.6222181 | F9: =PL!F33 -> 9.6222181 | G9: =PL!G33 -> 9.6222181 | H9: =PL!H33 -> 9.6222181 | I9: =PL!I33 -> 9.6222181 | J9: =PL!J33 -> 9.6222181 | K9: =PL!K33 -> 9.4690032 | ... M9: =PL!M33 -> 9.4579796
B10: EBIT | D10: =PL!D34 -> 5.0573579 | E10: =PL!E34 -> 72.472298 | F10: =PL!F34 -> 107.56517 | G10: =PL!G34 -> 144.42103 | H10: =PL!H34 -> 180.95493 | I10: =PL!I34 -> 217.13994 | J10: =PL!J34 -> 215.93929 | K10: =PL!K34 -> 210.36107 | ... M10: =PL!M34 -> 197.53542
B11: Interest
B12: - Term Loan | D12: =PL!D36 -> 2.875 | E12: =PL!E36 -> 11.095703 | F12: =PL!F36 -> 9.703125 | G12: =PL!G36 -> 8.265625 | H12: =PL!H36 -> 6.828125 | I12: =PL!I36 -> 5.390625 | J12: =PL!J36 -> 3.953125 | K12: =PL!K36 -> 2.515625 | ... M12: =PL!M36 -> 0.044921875
B13: - Working Capital | D13: =PL!D37 -> 1.9642805 | E13: =PL!E37 -> 12.710158 | F13: =PL!F37 -> 16.205024 | G13: =PL!G37 -> 19.817555 | H13: =PL!H37 -> 23.431398 | I13: =PL!I37 -> 27.046666 | J13: =PL!J37 -> 27.30127 | K13: =PL!K37 -> 27.324644 | ... M13: =PL!M37 -> 27.376998
B14: Bank Charges | D14: =PL!D38 -> 1.5714244 | E14: =PL!E38 -> 2.5420316 | F14: =PL!F38 -> 3.2410048 | G14: =PL!G38 -> 3.9635109 | H14: =PL!H38 -> 4.6862797 | I14: =PL!I38 -> 5.4093331 | J14: =PL!J38 -> 5.4602539 | K14: =PL!K38 -> 5.4649288 | ... M14: =PL!M38 -> 5.4753997
B15: PBT | D15: =PL!D39 -> -1.3533471 | E15: =PL!E39 -> 46.124405 | F15: =PL!F39 -> 78.416011 | G15: =PL!G39 -> 112.37434 | H15: =PL!H39 -> 146.00913 | I15: =PL!I39 -> 179.29331 | J15: =PL!J39 -> 179.22464 | K15: =PL!K39 -> 175.05587 | ... M15: =PL!M39 -> 164.6381
B16: Tax
B17: - Current Tax | D17: =PL!D41 -> 0 | E17: =PL!E41 -> 6.5522222 | F17: =PL!F41 -> 17.942274 | G17: =PL!G41 -> 27.138693 | H17: =PL!H41 -> 36.144593 | I17: =PL!I41 -> 44.976612 | J17: =PL!J41 -> 45.344412 | K17: =PL!K41 -> 44.583381 | ... M17: =PL!M41 -> 42.472157
B18: - Deferred Tax | D18: =PL!D42 -> 0 | E18: =PL!E42 -> 5.0563682 | F18: =PL!F42 -> 1.7934679 | G18: =PL!G42 -> 1.1436815 | H18: =PL!H42 -> 0.60298432 | I18: =PL!I42 -> 0.14792856 | J18: =PL!J42 -> -0.23715456 | K18: =PL!K42 -> -0.52531878 | ... M18: =PL!M42 -> -1.0360406
B19: PAT | D19: =PL!D43 -> -1.3533471 | E19: =PL!E43 -> 34.515815 | F19: =PL!F43 -> 58.680269 | G19: =PL!G43 -> 84.091967 | H19: =PL!H43 -> 109.26155 | I19: =PL!I43 -> 134.16877 | J19: =PL!J43 -> 134.11738 | K19: =PL!K43 -> 130.99781 | ... M19: =PL!M43 -> 123.20198
B20: Cash Accruals | D20: =D19+D9+D18 -> 1.0522074 | E20: =E19+E9+E18 -> 49.194401 | F20: =F19+F9+F18 -> 70.095955 | G20: =G19+G9+G18 -> 94.857866 | H20: =H19+H9+H18 -> 119.48675 | I20: =I19+I9+I18 -> 143.93892 | J20: =J19+J9+J18 -> 143.50245 | K20: =K19+K9+K18 -> 139.94149 | ... M20: =M19+M9+M18 -> 131.62392
B21: Paid up Capital | D21: =BS!D7 -> 63.186241 | E21: =BS!E7 -> 63.186241 | F21: =BS!F7 -> 63.186241 | G21: =BS!G7 -> 63.186241 | H21: =BS!H7 -> 63.186241 | I21: =BS!I7 -> 63.186241 | J21: =BS!J7 -> 63.186241 | K21: =BS!K7 -> 63.186241 | ... M21: =BS!M7 -> 63.186241
B22: Reserves & Surplus | D22: =BS!D8 -> -1.3533471 | E22: =BS!E8 -> 33.162468 | F22: =BS!F8 -> 91.842737 | G22: =BS!G8 -> 175.9347 | H22: =BS!H8 -> 285.19626 | I22: =BS!I8 -> 419.36503 | J22: =BS!J8 -> 553.48241 | K22: =BS!K8 -> 684.48022 | ... M22: =BS!M8 -> 935.11923
B23: Unsecured Loan | D23: =BS!D9 -> 0 | E23: =BS!E9 -> 0 | F23: =BS!F9 -> 0 | G23: =BS!G9 -> 0 | H23: =BS!H9 -> 0 | I23: =BS!I9 -> 0 | J23: =BS!J9 -> 0 | K23: =BS!K9 -> 0 | ... M23: =BS!M9 -> 0
B24: Term Loans | D24: =BS!D11+BS!D16 -> 115 | E24: =BS!E11+BS!E16 -> 104.21875 | F24: =BS!F11+BS!F16 -> 89.84375 | G24: =BS!G11+BS!G16 -> 75.46875 | H24: =BS!H11+BS!H16 -> 61.09375 | I24: =BS!I11+BS!I16 -> 46.71875 | J24: =BS!J11+BS!J16 -> 32.34375 | K24: =BS!K11+BS!K16 -> 17.96875 | ... M24: =BS!M11+BS!M16 -> 3.4194869e-14
B25: Current Liabilities (with CMLTB) | D25: =BS!D13 -> 135.34247 | E25: =BS!E13 -> 184.78383 | F25: =BS!F13 -> 232.37974 | G25: =BS!G13 -> 280.76905 | H25: =BS!H13 -> 329.17148 | I25: =BS!I13 -> 377.58816 | J25: =BS!J13 -> 379.3677 | K25: =BS!K13 -> 379.60144 | ... M25: =BS!M13 -> 365.74998
B26: Current Assets | D26: =BS!D23 -> 151.80384 | E26: =BS!E23 -> 236.0646 | F26: =BS!F23 -> 339.38146 | G26: =BS!G23 -> 468.25363 | H26: =BS!H23 -> 621.76783 | I26: =BS!I23 -> 799.74842 | J26: =BS!J23 -> 930.6554 | K26: =BS!K23 -> 1056.4556 | ... M26: =BS!M23 -> 1306.7293
B27: Fixed Assets | D27: =BS!D22 -> 149.59028 | E27: =BS!E22 -> 139.96806 | F27: =BS!F22 -> 130.34584 | G27: =BS!G22 -> 120.72362 | H27: =BS!H22 -> 111.10141 | I27: =BS!I22 -> 101.47919 | J27: =BS!J22 -> 91.85697 | K27: =BS!K22 -> 82.387967 | ... M27: =BS!M22 -> 63.472007
B28: Current Ratio | D28: =D26/D25 -> 1.1216275 | E28: =E26/E25 -> 1.2775176 | F28: =F26/F25 -> 1.4604606 | G28: =G26/G25 -> 1.6677538 | H28: =H26/H25 -> 1.8888873 | I28: =I26/I25 -> 2.1180442 | J28: =J26/J25 -> 2.4531751 | K28: =K26/K25 -> 2.7830654 | ... M28: =M26/M25 -> 3.5727391
B29: Current Ratio (w/o TL instl due 1 yr)
B30: Interest Coverage Ratio | D30: =D10/SUM(D12:D14) -> 0.78889262 | E30: =E10/SUM(E12:E14) -> 2.7505918 | F30: =F10/SUM(F12:F14) -> 3.6901642 | G30: =G10/SUM(G12:G14) -> 4.5065818 | H30: =H10/SUM(H12:H14) -> 5.1781592 | I30: =I10/SUM(I12:I14) -> 5.7373661 | J30: =J10/SUM(J12:J14) -> 5.8815568 | K30: =K10/SUM(K12:K14) -> 5.9583597 | ... M30: =M10/SUM(M12:M14) -> 6.0046052
B31: EBITDA/Interest (times) | D31: =D8/SUM(D12:D14) -> 1.1641329 | E31: =E8/SUM(E12:E14) -> 3.1157906 | F31: =F8/SUM(F12:F14) -> 4.020267 | G31: =G8/SUM(G12:G14) -> 4.806838 | H31: =H8/SUM(H12:H14) -> 5.4535061 | I31: =I8/SUM(I12:I14) -> 5.9916085 | J31: =J8/SUM(J12:J14) -> 6.143638 | K31: =K8/SUM(K12:K14) -> 6.226564 | ... M31: =M8/SUM(M12:M14) -> 6.2921052
B32: Total Tangible Assets | D32: =D27 -> 149.59028 | E32: =E27 -> 139.96806 | F32: =F27 -> 130.34584 | G32: =G27 -> 120.72362 | H32: =H27 -> 111.10141 | I32: =I27 -> 101.47919 | J32: =J27 -> 91.85697 | K32: =K27 -> 82.387967 | ... M32: =M27 -> 63.472007
B33: EBITDA/TTA(ROCE) % | D33: =D8/D32 -> 0.04988902 | E33: =E8/E32 -> 0.58652321 | F33: =F8/F32 -> 0.89904964 | G33: =G8/G32 -> 1.2759992 | H33: =H8/H32 -> 1.7153442 | I33: =I8/I32 -> 2.2345681 | J33: =J8/J32 -> 2.4555731 | K33: =K8/K32 -> 2.6682304 | ... M33: =M8/M32 -> 3.2611761
B34: FACR (Fixed Assets / Term Loans) | D34: =D27/D24 -> 1.300785 | E34: =E27/E24 -> 1.3430219 | F34: =F27/F24 -> 1.4508059 | G34: =G27/G24 -> 1.5996505 | H34: =H27/H24 -> 1.8185396 | I34: =I27/I24 -> 2.1721298 | J34: =J27/J24 -> 2.8400223 | K34: =K27/K24 -> 4.5850695 | ... M34: =M27/M24 -> 1.8561851e+15
B35: ACR
B36: Net Worth | D36: =SUM(D21:D23) -> 61.832894 | E36: =SUM(E21:E23) -> 96.348709 | F36: =SUM(F21:F23) -> 155.02898 | G36: =SUM(G21:G23) -> 239.12094 | H36: =SUM(H21:H23) -> 348.3825 | I36: =SUM(I21:I23) -> 482.55127 | J36: =SUM(J21:J23) -> 616.66865 | K36: =SUM(K21:K23) -> 747.66646 | ... M36: =SUM(M21:M23) -> 998.30547
B37: TNW (including DTL)
B38: TOL
B39: TOL/TNW
B40: Debt Equity Ratio | D40: =D24/D36 -> 1.8598515 | E40: =E24/E36 -> 1.0816829 | F40: =F24/F36 -> 0.57952875 | G40: =G24/G36 -> 0.31560912 | H40: =H24/H36 -> 0.17536401 | I40: =I24/I36 -> 0.096816138 | J40: =J24/J36 -> 0.052449156 | K40: =K24/K36 -> 0.02403311 | ... M40: =M24/M36 -> 3.4252912e-17
B41: EBITDA Margin (%) | D41: =D8/D5 -> 0.046384631 | E41: =E8/E5 -> 0.083368685 | F41: =F8/F5 -> 0.093014975 | G41: =G8/G5 -> 0.099788392 | H41: =H8/H5 -> 0.10428175 | I41: =I8/I5 -> 0.10740179 | J41: =J8/J5 -> 0.10596363 | K41: =K8/K5 -> 0.10327113 | ... M41: =M8/M5 -> 0.097240753
B42: Net Profit Margin (%) | D42: =D19/D5 -> -0.0084115294 | E42: =E19/E5 -> 0.035051526 | F42: =F19/F5 -> 0.046576207 | G42: =G19/G5 -> 0.054474326 | H42: =H19/H5 -> 0.059786735 | I42: =I19/I5 -> 0.063546612 | J42: =J19/J5 -> 0.063005273 | K42: =K19/K5 -> 0.061539769 | ... M42: =M19/M5 -> 0.057877467
B43: DSCR | D43: =Ratio!D14 -> 1.3659852 | E43: =Ratio!E14 -> 2.755873 | F43: =Ratio!F14 -> 3.3141734 | G43: =Ratio!G14 -> 4.5547988 | H43: =Ratio!H14 -> 5.9573709 | I43: =Ratio!I14 -> 7.5550124 | J43: =Ratio!J14 -> 8.0453168 | K43: =Ratio!K14 -> 8.4340941 | ... M43: =Ratio!M14 -> 9.0557497
B44: Average DSCR | D44: =Ratio!C15 -> 5.8939786
B45: Minimum DSCR | D45: =Ratio!C16 -> 1.3659852
B46: Average OPM | D46: =AVERAGE(D41:M41) -> 0.094108521
B47: Average NPM | D47: =AVERAGE(D42:M42) -> 0.049331338
B50: Movement of TNW | D50: =D4 -> 44286 | E50: =E4 -> 44651 | F50: =F4 -> 45016 | G50: =G4 -> 45382 | H50: =H4 -> 45747 | I50: =I4 -> 46112 | J50: =J4 -> 46477 | K50: =K4 -> 46843 | ... M50: =M4 -> 47573
B51: Opening TNW
B52: Add/Subtract PAT
B53: Inc/Dec in DTL
B54: Inc/dec in Equity
B55: Closing TNW
B57: Security Cover | D57: =D50 -> 44286 | E57: =E50 -> 44651 | F57: =F50 -> 45016 | G57: =G50 -> 45382 | H57: =H50 -> 45747 | I57: =I50 -> 46112 | J57: =J50 -> 46477 | K57: =K50 -> 46843 | ... M57: =M50 -> 47573
B58: Net Fixed Assets
B59: Term Loan Outstanding
B60: Security Margin
B61: Security Margin (%)

Sheet Sensitivity
D2: Sensitivity Analysis
D4: Particulars | E4: Factor | F4: IRR | G4: Avg DSCR | H4: Min DSCR
D5: Base Case | F5: =Ratio!C32 -> 0.58365602 | G5: =Ratio!C15 -> 5.8939786 | H5: =Ratio!C16 -> 1.3659852
D6: Increase in Project Cost by 5% | F6: =E19 -> 0.56155034 | G6: =F19 -> 5.9019213 | H6: =G19 -> 1.3659852
D7: Increase in Raw Material Prices by 5% | F7: =E24 -> 0.42644404 | G7: =F24 -> 4.2393925 | H7: =G24 -> -0.058624207
D8: Increase in Operating Cost by 5% | F8: =E29 -> 0.48715344 | G8: =F29 -> 4.8694108 | H8: =G29 -> 0.46865029
D9: Decrease in Selling Prices by 5% | F9: =E34 -> 0.27724874 | G9: =F34 -> 2.7868169 | H9: =G34 -> -1.217726
D10: Increase in Interest Rate by 2% | F10: =E38 -> 0.5659195 | G10: =F38 -> 5.4042639 | H10: =G38 -> 1.0244497
D11: Decrease in Capacity Utilisation by 5% | F11: =E44 -> 0.50170062 | G11: =F44 -> 5.201237 | H11: =G44 -> 0.493429
E14: IRR | F14: Avg DSCR | G14: Min DSCR
D16: Increase in Project Cost | E16: =F5 -> 0.58365602 | F16: =G5 -> 5.8939786 | G16: =H5 -> 1.3659852
D17: 0.03 | E17: 0.57017299 | F17: 5.8987442 | G17: 1.3659852
D18: 0.04 | E18: 0.56582637 | F18: 5.9003328 | G18: 1.3659852
D19: 0.05 | E19: 0.56155034 | F19: 5.9019213 | G19: 1.3659852
D21: Increase in Raw Material Prices | E21: =F5 -> 0.58365602 | F21: =G5 -> 5.8939786 | G21: =H5 -> 1.3659852
D22: 0.03 | E22: 0.49027553 | F22: 4.9012269 | G22: 0.51121955
D23: 0.04 | E23: 0.4586996 | F23: 4.5703097 | G23: 0.22629767
D24: 0.05 | E24: 0.42644404 | F24: 4.2393925 | G24: -0.058624207
D26: Increase in Operating Costs | E26: =F5 -> 0.58365602 | F26: =G5 -> 5.8939786 | G26: =H5 -> 1.3659852
D27: 0.03 | E27: 0.52595926 | F27: 5.2792379 | G27: 0.82758425
D28: 0.04 | E28: 0.5065997 | F28: 5.0743243 | G28: 0.64811727
D29: 0.05 | E29: 0.48715344 | F29: 4.8694108 | G29: 0.46865029
D31: Decrase in Selling Prices | E31: =F5 -> 0.58365602 | F31: =G5 -> 5.8939786 | G31: =H5 -> 1.3659852
D32: -0.03 | E32: 0.40588365 | F32: 4.0296816 | G32: -0.1842415
D33: -0.04 | E33: 0.34312222 | F33: 3.4082493 | G33: -0.70098373
D34: -0.05 | E34: 0.27724874 | F34: 2.7868169 | G34: -1.217726
D36: Increase in Interest Rates | E36: =F5 -> 0.58365602 | F36: =G5 -> 5.8939786 | G36: =H5 -> 1.3659852
D37: 0.01 | E37: 0.57477605 | F37: 5.6417509 | G37: 1.1796931
D38: 0.02 | E38: 0.5659195 | F38: 5.4042639 | G38: 1.0244497
D39: 0.03 | E39: 0.5570851 | F39: 5.1802619 | G39: 0.89308983
D41: Decrease in Capacity Utilization | E41: =F5 -> 0.58365602 | F41: =G5 -> 5.8939786 | G41: =H5 -> 1.3659852
D42: -0.03 | E42: 0.53405892 | F42: 5.4783336 | G42: 0.84245147
D43: -0.04 | E43: 0.51781115 | F43: 5.3397853 | G43: 0.66794024
D44: -0.05 | E44: 0.50170062 | F44: 5.201237 | G44: 0.493429

Sheet Sheet2
C2: 100000
C3: 3
C4: 0.1
B5: EMI | C5: =PMT(C4/12,C3*12,-C2) -> 3226.7187
C7: =C5 -> 3226.7187 | D7: 2 | E7: 3 | F7: 4 | G7: 5 | H7: 6
C8: 0.09 | D8: 4568.4742 | E8: 3179.9733 | F8: 2488.5042 | G8: 2075.8355 | H8: 1802.5537
C9: 0.1 | D9: 4614.4926 | E9: 3226.7187 | F9: 2536.2583 | G9: 2124.7045 | H9: 1852.5838
C10: 0.11 | D10: 4660.7838 | E10: 3273.8717 | F10: 2584.5523 | G10: 2174.2423 | H10: 1903.4079
C11: 0.12 | D11: 4707.3472 | E11: 3321.431 | F11: 2633.3835 | G11: 2224.4448 | H11: 1955.0193
D14: =C5 -> 3226.7187
C15: 0.09 | D15: 3179.9733
C16: 0.1 | D16: 3226.7187
C17: 0.11 | D17: 3273.8717
C18: 0.12 | D18: 3321.431

Sheet Sheet1
C1: ABC (Companies Act) | E1: ABC (IT Act) | I1: CA | J1: IT
B2: Revenue | C2: 1000 | E2: 1000 | H2: 1000 | I2: 0.2 | J2: 0.3
B3: Less: Expenses | C3: 500 | E3: 500 | H3: =200 -> 200
B4: EBITDA | C4: =C2-C3 -> 500 | E4: =E2-E3 -> 500
B5: Less: Dep | C5: =H2*I2 -> 200 | E5: =H2*J2 -> 300
B6: EBIT | C6: =C4-C5 -> 300 | E6: =E4-E5 -> 200
B7: Less: Int | C7: 100 | E7: 100
B8: EBT | C8: =C6-C7 -> 200 | E8: =E6-E7 -> 100
A9: 0.2 | B9: Less: Tax | C9: =C8*A9 -> 40 | E9: =E8*A9 -> 20
B10: PAT | C10: =C8-C9 -> 160 | E10: =E8-E9 -> 80
C12: ABC (Companies Act)
B13: Revenue | C13: 1000
B14: Less: Expenses | C14: 500
B15: EBITDA | C15: =C13-C14 -> 500
B16: Less: Dep | C16: =C5 -> 200
B17: EBIT | C17: =C15-C16 -> 300
B18: Less: Int | C18: 100
B19: EBT | C19: =C17-C18 -> 200
B20: Less: Current Tax | C20: =E9 -> 20
B21: Less: Defeered Tax | C21: =C9-E9 -> 20
B22: PAT | C22: =C19-C20-C21 -> 160
B25: Asset Value | C25: 1000
B26: Residual Value | C26: =5%*C25 -> 50
B27: SLM | C27: =1/C29 -> 0.1
B28: WDV | C28: =((C26/C25)^(1/10)-1)*-1 -> 0.25886555
B29: Life | C29: 10
C31: 1000
C32: SLM | D32: WDV
B33: 1 | C33: =($C$31-$C$26)*$C$27 -> 95 | D33: =$C$31*$C$28 -> 258.86555 | E33: =C31-D33 -> 741.13445
B34: 2 | C34: =C33 -> 95 | D34: =E33*$C$28 -> 191.85418 | E34: =E33-D34 -> 549.28027
B35: 3 | C35: =C34 -> 95 | D35: =E34*$C$28 -> 142.18974 | E35: =E34-D35 -> 407.09053
B36: 4 | C36: =C35 -> 95 | D36: =E35*$C$28 -> 105.38171 | E36: =E35-D36 -> 301.70882
B37: 5 | C37: =C36 -> 95 | D37: =E36*$C$28 -> 78.102019 | E37: =E36-D37 -> 223.6068
B38: 6 | C38: =C37 -> 95 | D38: =E37*$C$28 -> 57.884097 | E38: =E37-D38 -> 165.7227
B39: 7 | C39: =C38 -> 95 | D39: =E38*$C$28 -> 42.899898 | E39: =E38-D39 -> 122.8228
B40: 8 | C40: =C39 -> 95 | D40: =E39*$C$28 -> 31.794592 | E40: =E39-D40 -> 91.02821
B41: 9 | C41: =C40 -> 95 | D41: =E40*$C$28 -> 23.564068 | E41: =E40-D41 -> 67.464142
B42: 10 | C42: =C41 -> 95 | D42: =E41*$C$28 -> 17.464142 | E42: =E41-D42 -> 50
C43: =SUM(C33:C42) -> 950 | D43: =SUM(D33:D42) -> 950
