Workbook
Name UPDATE: 'Data Sheet'!$E$1

Sheet Profit & Loss
A1: ='Data Sheet'!B1 -> MAHINDRA & MAHINDRA LTD | H1: =UPDATE | M1: SCREENER.IN
A3: Narration | B3: ='Data Sheet'!B16 -> 42460 | C3: ='Data Sheet'!C16 -> 42825 | D3: ='Data Sheet'!D16 -> 43190 | E3: ='Data Sheet'!E16 -> 43555 | F3: ='Data Sheet'!F16 -> 43921 | G3: ='Data Sheet'!G16 -> 44286 | H3: ='Data Sheet'!H16 -> 44651 | I3: ='Data Sheet'!I16 -> 45016 | ... K3: ='Data Sheet'!K16 -> 45747 | L3: Trailing | M3: Best Case | N3: Worst Case
A4: Sales | B4: ='Data Sheet'!B17 -> 75841.42 | C4: ='Data Sheet'!C17 -> 83773.05 | D4: ='Data Sheet'!D17 -> 92093.95 | E4: ='Data Sheet'!E17 -> 104720.68 | F4: ='Data Sheet'!F17 -> 75381.93 | G4: ='Data Sheet'!G17 -> 74277.78 | H4: ='Data Sheet'!H17 -> 90170.57 | I4: ='Data Sheet'!I17 -> 121268.55 | ... K4: ='Data Sheet'!K17 -> 159210.82 | L4: =SUM(Quarters!H4:K4) -> 186333.92 | M4: =$K4+M23*K4 -> 192431.06 | N4: =$K4+N23*L4 -> 174367.59
A5: Expenses | B5: =SUM('Data Sheet'!B18,'Data Sheet'!B20:B24, -1*'Data Sheet'!B19) -> 65758.98 | C5: =SUM('Data Sheet'!C18,'Data Sheet'!C20:C24, -1*'Data Sheet'!C19) -> 73038.22 | D5: =SUM('Data Sheet'!D18,'Data Sheet'!D20:D24, -1*'Data Sheet'!D19) -> 78867.85 | E5: =SUM('Data Sheet'!E18,'Data Sheet'!E20:E24, -1*'Data Sheet'!E19) -> 89514.17 | F5: =SUM('Data Sheet'!F18,'Data Sheet'!F20:F24, -1*'Data Sheet'!F19) -> 65224.18 | G5: =SUM('Data Sheet'!G18,'Data Sheet'!G20:G24, -1*'Data Sheet'!G19) -> 62790.76 | H5: =SUM('Data Sheet'!H18,'Data Sheet'!H20:H24, -1*'Data Sheet'!H19) -> 75487.72 | I5: =SUM('Data Sheet'!I18,'Data Sheet'!I20:I24, -1*'Data Sheet'!I19) -> 100983.26 | ... K5: =SUM('Data Sheet'!K18,'Data Sheet'!K20:K24, -1*'Data Sheet'!K19) -> 128692.63 | L5: =SUM(Quarters!H5:K5) -> 151094.89 | M5: =M4-M6 -> 156038.95 | N5: =N4-N6 -> 146684.68
A6: Operating Profit | B6: =B4-B5 -> 10082.44 | C6: =C4-C5 -> 10734.83 | D6: =D4-D5 -> 13226.1 | E6: =E4-E5 -> 15206.51 | F6: =F4-F5 -> 10157.75 | G6: =G4-G5 -> 11487.02 | H6: =H4-H5 -> 14682.85 | I6: =I4-I5 -> 20285.29 | ... K6: =K4-K5 -> 30518.19 | L6: =SUM(Quarters!H6:K6) -> 35239.03 | M6: =M4*M24 -> 36392.106 | N6: =N4*N24 -> 27682.908
A7: Other Income | B7: ='Data Sheet'!B25 -> 1398.83 | C7: ='Data Sheet'!C25 -> 2076.61 | D7: ='Data Sheet'!D25 -> 4366.41 | E7: ='Data Sheet'!E25 -> 2676.45 | F7: ='Data Sheet'!F25 -> 884.69 | G7: ='Data Sheet'!G25 -> 1151.51 | H7: ='Data Sheet'!H25 -> 3204.47 | I7: ='Data Sheet'!I25 -> 3961.45 | ... K7: ='Data Sheet'!K25 -> 3718.47 | L7: =SUM(Quarters!H7:K7) -> 4646.53 | M7: 0 | N7: 0
A8: Depreciation | B8: ='Data Sheet'!B26 -> 2441.65 | C8: ='Data Sheet'!C26 -> 2812.72 | D8: ='Data Sheet'!D26 -> 3279.9 | E8: ='Data Sheet'!E26 -> 3990.77 | F8: ='Data Sheet'!F26 -> 3366.68 | G8: ='Data Sheet'!G26 -> 3378.11 | H8: ='Data Sheet'!H26 -> 3507.5 | I8: ='Data Sheet'!I26 -> 4356.81 | ... K8: ='Data Sheet'!K26 -> 6073.65 | L8: =SUM(Quarters!H8:K8) -> 7408.06 | M8: =+$L8 -> 7408.06 | N8: =+$L8 -> 7408.06
A9: Interest | B9: ='Data Sheet'!B27 -> 3367.59 | C9: ='Data Sheet'!C27 -> 3648.46 | D9: ='Data Sheet'!D27 -> 3987.09 | E9: ='Data Sheet'!E27 -> 5021.35 | F9: ='Data Sheet'!F27 -> 6021.15 | G9: ='Data Sheet'!G27 -> 6102.22 | H9: ='Data Sheet'!H27 -> 5018.05 | I9: ='Data Sheet'!I27 -> 5829.7 | ... K9: ='Data Sheet'!K27 -> 9083.39 | L9: =SUM(Quarters!H9:K9) -> 9580.04 | M9: =+$L9 -> 9580.04 | N9: =+$L9 -> 9580.04
A10: Profit before tax | B10: ='Data Sheet'!B28 -> 5672.03 | C10: ='Data Sheet'!C28 -> 6350.26 | D10: ='Data Sheet'!D28 -> 10325.52 | E10: ='Data Sheet'!E28 -> 8870.84 | F10: ='Data Sheet'!F28 -> 1654.61 | G10: ='Data Sheet'!G28 -> 3158.2 | H10: ='Data Sheet'!H28 -> 9361.77 | I10: ='Data Sheet'!I28 -> 14060.23 | ... K10: ='Data Sheet'!K28 -> 19079.62 | L10: =SUM(Quarters!H10:K10) -> 22897.46 | M10: =M6+M7-SUM(M8:M9) -> 19404.006 | N10: =N6+N7-SUM(N8:N9) -> 10694.808
A11: Tax | B11: ='Data Sheet'!B29 -> 2117.53 | C11: ='Data Sheet'!C29 -> 2299.73 | D11: ='Data Sheet'!D29 -> 2367.73 | E11: ='Data Sheet'!E29 -> 2853.99 | F11: ='Data Sheet'!F29 -> 1975.61 | G11: ='Data Sheet'!G29 -> 1645.81 | H11: ='Data Sheet'!H29 -> 2108.76 | I11: ='Data Sheet'!I29 -> 2685.75 | ... K11: ='Data Sheet'!K29 -> 5006.45 | L11: =SUM(Quarters!H11:K11) -> 5993.81 | M11: =IF($L10>0,$L11/$L10,0) -> 0.26176746 | N11: =IF($L10>0,$L11/$L10,0) -> 0.26176746
A12: Net profit | B12: ='Data Sheet'!B30 -> 3148.43 | C12: ='Data Sheet'!C30 -> 3698.04 | D12: ='Data Sheet'!D30 -> 7510.39 | E12: ='Data Sheet'!E30 -> 5315.46 | F12: ='Data Sheet'!F30 -> 127.04 | G12: ='Data Sheet'!G30 -> 1812.49 | H12: ='Data Sheet'!H30 -> 6577.32 | I12: ='Data Sheet'!I30 -> 10281.5 | ... K12: ='Data Sheet'!K30 -> 12929.1 | L12: =SUM(Quarters!H12:K12) -> 15726.45 | M12: =M10-M11*M10 -> 14324.669 | N12: =N10-N11*N10 -> 7895.2552
A13: EPS | B13: =IF('Data Sheet'!B93>0,B12/'Data Sheet'!B93,0) -> 25.345597 | C13: =IF('Data Sheet'!C93>0,C12/'Data Sheet'!C93,0) -> 29.770085 | D13: =IF('Data Sheet'!D93>0,D12/'Data Sheet'!D93,0) -> 60.41176 | E13: =IF('Data Sheet'!E93>0,E12/'Data Sheet'!E93,0) -> 42.756274 | F13: =IF('Data Sheet'!F93>0,F12/'Data Sheet'!F93,0) -> 1.021879 | G13: =IF('Data Sheet'!G93>0,G12/'Data Sheet'!G93,0) -> 14.579231 | H13: =IF('Data Sheet'!H93>0,H12/'Data Sheet'!H93,0) -> 52.906371 | I13: =IF('Data Sheet'!I93>0,I12/'Data Sheet'!I93,0) -> 82.681946 | ... K13: =IF('Data Sheet'!K93>0,K12/'Data Sheet'!K93,0) -> 103.97346 | L13: =IF('Data Sheet'!$B6>0,'Profit & Loss'!L12/'Data Sheet'!$B6,0) -> 126.46631 | M13: =IF('Data Sheet'!$B6>0,'Profit & Loss'!M12/'Data Sheet'!$B6,0) -> 115.1937 | N13: =IF('Data Sheet'!$B6>0,'Profit & Loss'!N12/'Data Sheet'!$B6,0) -> 63.490728
A14: Price to earning | B14: =IF(B15>0,B15/B13,"") -> 23.883833 | C14: =IF(C15>0,C15/C13,"") -> 21.613979 | D14: =IF(D15>0,D15/D13,"") -> 12.231062 | E14: =IF(E15>0,E15/E13,"") -> 15.761429 | F14: =IF(F15>0,F15/F13,"") -> 278.84906 | G14: =IF(G15>0,G15/G13,"") -> 54.546773 | H14: =IF(H15>0,H15/H13,"") -> 15.244856 | I14: =IF(I15>0,I15/I13,"") -> 14.013942 | ... K14: =IF(K15>0,K15/K13,"") -> 25.639235 | L14: =IF(L13>0,L15/L13,0) -> 24.49269 | M14: =M25 -> 24.49269 | N14: =N25 -> 21.337015
A15: Price | B15: ='Data Sheet'!B90 -> 605.35 | C15: ='Data Sheet'!C90 -> 643.45 | D15: ='Data Sheet'!D90 -> 738.9 | E15: ='Data Sheet'!E90 -> 673.9 | F15: ='Data Sheet'!F90 -> 284.95 | G15: ='Data Sheet'!G90 -> 795.25 | H15: ='Data Sheet'!H90 -> 806.55 | I15: ='Data Sheet'!I90 -> 1158.7 | ... K15: ='Data Sheet'!K90 -> 2665.8 | L15: ='Data Sheet'!B8 -> 3097.5 | M15: =M13*M14 -> 2821.4035 | N15: =N13*N14 -> 1354.7026
A17: RATIOS:
A18: Dividend Payout | B18: =IF('Data Sheet'!B30>0, 'Data Sheet'!B31/'Data Sheet'!B30, 0) -> 0.20612178 | C18: =IF('Data Sheet'!C30>0, 'Data Sheet'!C31/'Data Sheet'!C30, 0) -> 0.21833999 | D18: =IF('Data Sheet'!D30>0, 'Data Sheet'!D31/'Data Sheet'!D30, 0) -> 0.10847639 | E18: =IF('Data Sheet'!E30>0, 'Data Sheet'!E31/'Data Sheet'!E30, 0) -> 0.17396989 | F18: =IF('Data Sheet'!F30>0, 'Data Sheet'!F31/'Data Sheet'!F30, 0) -> 2.050614 | G18: =IF('Data Sheet'!G30>0, 'Data Sheet'!G31/'Data Sheet'!G30, 0) -> 0.53600847 | H18: =IF('Data Sheet'!H30>0, 'Data Sheet'!H31/'Data Sheet'!H30, 0) -> 0.19529231 | I18: =IF('Data Sheet'!I30>0, 'Data Sheet'!I31/'Data Sheet'!I30, 0) -> 0.17601128 | ... K18: =IF('Data Sheet'!K30>0, 'Data Sheet'!K31/'Data Sheet'!K30, 0) -> 0.21844057
A19: OPM | B19: =IF(B6>0,B6/B4,0) -> 0.13294108 | C19: =IF(C6>0,C6/C4,0) -> 0.12814181 | D19: =IF(D6>0,D6/D4,0) -> 0.1436153 | E19: =IF(E6>0,E6/E4,0) -> 0.14521019 | F19: =IF(F6>0,F6/F4,0) -> 0.13475046 | G19: =IF(G6>0,G6/G4,0) -> 0.15464948 | H19: =IF(H6>0,H6/H4,0) -> 0.16283417 | I19: =IF(I6>0,I6/I4,0) -> 0.16727577 | ... L19: =IF(L6>0,L6/L4,0) -> 0.18911763
G22: TRENDS: | H22: 10 YEARS | I22: 7 YEARS | J22: 5 YEARS | K22: 3 YEARS | L22: RECENT | M22: BEST | N22: WORST
G23: Sales Growth | H23: =IF(B4=0,"",POWER($K4/B4,1/9)-1) -> 0.085888228 | I23: =IF(D4=0,"",POWER($K4/D4,1/7)-1) -> 0.081341992 | J23: =IF(F4=0,"",POWER($K4/F4,1/5)-1) -> 0.16129101 | K23: =IF(H4=0,"",POWER($K4/H4, 1/3)-1) -> 0.20865565 | L23: =IF(ISERROR(MAX(IF(J4=0,"",(K4-J4)/J4),IF(K4=0,"",(L4-K4)/K4))),"",MAX(IF(J4=0,"",(K4-J4)/J4),IF(K4=0,"",(L4-K4)/K4))) -> 0.17035965 | M23: =MAX(K23:L23) -> 0.20865565 | N23: =MIN(H23:L23) -> 0.081341992
G24: OPM | H24: =IF(SUM(B4:$K$4)=0,"",SUMPRODUCT(B19:$K$19,B4:$K$4)/SUM(B4:$K$4)) -> 0.15876177 | I24: =IF(SUM(E4:$K$4)=0,"",SUMPRODUCT(E19:$K$19,E4:$K$4)/SUM(E4:$K$4)) -> 0.16650714 | J24: =IF(SUM(G4:$K$4)=0,"",SUMPRODUCT(G19:$K$19,G4:$K$4)/SUM(G4:$K$4)) -> 0.17442506 | K24: =IF(SUM(I4:$K$4)=0, "", SUMPRODUCT(I19:$K$19,I4:$K$4)/SUM(I4:$K$4)) -> 0.18041719 | L24: =L19 -> 0.18911763 | M24: =MAX(K24:L24) -> 0.18911763 | N24: =MIN(H24:L24) -> 0.15876177
G25: Price to Earning | H25: =IF(ISERROR(AVERAGEIF(B14:$L14,">0")),"",AVERAGEIF(B14:$L14,">0")) -> 46.134459 | I25: =IF(ISERROR(AVERAGEIF(E14:$L14,">0")),"",AVERAGEIF(E14:$L14,">0")) -> 56.218772 | J25: =IF(ISERROR(AVERAGEIF(G14:$L14,">0")),"",AVERAGEIF(G14:$L14,">0")) -> 25.856615 | K25: =IF(ISERROR(AVERAGEIF(I14:$L14,">0")),"",AVERAGEIF(I14:$L14,">0")) -> 21.337015 | L25: =L14 -> 24.49269 | M25: =MAX(K25:L25) -> 24.49269 | N25: =MIN(H25:L25) -> 21.337015

Sheet Quarters
A1: ='Profit & Loss'!A1 -> MAHINDRA & MAHINDRA LTD | E1: =UPDATE | J1: SCREENER.IN
A3: Narration | B3: ='Data Sheet'!B41 -> 45199 | C3: ='Data Sheet'!C41 -> 45291 | D3: ='Data Sheet'!D41 -> 45382 | E3: ='Data Sheet'!E41 -> 45473 | F3: ='Data Sheet'!F41 -> 45565 | G3: ='Data Sheet'!G41 -> 45657 | H3: ='Data Sheet'!H41 -> 45747 | I3: ='Data Sheet'!I41 -> 45838 | ... K3: ='Data Sheet'!K41 -> 46022
A4: Sales | B4: ='Data Sheet'!B42 -> 34435.52 | C4: ='Data Sheet'!C42 -> 35299.39 | D4: ='Data Sheet'!D42 -> 35451.73 | E4: ='Data Sheet'!E42 -> 37217.72 | F4: ='Data Sheet'!F42 -> 37923.74 | G4: ='Data Sheet'!G42 -> 41470.05 | H4: ='Data Sheet'!H42 -> 42599.31 | I4: ='Data Sheet'!I42 -> 45529.19 | ... K4: ='Data Sheet'!K42 -> 52099.75
A5: Expenses | B5: ='Data Sheet'!B43 -> 28705.94 | C5: ='Data Sheet'!C43 -> 29075.41 | D5: ='Data Sheet'!D43 -> 28847.82 | E5: ='Data Sheet'!E43 -> 29974.6 | F5: ='Data Sheet'!F43 -> 30790.34 | G5: ='Data Sheet'!G43 -> 33239.32 | H5: ='Data Sheet'!H43 -> 34688.37 | I5: ='Data Sheet'!I43 -> 37301.39 | ... K5: ='Data Sheet'!K43 -> 41939.37
A6: Operating Profit | B6: ='Data Sheet'!B50 -> 5729.58 | C6: ='Data Sheet'!C50 -> 6223.98 | D6: ='Data Sheet'!D50 -> 6603.91 | E6: ='Data Sheet'!E50 -> 7243.12 | F6: ='Data Sheet'!F50 -> 7133.4 | G6: ='Data Sheet'!G50 -> 8230.73 | H6: ='Data Sheet'!H50 -> 7910.94 | I6: ='Data Sheet'!I50 -> 8227.8 | ... K6: ='Data Sheet'!K50 -> 10160.38
A7: Other Income | B7: ='Data Sheet'!B44 -> 811.95 | C7: ='Data Sheet'!C44 -> 755.69 | D7: ='Data Sheet'!D44 -> 750.44 | E7: ='Data Sheet'!E44 -> 733.21 | F7: ='Data Sheet'!F44 -> 1125.57 | G7: ='Data Sheet'!G44 -> 718.59 | H7: ='Data Sheet'!H44 -> 1141.1 | I7: ='Data Sheet'!I44 -> 1395.06 | ... K7: ='Data Sheet'!K44 -> 976.43
A8: Depreciation | B8: ='Data Sheet'!B45 -> 1138.64 | C8: ='Data Sheet'!C45 -> 1122.59 | D8: ='Data Sheet'!D45 -> 1335.05 | E8: ='Data Sheet'!E45 -> 1247.77 | F8: ='Data Sheet'!F45 -> 1301.99 | G8: ='Data Sheet'!G45 -> 1495.17 | H8: ='Data Sheet'!H45 -> 2028.72 | I8: ='Data Sheet'!I45 -> 1547.56 | ... K8: ='Data Sheet'!K45 -> 2162.89
A9: Interest | B9: ='Data Sheet'!B46 -> 1835.19 | C9: ='Data Sheet'!C46 -> 1944.88 | D9: ='Data Sheet'!D46 -> 1989.3 | E9: ='Data Sheet'!E46 -> 2107.69 | F9: ='Data Sheet'!F46 -> 2217.02 | G9: ='Data Sheet'!G46 -> 2362.16 | H9: ='Data Sheet'!H46 -> 2396.52 | I9: ='Data Sheet'!I46 -> 2431.19 | ... K9: ='Data Sheet'!K46 -> 2405.3
A10: Profit before tax | B10: ='Data Sheet'!B47 -> 3567.7 | C10: ='Data Sheet'!C47 -> 3912.2 | D10: ='Data Sheet'!D47 -> 4030 | E10: ='Data Sheet'!E47 -> 4620.87 | F10: ='Data Sheet'!F47 -> 4739.96 | G10: ='Data Sheet'!G47 -> 5091.99 | H10: ='Data Sheet'!H47 -> 4626.8 | I10: ='Data Sheet'!I47 -> 5644.11 | ... K10: ='Data Sheet'!K47 -> 6568.62
A11: Tax | B11: ='Data Sheet'!B48 -> 1083.73 | C11: ='Data Sheet'!C48 -> 935.16 | D11: ='Data Sheet'!D48 -> 905.06 | E11: ='Data Sheet'!E48 -> 1075.09 | F11: ='Data Sheet'!F48 -> 1378.9 | G11: ='Data Sheet'!G48 -> 1467.51 | H11: ='Data Sheet'!H48 -> 1084.95 | I11: ='Data Sheet'!I48 -> 1267.53 | ... K11: ='Data Sheet'!K48 -> 1547.15
A12: Net profit | B12: ='Data Sheet'!B49 -> 2347.75 | C12: ='Data Sheet'!C49 -> 2658.4 | D12: ='Data Sheet'!D49 -> 2754.08 | E12: ='Data Sheet'!E49 -> 3282.63 | F12: ='Data Sheet'!F49 -> 3170.72 | G12: ='Data Sheet'!G49 -> 3180.58 | H12: ='Data Sheet'!H49 -> 3295.17 | I12: ='Data Sheet'!I49 -> 4083.32 | ... K12: ='Data Sheet'!K49 -> 4674.64
A14: OPM | B14: =IF(B4>0,B6/B4,"") -> 0.16638576 | C14: =IF(C4>0,C6/C4,"") -> 0.17631976 | D14: =IF(D4>0,D6/D4,"") -> 0.18627892 | E14: =IF(E4>0,E6/E4,"") -> 0.19461482 | F14: =IF(F4>0,F6/F4,"") -> 0.18809854 | G14: =IF(G4>0,G6/G4,"") -> 0.19847408 | H14: =IF(H4>0,H6/H4,"") -> 0.18570582 | I14: =IF(I4>0,I6/I4,"") -> 0.18071483 | ... K14: =IF(K4>0,K6/K4,"") -> 0.19501783

Sheet Balance Sheet
A1: ='Profit & Loss'!A1 -> MAHINDRA & MAHINDRA LTD | E1: =UPDATE | J1: SCREENER.IN
A3: Narration | B3: ='Data Sheet'!B56 -> 42460 | C3: ='Data Sheet'!C56 -> 42825 | D3: ='Data Sheet'!D56 -> 43190 | E3: ='Data Sheet'!E56 -> 43555 | F3: ='Data Sheet'!F56 -> 43921 | G3: ='Data Sheet'!G56 -> 44286 | H3: ='Data Sheet'!H56 -> 44651 | I3: ='Data Sheet'!I56 -> 45016 | ... K3: ='Data Sheet'!K56 -> 45747
A4: Equity Share Capital | B4: ='Data Sheet'!B57 -> 270.4 | C4: ='Data Sheet'!C57 -> 310.55 | D4: ='Data Sheet'!D57 -> 543.13 | E4: ='Data Sheet'!E57 -> 543.96 | F4: ='Data Sheet'!F57 -> 554.28 | G4: ='Data Sheet'!G57 -> 555.15 | H4: ='Data Sheet'!H57 -> 556.06 | I4: ='Data Sheet'!I57 -> 556.82 | ... K4: ='Data Sheet'!K57 -> 558.15
A5: Reserves | B5: ='Data Sheet'!B58 -> 26222.25 | C5: ='Data Sheet'!C58 -> 29467.1 | D5: ='Data Sheet'!D58 -> 36232.06 | E5: ='Data Sheet'!E58 -> 39439.45 | F5: ='Data Sheet'!F58 -> 39415.03 | G5: ='Data Sheet'!G58 -> 41026.77 | H5: ='Data Sheet'!H58 -> 46566.58 | I5: ='Data Sheet'!I58 -> 55808.97 | ... K5: ='Data Sheet'!K58 -> 76480.71
A6: Borrowings | B6: ='Data Sheet'!B59 -> 41552.93 | C6: ='Data Sheet'!C59 -> 48761.91 | D6: ='Data Sheet'!D59 -> 55897.92 | E6: ='Data Sheet'!E59 -> 70848.3 | F6: ='Data Sheet'!F59 -> 82092.28 | G6: ='Data Sheet'!G59 -> 80624.83 | H6: ='Data Sheet'!H59 -> 77605.21 | I6: ='Data Sheet'!I59 -> 92246.85 | ... K6: ='Data Sheet'!K59 -> 129024.58
A7: Other Liabilities | B7: ='Data Sheet'!B60 -> 31806.24 | C7: ='Data Sheet'!C60 -> 35295.92 | D7: ='Data Sheet'!D60 -> 43696.2 | E7: ='Data Sheet'!E60 -> 51056.95 | F7: ='Data Sheet'!F60 -> 43654.54 | G7: ='Data Sheet'!G60 -> 42761.58 | H7: ='Data Sheet'!H60 -> 47660.64 | I7: ='Data Sheet'!I60 -> 55670.49 | ... K7: ='Data Sheet'!K60 -> 69949.72
A8: Total | B8: ='Data Sheet'!B61 -> 99851.82 | C8: ='Data Sheet'!C61 -> 113835.48 | D8: ='Data Sheet'!D61 -> 136369.31 | E8: ='Data Sheet'!E61 -> 161888.66 | F8: ='Data Sheet'!F61 -> 165716.13 | G8: ='Data Sheet'!G61 -> 164968.33 | H8: ='Data Sheet'!H61 -> 172388.49 | I8: ='Data Sheet'!I61 -> 204283.13 | ... K8: ='Data Sheet'!K61 -> 276013.16
A10: Net Block | B10: ='Data Sheet'!B62 -> 20584.71 | C10: ='Data Sheet'!C62 -> 20989.01 | D10: ='Data Sheet'!D62 -> 26181.9 | E10: ='Data Sheet'!E62 -> 28982.74 | F10: ='Data Sheet'!F62 -> 29689.27 | G10: ='Data Sheet'!G62 -> 21379.68 | H10: ='Data Sheet'!H62 -> 26018.49 | I10: ='Data Sheet'!I62 -> 27139.98 | ... K10: ='Data Sheet'!K62 -> 34636.36
A11: Capital Work in Progress | B11: ='Data Sheet'!B63 -> 2371.35 | C11: ='Data Sheet'!C63 -> 4278.94 | D11: ='Data Sheet'!D63 -> 4269.47 | E11: ='Data Sheet'!E63 -> 4759.84 | F11: ='Data Sheet'!F63 -> 6856.48 | G11: ='Data Sheet'!G63 -> 7872.61 | H11: ='Data Sheet'!H63 -> 6702.81 | I11: ='Data Sheet'!I63 -> 3968.58 | ... K11: ='Data Sheet'!K63 -> 8297.64
A12: Investments | B12: ='Data Sheet'!B64 -> 11602.58 | C12: ='Data Sheet'!C64 -> 14662.44 | D12: ='Data Sheet'!D64 -> 16017.61 | E12: ='Data Sheet'!E64 -> 18268.1 | F12: ='Data Sheet'!F64 -> 19210.34 | G12: ='Data Sheet'!G64 -> 28777.66 | H12: ='Data Sheet'!H64 -> 30060.43 | I12: ='Data Sheet'!I64 -> 35272.42 | ... K12: ='Data Sheet'!K64 -> 41308.57
A13: Other Assets | B13: ='Data Sheet'!B65 -> 65293.18 | C13: ='Data Sheet'!C65 -> 73905.09 | D13: ='Data Sheet'!D65 -> 89900.33 | E13: ='Data Sheet'!E65 -> 109877.98 | F13: ='Data Sheet'!F65 -> 109960.04 | G13: ='Data Sheet'!G65 -> 106938.38 | H13: ='Data Sheet'!H65 -> 109606.76 | I13: ='Data Sheet'!I65 -> 137902.15 | ... K13: ='Data Sheet'!K65 -> 191770.59
A14: Total | B14: ='Data Sheet'!B66 -> 99851.82 | C14: ='Data Sheet'!C66 -> 113835.48 | D14: ='Data Sheet'!D66 -> 136369.31 | E14: ='Data Sheet'!E66 -> 161888.66 | F14: ='Data Sheet'!F66 -> 165716.13 | G14: ='Data Sheet'!G66 -> 164968.33 | H14: ='Data Sheet'!H66 -> 172388.49 | I14: ='Data Sheet'!I66 -> 204283.13 | ... K14: ='Data Sheet'!K66 -> 276013.16
A16: Working Capital | B16: =B13-B7 -> 33486.94 | C16: =C13-C7 -> 38609.17 | D16: =D13-D7 -> 46204.13 | E16: =E13-E7 -> 58821.03 | F16: =F13-F7 -> 66305.5 | G16: =G13-G7 -> 64176.8 | H16: =H13-H7 -> 61946.12 | I16: =I13-I7 -> 82231.66 | ... K16: =K13-K7 -> 121820.87
A17: Debtors | B17: ='Data Sheet'!B67 -> 5817.6 | C17: ='Data Sheet'!C67 -> 7199.26 | D17: ='Data Sheet'!D67 -> 8489.82 | E17: ='Data Sheet'!E67 -> 8677.89 | F17: ='Data Sheet'!F67 -> 6928.28 | G17: ='Data Sheet'!G67 -> 6007.76 | H17: ='Data Sheet'!H67 -> 6373.95 | I17: ='Data Sheet'!I67 -> 7028.02 | ... K17: ='Data Sheet'!K67 -> 8279.7
A18: Inventory | B18: ='Data Sheet'!B68 -> 9116.12 | C18: ='Data Sheet'!C68 -> 8886.01 | D18: ='Data Sheet'!D68 -> 9335.57 | E18: ='Data Sheet'!E68 -> 12200.16 | F18: ='Data Sheet'!F68 -> 11111.86 | G18: ='Data Sheet'!G68 -> 9615.41 | H18: ='Data Sheet'!H68 -> 11595.82 | I18: ='Data Sheet'!I68 -> 16854.97 | ... K18: ='Data Sheet'!K68 -> 20330.93
A20: Debtor Days | B20: =IF('Profit & Loss'!B4>0,'Balance Sheet'!B17/('Profit & Loss'!B4/365),0) -> 27.99821 | C20: =IF('Profit & Loss'!C4>0,'Balance Sheet'!C17/('Profit & Loss'!C4/365),0) -> 31.367246 | D20: =IF('Profit & Loss'!D4>0,'Balance Sheet'!D17/('Profit & Loss'!D4/365),0) -> 33.648077 | E20: =IF('Profit & Loss'!E4>0,'Balance Sheet'!E17/('Profit & Loss'!E4/365),0) -> 30.24646 | F20: =IF('Profit & Loss'!F4>0,'Balance Sheet'!F17/('Profit & Loss'!F4/365),0) -> 33.546796 | G20: =IF('Profit & Loss'!G4>0,'Balance Sheet'!G17/('Profit & Loss'!G4/365),0) -> 29.522051 | H20: =IF('Profit & Loss'!H4>0,'Balance Sheet'!H17/('Profit & Loss'!H4/365),0) -> 25.80101 | I20: =IF('Profit & Loss'!I4>0,'Balance Sheet'!I17/('Profit & Loss'!I4/365),0) -> 21.153278 | ... K20: =IF('Profit & Loss'!K4>0,'Balance Sheet'!K17/('Profit & Loss'!K4/365),0) -> 18.98169
A21: Inventory Turnover | B21: =IF('Balance Sheet'!B18>0,'Profit & Loss'!B4/'Balance Sheet'!B18,0) -> 8.3194846 | C21: =IF('Balance Sheet'!C18>0,'Profit & Loss'!C4/'Balance Sheet'!C18,0) -> 9.4275215 | D21: =IF('Balance Sheet'!D18>0,'Profit & Loss'!D4/'Balance Sheet'!D18,0) -> 9.8648449 | E21: =IF('Balance Sheet'!E18>0,'Profit & Loss'!E4/'Balance Sheet'!E18,0) -> 8.5835497 | F21: =IF('Balance Sheet'!F18>0,'Profit & Loss'!F4/'Balance Sheet'!F18,0) -> 6.7839165 | G21: =IF('Balance Sheet'!G18>0,'Profit & Loss'!G4/'Balance Sheet'!G18,0) -> 7.7248687 | H21: =IF('Balance Sheet'!H18>0,'Profit & Loss'!H4/'Balance Sheet'!H18,0) -> 7.7761271 | I21: =IF('Balance Sheet'!I18>0,'Profit & Loss'!I4/'Balance Sheet'!I18,0) -> 7.1948244 | ... K21: =IF('Balance Sheet'!K18>0,'Profit & Loss'!K4/'Balance Sheet'!K18,0) -> 7.8309659
A23: Return on Equity | B23: =IF(SUM('Balance Sheet'!B4:B5)>0,'Profit & Loss'!B12/SUM('Balance Sheet'!B4:B5),"") -> 0.11884164 | C23: =IF(SUM('Balance Sheet'!C4:C5)>0,'Profit & Loss'!C12/SUM('Balance Sheet'!C4:C5),"") -> 0.12418844 | D23: =IF(SUM('Balance Sheet'!D4:D5)>0,'Profit & Loss'!D12/SUM('Balance Sheet'!D4:D5),"") -> 0.20422437 | E23: =IF(SUM('Balance Sheet'!E4:E5)>0,'Profit & Loss'!E12/SUM('Balance Sheet'!E4:E5),"") -> 0.13294164 | F23: =IF(SUM('Balance Sheet'!F4:F5)>0,'Profit & Loss'!F12/SUM('Balance Sheet'!F4:F5),"") -> 0.0031784387 | G23: =IF(SUM('Balance Sheet'!G4:G5)>0,'Profit & Loss'!G12/SUM('Balance Sheet'!G4:G5),"") -> 0.043588415 | H23: =IF(SUM('Balance Sheet'!H4:H5)>0,'Profit & Loss'!H12/SUM('Balance Sheet'!H4:H5),"") -> 0.13957877 | I23: =IF(SUM('Balance Sheet'!I4:I5)>0,'Profit & Loss'!I12/SUM('Balance Sheet'!I4:I5),"") -> 0.18240674 | ... K23: =IF(SUM('Balance Sheet'!K4:K5)>0,'Profit & Loss'!K12/SUM('Balance Sheet'!K4:K5),"") -> 0.16782569
A24: Return on Capital Emp | C24: =IF((B4+B5+B6+C4+C5+C6)>0,('Profit & Loss'!C10+'Profit & Loss'!C9)*2/(B4+B5+B6+C4+C5+C6),"") -> 0.13642201 | D24: =IF((C4+C5+C6+D4+D5+D6)>0,('Profit & Loss'!D10+'Profit & Loss'!D9)*2/(C4+C5+C6+D4+D5+D6),"") -> 0.16719101 | E24: =IF((D4+D5+D6+E4+E5+E6)>0,('Profit & Loss'!E10+'Profit & Loss'!E9)*2/(D4+D5+D6+E4+E5+E6),"") -> 0.13652935 | F24: =IF((E4+E5+E6+F4+F5+F6)>0,('Profit & Loss'!F10+'Profit & Loss'!F9)*2/(E4+E5+E6+F4+F5+F6),"") -> 0.065916538 | G24: =IF((F4+F5+F6+G4+G5+G6)>0,('Profit & Loss'!G10+'Profit & Loss'!G9)*2/(F4+F5+F6+G4+G5+G6),"") -> 0.075821697 | H24: =IF((G4+G5+G6+H4+H5+H6)>0,('Profit & Loss'!H10+'Profit & Loss'!H9)*2/(G4+G5+G6+H4+H5+H6),"") -> 0.11646663 | I24: =IF((H4+H5+H6+I4+I5+I6)>0,('Profit & Loss'!I10+'Profit & Loss'!I9)*2/(H4+H5+H6+I4+I5+I6),"") -> 0.14553226 | J24: =IF((I4+I5+I6+J4+J5+J6)>0,('Profit & Loss'!J10+'Profit & Loss'!J9)*2/(I4+I5+I6+J4+J5+J6),"") -> 0.14509796 | K24: =IF((J4+J5+J6+K4+K5+K6)>0,('Profit & Loss'!K10+'Profit & Loss'!K9)*2/(J4+J5+J6+K4+K5+K6),"") -> 0.14787565

Sheet Cash Flow
A1: ='Balance Sheet'!A1 -> MAHINDRA & MAHINDRA LTD | E1: =UPDATE | J1: SCREENER.IN
A3: Narration | B3: ='Data Sheet'!B81 -> 42460 | C3: ='Data Sheet'!C81 -> 42825 | D3: ='Data Sheet'!D81 -> 43190 | E3: ='Data Sheet'!E81 -> 43555 | F3: ='Data Sheet'!F81 -> 43921 | G3: ='Data Sheet'!G81 -> 44286 | H3: ='Data Sheet'!H81 -> 44651 | I3: ='Data Sheet'!I81 -> 45016 | ... K3: ='Data Sheet'!K81 -> 45747
A4: Cash from Operating Activity | B4: ='Data Sheet'!B82 -> 2384.76 | C4: ='Data Sheet'!C82 -> 183.09 | D4: ='Data Sheet'!D82 -> 681.86 | E4: ='Data Sheet'!E82 -> -4347.29 | F4: ='Data Sheet'!F82 -> -1456.93 | G4: ='Data Sheet'!G82 -> 17908.83 | H4: ='Data Sheet'!H82 -> 9247.55 | I4: ='Data Sheet'!I82 -> -7074.02 | ... K4: ='Data Sheet'!K82 -> 3175.81
A5: Cash from Investing Activity | B5: ='Data Sheet'!B83 -> -5505.97 | C5: ='Data Sheet'!C83 -> -5875.29 | D5: ='Data Sheet'!D83 -> -5467.22 | E5: ='Data Sheet'!E83 -> -7173.97 | F5: ='Data Sheet'!F83 -> -6869.79 | G5: ='Data Sheet'!G83 -> -19685.5 | H5: ='Data Sheet'!H83 -> -3251.95 | I5: ='Data Sheet'!I83 -> -8866.27 | ... K5: ='Data Sheet'!K83 -> -18616.13
A6: Cash from Financing Activity | B6: ='Data Sheet'!B84 -> 2966.81 | C6: ='Data Sheet'!C84 -> 6107.97 | D6: ='Data Sheet'!D84 -> 6314.5 | E6: ='Data Sheet'!E84 -> 13193.63 | F6: ='Data Sheet'!F84 -> 6932.75 | G6: ='Data Sheet'!G84 -> 406.23 | H6: ='Data Sheet'!H84 -> -5882.6 | I6: ='Data Sheet'!I84 -> 15946.11 | ... K6: ='Data Sheet'!K84 -> 15834.11
A7: Net Cash Flow | B7: ='Data Sheet'!B85 -> -154.4 | C7: ='Data Sheet'!C85 -> 415.77 | D7: ='Data Sheet'!D85 -> 1529.14 | E7: ='Data Sheet'!E85 -> 1672.37 | F7: ='Data Sheet'!F85 -> -1393.97 | G7: ='Data Sheet'!G85 -> -1370.44 | H7: ='Data Sheet'!H85 -> 113 | I7: ='Data Sheet'!I85 -> 5.82 | ... K7: ='Data Sheet'!K85 -> 393.79

Sheet Data Sheet
A1: COMPANY NAME | B1: MAHINDRA & MAHINDRA LTD | E1: =IF(B2<>B3, "A NEW VERSION OF THE WORKSHEET IS AVAILABLE", "")
A2: LATEST VERSION | B2: 2.1 | E2: PLEASE DO NOT MAKE ANY CHANGES TO THIS SHEET
A3: CURRENT VERSION | B3: 2.1
A5: META
A6: Number of shares | B6: =IF(B9>0, B9/B8, 0) -> 124.35288
A7: Face Value | B7: 5
A8: Current Price | B8: 3097.5
A9: Market Capitalization | B9: 385183.06
A15: PROFIT & LOSS
A16: Report Date | B16: 42460 | C16: 42825 | D16: 43190 | E16: 43555 | F16: 43921 | G16: 44286 | H16: 44651 | I16: 45016 | J16: 45382 | K16: 45747
A17: Sales | B17: 75841.42 | C17: 83773.05 | D17: 92093.95 | E17: 104720.68 | F17: 75381.93 | G17: 74277.78 | H17: 90170.57 | I17: 121268.55 | J17: 139078.27 | K17: 159210.82
A18: Raw Material Cost | B18: 45584.35 | C18: 50655.2 | D18: 53457.29 | E18: 61881.19 | F18: 37595.3 | G18: 38271.2 | H18: 52664.85 | I18: 76019.87 | J18: 85070.07 | K18: 95754.9
A19: Change in Inventory | B19: 458.51 | C19: 13.83 | D19: -83.33 | E19: 1730.48 | F19: -826.62 | G19: -135.59 | H19: 861.66 | I19: 2032.31 | J19: 1455.32 | K19: 12.18
A20: Power and Fuel | B20: 639.97 | C20: 657.06 | D20: 733.9 | E20: 817.11 | F20: 530.92 | G20: 429.56 | H20: 541.27 | I20: 830.48 | J20: 752.73 | K20: 832.35
A21: Other Mfr. Exp | B21: 2618.7 | C21: 3255.3 | D21: 3590.26 | E21: 4253 | F21: 3277.79 | G21: 2523.4 | H21: 3124.27 | I21: 3838.42 | J21: 3791.75 | K21: 4162.28
A22: Employee Cost | B22: 7689.4 | C22: 8910.63 | D22: 10004.62 | E22: 11242.08 | F22: 8214.82 | G22: 7813.26 | H22: 8386.74 | I22: 9677.95 | J22: 10624.33 | K22: 11126.17
A23: Selling and admin | B23: 5758.86 | C23: 6253.64 | D23: 7591.15 | E23: 9658.98 | F23: 6316.52 | G23: 4628.75 | H23: 5977.67 | I23: 7681.87 | J23: 9832.2 | K23: 10811.4 | L23: =SUM(H23:K23) -> 34303.14 | M23: =SUM(L23,L24) -> 56512.99
A24: Other Expenses | B24: 3926.21 | C24: 3320.22 | D24: 3407.3 | E24: 3392.29 | F24: 8462.21 | G24: 8989 | H24: 5654.58 | I24: 4966.98 | J24: 5570.58 | K24: 6017.71 | L24: =SUM(H24:K24) -> 22209.85
A25: Other Income | B25: 1398.83 | C25: 2076.61 | D25: 4366.41 | E25: 2676.45 | F25: 884.69 | G25: 1151.51 | H25: 3204.47 | I25: 3961.45 | J25: 3297.85 | K25: 3718.47
A26: Depreciation | B26: 2441.65 | C26: 2812.72 | D26: 3279.9 | E26: 3990.77 | F26: 3366.68 | G26: 3378.11 | H26: 3507.5 | I26: 4356.81 | J26: 4723.78 | K26: 6073.65
A27: Interest | B27: 3367.59 | C27: 3648.46 | D27: 3987.09 | E27: 5021.35 | F27: 6021.15 | G27: 6102.22 | H27: 5018.05 | I27: 5829.7 | J27: 7488.21 | K27: 9083.39
A28: Profit before tax | B28: 5672.03 | C28: 6350.26 | D28: 10325.52 | E28: 8870.84 | F28: 1654.61 | G28: 3158.2 | H28: 9361.77 | I28: 14060.23 | J28: 15977.79 | K28: 19079.62
A29: Tax | B29: 2117.53 | C29: 2299.73 | D29: 2367.73 | E29: 2853.99 | F29: 1975.61 | G29: 1645.81 | H29: 2108.76 | I29: 2685.75 | J29: 3707.97 | K29: 5006.45
A30: Net profit | B30: 3148.43 | C30: 3698.04 | D30: 7510.39 | E30: 5315.46 | F30: 127.04 | G30: 1812.49 | H30: 6577.32 | I30: 10281.5 | J30: 11268.64 | K30: 12929.1
A31: Dividend Amount | B31: 648.96 | C31: 807.43 | D31: 814.7 | E31: 924.73 | F31: 260.51 | G31: 971.51 | H31: 1284.5 | I31: 1809.66 | J31: 2352.14 | K31: 2824.24
A40: Quarters
A41: Report Date | B41: 45199 | C41: 45291 | D41: 45382 | E41: 45473 | F41: 45565 | G41: 45657 | H41: 45747 | I41: 45838 | J41: 45930 | K41: 46022
A42: Sales | B42: 34435.52 | C42: 35299.39 | D42: 35451.73 | E42: 37217.72 | F42: 37923.74 | G42: 41470.05 | H42: 42599.31 | I42: 45529.19 | J42: 46105.67 | K42: 52099.75
A43: Expenses | B43: 28705.94 | C43: 29075.41 | D43: 28847.82 | E43: 29974.6 | F43: 30790.34 | G43: 33239.32 | H43: 34688.37 | I43: 37301.39 | J43: 37165.76 | K43: 41939.37
A44: Other Income | B44: 811.95 | C44: 755.69 | D44: 750.44 | E44: 733.21 | F44: 1125.57 | G44: 718.59 | H44: 1141.1 | I44: 1395.06 | J44: 1133.94 | K44: 976.43
A45: Depreciation | B45: 1138.64 | C45: 1122.59 | D45: 1335.05 | E45: 1247.77 | F45: 1301.99 | G45: 1495.17 | H45: 2028.72 | I45: 1547.56 | J45: 1668.89 | K45: 2162.89
A46: Interest | B46: 1835.19 | C46: 1944.88 | D46: 1989.3 | E46: 2107.69 | F46: 2217.02 | G46: 2362.16 | H46: 2396.52 | I46: 2431.19 | J46: 2347.03 | K46: 2405.3
A47: Profit before tax | B47: 3567.7 | C47: 3912.2 | D47: 4030 | E47: 4620.87 | F47: 4739.96 | G47: 5091.99 | H47: 4626.8 | I47: 5644.11 | J47: 6057.93 | K47: 6568.62
A48: Tax | B48: 1083.73 | C48: 935.16 | D48: 905.06 | E48: 1075.09 | F48: 1378.9 | G48: 1467.51 | H48: 1084.95 | I48: 1267.53 | J48: 2094.18 | K48: 1547.15
A49: Net profit | B49: 2347.75 | C49: 2658.4 | D49: 2754.08 | E49: 3282.63 | F49: 3170.72 | G49: 3180.58 | H49: 3295.17 | I49: 4083.32 | J49: 3673.32 | K49: 4674.64
A50: Operating Profit | B50: 5729.58 | C50: 6223.98 | D50: 6603.91 | E50: 7243.12 | F50: 7133.4 | G50: 8230.73 | H50: 7910.94 | I50: 8227.8 | J50: 8939.91 | K50: 10160.38
A55: BALANCE SHEET
A56: Report Date | B56: 42460 | C56: 42825 | D56: 43190 | E56: 43555 | F56: 43921 | G56: 44286 | H56: 44651 | I56: 45016 | J56: 45382 | K56: 45747
A57: Equity Share Capital | B57: 270.4 | C57: 310.55 | D57: 543.13 | E57: 543.96 | F57: 554.28 | G57: 555.15 | H57: 556.06 | I57: 556.82 | J57: 557.38 | K57: 558.15
A58: Reserves | B58: 26222.25 | C58: 29467.1 | D58: 36232.06 | E58: 39439.45 | F58: 39415.03 | G58: 41026.77 | H58: 46566.58 | I58: 55808.97 | J58: 65633.17 | K58: 76480.71
A59: Borrowings | B59: 41552.93 | C59: 48761.91 | D59: 55897.92 | E59: 70848.3 | F59: 82092.28 | G59: 80624.83 | H59: 77605.21 | I59: 92246.85 | J59: 108647.25 | K59: 129024.58
A60: Other Liabilities | B60: 31806.24 | C60: 35295.92 | D60: 43696.2 | E60: 51056.95 | F60: 43654.54 | G60: 42761.58 | H60: 47660.64 | I60: 55670.49 | J60: 59883.94 | K60: 69949.72
A61: Total | B61: 99851.82 | C61: 113835.48 | D61: 136369.31 | E61: 161888.66 | F61: 165716.13 | G61: 164968.33 | H61: 172388.49 | I61: 204283.13 | J61: 234721.74 | K61: 276013.16
A62: Net Block | B62: 20584.71 | C62: 20989.01 | D62: 26181.9 | E62: 28982.74 | F62: 29689.27 | G62: 21379.68 | H62: 26018.49 | I62: 27139.98 | J62: 28129.41 | K62: 34636.36
A63: Capital Work in Progress | B63: 2371.35 | C63: 4278.94 | D63: 4269.47 | E63: 4759.84 | F63: 6856.48 | G63: 7872.61 | H63: 6702.81 | I63: 3968.58 | J63: 8039.3 | K63: 8297.64
A64: Investments | B64: 11602.58 | C64: 14662.44 | D64: 16017.61 | E64: 18268.1 | F64: 19210.34 | G64: 28777.66 | H64: 30060.43 | I64: 35272.42 | J64: 35208.1 | K64: 41308.57
A65: Other Assets | B65: 65293.18 | C65: 73905.09 | D65: 89900.33 | E65: 109877.98 | F65: 109960.04 | G65: 106938.38 | H65: 109606.76 | I65: 137902.15 | J65: 163344.93 | K65: 191770.59
A66: Total | B66: 99851.82 | C66: 113835.48 | D66: 136369.31 | E66: 161888.66 | F66: 165716.13 | G66: 164968.33 | H66: 172388.49 | I66: 204283.13 | J66: 234721.74 | K66: 276013.16
A67: Receivables | B67: 5817.6 | C67: 7199.26 | D67: 8489.82 | E67: 8677.89 | F67: 6928.28 | G67: 6007.76 | H67: 6373.95 | I67: 7028.02 | J67: 7459.4 | K67: 8279.7
... A70: No. of Equity Shares | B70: 592633807 | C70: 621092384 | D70: 1243192544 | E70: 1243192544 | F70: 1243192544 | G70: 1110297953 | H70: 1112130815 | I70: 1198118224 | J70: 1114775772 | K70: 1116313361
A71: New Bonus Shares | D71: 621596272
A72: Face value | B72: 5 | C72: 5 | D72: 5 | E72: 5 | F72: 5 | G72: 5 | H72: 5 | I72: 5 | J72: 5 | K72: 5
A80: CASH FLOW:
A81: Report Date | B81: 42460 | C81: 42825 | D81: 43190 | E81: 43555 | F81: 43921 | G81: 44286 | H81: 44651 | I81: 45016 | J81: 45382 | K81: 45747
A82: Cash from Operating Activity | B82: 2384.76 | C82: 183.09 | D82: 681.86 | E82: -4347.29 | F82: -1456.93 | G82: 17908.83 | H82: 9247.55 | I82: -7074.02 | J82: -5629.95 | K82: 3175.81
A83: Cash from Investing Activity | B83: -5505.97 | C83: -5875.29 | D83: -5467.22 | E83: -7173.97 | F83: -6869.79 | G83: -19685.5 | H83: -3251.95 | I83: -8866.27 | J83: -5614.77 | K83: -18616.13
A84: Cash from Financing Activity | B84: 2966.81 | C84: 6107.97 | D84: 6314.5 | E84: 13193.63 | F84: 6932.75 | G84: 406.23 | H84: -5882.6 | I84: 15946.11 | J84: 12281.41 | K84: 15834.11
A85: Net Cash Flow | B85: -154.4 | C85: 415.77 | D85: 1529.14 | E85: 1672.37 | F85: -1393.97 | G85: -1370.44 | H85: 113 | I85: 5.82 | J85: 1036.69 | K85: 393.79
A90: PRICE: | B90: 605.35 | C90: 643.45 | D90: 738.9 | E90: 673.9 | F90: 284.95 | G90: 795.25 | H90: 806.55 | I90: 1158.7 | J90: 1921.35 | K90: 2665.8
A92: DERIVED:
A93: Adjusted Equity Shares in Cr | B93: 124.22 | C93: 124.22 | D93: 124.32 | E93: 124.32 | F93: 124.32 | G93: 124.32 | H93: 124.32 | I93: 124.35 | J93: 124.35 | K93: 124.35

Sheet cash flow 
C2: 42064 | D2: 42430 | E2: 42795 | F2: 43160 | G2: 43525 | H2: 43891 | I2: 44256 | J2: 44621 | K2: 44986 | L2: 45352 | M2: 45717 | N2: 46082
B3: Cash from Operating Activity - | C3: 1055 | D3: 2385 | E3: 183 | F3: 682 | G3: -4347 | H3: -1457 | I3: 17909 | J3: 9248 | K3: -7074 | L3: -5630 | M3: 3176 | N3: 11657
B4: Profit from operations | C4: 6454 | D4: 7595 | E4: 7911 | F4: 10159 | G4: 11112 | H4: 7774 | I4: 7588 | J4: 10515 | K4: 15642 | L4: 17541 | M4: 22050 | N4: 28938
B5: Receivables | C5: -575 | D5: 177 | E5: -8609 | F5: -11918 | G5: -13712 | H5: -1516 | I5: 4896 | J5: -2506 | K5: -21702 | L5: -21777 | M5: -20952 | N5: -3516
B6: Inventory | C6: -62 | D6: -1113 | E6: 241 | F6: -256 | G6: -2276 | H6: 1316 | I6: 226 | J6: -2173 | K6: -5252 | L6: -1753 | M6: -1646 | N6: -593
B7: Payables | C7: 1169 | D7: 1939 | E7: 2645 | F7: 5361 | G7: 3466 | H7: -6775 | I7: 7049 | J7: 4972 | K7: 7013 | L7: 4354 | M7: 8485 | N7: 8763
B8: Loans Advances | C8: -4229 | D8: 0 | E8: 0 | F8: 0 | G8: 0 | H8: 0 | I8: 0 | J8: 0 | K8: 0 | L8: 0 | M8: 0 | N8: 0
B9: Other WC items | C9: 0 | D9: -4241 | E9: 0 | F9: 0 | G9: 0 | H9: 0 | I9: 0 | J9: 0 | K9: 0 | L9: 0 | M9: 0 | N9: -15670
B10: Working capital changes | C10: -3698 | D10: -3238 | E10: -5724 | F10: -6813 | G10: -12522 | H10: -6974 | I10: 12171 | J10: 293 | K10: -19941 | L10: -19175 | M10: -14113 | N10: -11016
B11: Direct taxes | C11: -1701 | D11: -1973 | E11: -2005 | F11: -2664 | G11: -2937 | H11: -2257 | I11: -1850 | J11: -1560 | K11: -2775 | L11: -3996 | M11: -4761 | N11: -6265
B12: Cash from Investing Activity - | C12: -4357 | D12: -5506 | E12: -5875 | F12: -5467 | G12: -7174 | H12: -6870 | I12: -19686 | J12: -3252 | K12: -8866 | L12: -5615 | M12: -18616 | N12: -17707
B13: Fixed assets purchased | C13: -4759 | D13: -4172 | E13: -5026 | F13: -5906 | G13: -7340 | H13: -6896 | I13: -5989 | J13: -6040 | K13: -6305 | L13: -9946 | M13: -10392 | N13: -9605
B14: Fixed assets sold | C14: 43 | D14: 59 | E14: 63 | F14: 115 | G14: 142 | H14: 102 | I14: 1364 | J14: 120 | K14: 138 | L14: 273 | M14: 583 | N14: 493
... B34: CFO/OP | C34: 0.31 | D34: 0.43 | E34: 0.2 | F34: 0.25 | G34: -0.09 | H34: 0.08 | I34: 1.72 | J34: 0.74 | K34: -0.21 | L34: -0.07 | M34: 0.26 | N34: 0.48

Sheet historical sf 
A2: # | B2: =" historical fiancial statement " &'Data Sheet'!B1 -> historical fiancial statement MAHINDRA & MAHINDRA LTD
B4: years | C4: ='Data Sheet'!B16 -> 42460 | D4: ='Data Sheet'!C16 -> 42825 | E4: ='Data Sheet'!D16 -> 43190 | F4: ='Data Sheet'!E16 -> 43555 | G4: ='Data Sheet'!F16 -> 43921 | H4: ='Data Sheet'!G16 -> 44286 | I4: ='Data Sheet'!H16 -> 44651 | J4: ='Data Sheet'!I16 -> 45016 | ... L4: ='Data Sheet'!K16 -> 45747 | M4: ltm
A5: # | B5: income statement
B6: sales | C6: =IFERROR('Data Sheet'!B17,0) -> 75841.42 | D6: =IFERROR('Data Sheet'!C17,0) -> 83773.05 | E6: =IFERROR('Data Sheet'!D17,0) -> 92093.95 | F6: =IFERROR('Data Sheet'!E17,0) -> 104720.68 | G6: =IFERROR('Data Sheet'!F17,0) -> 75381.93 | H6: =IFERROR('Data Sheet'!G17,0) -> 74277.78 | I6: =IFERROR('Data Sheet'!H17,0) -> 90170.57 | J6: =IFERROR('Data Sheet'!I17,0) -> 121268.55 | ... L6: =IFERROR('Data Sheet'!K17,0) -> 159210.82 | M6: =IFERROR(SUM('Data Sheet'!B42:K42),0) -> 408132.07
B7: sales growth | C7: - | D7: =D6/C6-1 -> 0.10458177 | E7: =E6/D6-1 -> 0.099326693 | F7: =F6/E6-1 -> 0.13710705 | G7: =G6/F6-1 -> -0.28016195 | H7: =H6/G6-1 -> -0.01464741 | I7: =I6/H6-1 -> 0.21396426 | J7: =J6/I6-1 -> 0.34487949 | K7: =K6/J6-1 -> 0.14686182 | ... M7: =M6/L6-1 -> 1.5634694
B9: COGS | C9: =IFERROR(SUM('Data Sheet'!B18,'Data Sheet'!B20:B22)-1*'Data Sheet'!B19,0) -> 56073.91 | D9: =IFERROR(SUM('Data Sheet'!C18,'Data Sheet'!C20:C22)-1*'Data Sheet'!C19,0) -> 63464.36 | E9: =IFERROR(SUM('Data Sheet'!D18,'Data Sheet'!D20:D22)-1*'Data Sheet'!D19,0) -> 67869.4 | F9: =IFERROR(SUM('Data Sheet'!E18,'Data Sheet'!E20:E22)-1*'Data Sheet'!E19,0) -> 76462.9 | G9: =IFERROR(SUM('Data Sheet'!F18,'Data Sheet'!F20:F22)-1*'Data Sheet'!F19,0) -> 50445.45 | H9: =IFERROR(SUM('Data Sheet'!G18,'Data Sheet'!G20:G22)-1*'Data Sheet'!G19,0) -> 49173.01 | I9: =IFERROR(SUM('Data Sheet'!H18,'Data Sheet'!H20:H22)-1*'Data Sheet'!H19,0) -> 63855.47 | J9: =IFERROR(SUM('Data Sheet'!I18,'Data Sheet'!I20:I22)-1*'Data Sheet'!I19,0) -> 88334.41 | ... L9: =IFERROR(SUM('Data Sheet'!K18,'Data Sheet'!K20:K22)-1*'Data Sheet'!K19,0) -> 111863.52 | M9: =IFERROR(SUM('Data Sheet'!H43:K43),0) -> 151094.89 | N9: =_xlfn.FORMULATEXT(L9) -> =IFERROR(SUM('Data Sheet'!K18,'Data Sheet'!K20:K22)-1*'Data Sheet'!K19,0)
B10: COGS % sales | C10: =C9/C6 -> 0.73935733 | D10: =D9/D6 -> 0.7575749 | E10: =E9/E6 -> 0.73695829 | F10: =F9/F6 -> 0.73016046 | G10: =G9/G6 -> 0.66919818 | H10: =H9/H6 -> 0.66201507 | I10: =I9/I6 -> 0.7081631 | J10: =J9/J6 -> 0.72841978 | ... M10: =M9/M6 -> 0.37021078
B12: gross profit | C12: =C6-C9 -> 19767.51 | D12: =D6-D9 -> 20308.69 | E12: =E6-E9 -> 24224.55 | F12: =F6-F9 -> 28257.78 | G12: =G6-G9 -> 24936.48 | H12: =H6-H9 -> 25104.77 | I12: =I6-I9 -> 26315.1 | J12: =J6-J9 -> 32934.14 | ... M12: =M6-M9 -> 257037.18
B14: selling and gernal expnences | C14: =IFERROR(SUM('Data Sheet'!B23:B24),0) -> 9685.07 | D14: =IFERROR(SUM('Data Sheet'!C23:C24),0) -> 9573.86 | E14: =IFERROR(SUM('Data Sheet'!D23:D24),0) -> 10998.45 | F14: =IFERROR(SUM('Data Sheet'!E23:E24),0) -> 13051.27 | G14: =IFERROR(SUM('Data Sheet'!F23:F24),0) -> 14778.73 | H14: =IFERROR(SUM('Data Sheet'!G23:G24),0) -> 13617.75 | I14: =IFERROR(SUM('Data Sheet'!H23:H24),0) -> 11632.25 | J14: =IFERROR(SUM('Data Sheet'!I23:I24),0) -> 12648.85 | ... L14: =IFERROR(SUM('Data Sheet'!K23:K24),0) -> 16829.11 | M14: =IFERROR('Data Sheet'!M23,0) -> 56512.99
B15: s&g exp % sales | C15: =C14/C6 -> 0.12770159 | D15: =D14/D6 -> 0.11428329 | E15: =E14/E6 -> 0.11942641 | F15: =F14/F6 -> 0.12462935 | G15: =G14/G6 -> 0.19605136 | H15: =H14/H6 -> 0.18333545 | I15: =I14/I6 -> 0.12900273 | J15: =J14/J6 -> 0.10430445 | ... M15: =M14/M6 -> 0.13846741
B17: EBITA | C17: =C12-C14 -> 10082.44 | D17: =D12-D14 -> 10734.83 | E17: =E12-E14 -> 13226.1 | F17: =F12-F14 -> 15206.51 | G17: =G12-G14 -> 10157.75 | H17: =H12-H14 -> 11487.02 | I17: =I12-I14 -> 14682.85 | J17: =J12-J14 -> 20285.29 | ... L17: =L12-L14 -> 30518.19
B18: ebit % sales | C18: =C17/C6 -> 0.13294108 | D18: =D17/D6 -> 0.12814181 | E18: =E17/E6 -> 0.1436153 | F18: =F17/F6 -> 0.14521019 | G18: =G17/G6 -> 0.13475046 | H18: =H17/H6 -> 0.15464948 | I18: =I17/I6 -> 0.16283417 | J18: =J17/J6 -> 0.16727577 | ... M18: =M17/M6 -> 0
B20: Interest | C20: =IFERROR('Data Sheet'!B27,0) -> 3367.59 | D20: =IFERROR('Data Sheet'!C27,0) -> 3648.46 | E20: =IFERROR('Data Sheet'!D27,0) -> 3987.09 | F20: =IFERROR('Data Sheet'!E27,0) -> 5021.35 | G20: =IFERROR('Data Sheet'!F27,0) -> 6021.15 | H20: =IFERROR('Data Sheet'!G27,0) -> 6102.22 | I20: =IFERROR('Data Sheet'!H27,0) -> 5018.05 | J20: =IFERROR('Data Sheet'!I27,0) -> 5829.7 | ... L20: =IFERROR('Data Sheet'!K27,0) -> 9083.39 | M20: =IFERROR(SUM('Data Sheet'!H27:K27),0) -> 27419.35
B21: interest % sales | C21: =C20/C6 -> 0.044403045 | D21: =D20/D6 -> 0.043551715 | E21: =E20/E6 -> 0.043293723 | F21: =F20/F6 -> 0.047949937 | G21: =G20/G6 -> 0.079875243 | H21: =H20/H6 -> 0.082154044 | I21: =I20/I6 -> 0.055650641 | J21: =J20/J6 -> 0.048072645 | ... M21: =M20/M6 -> 0.067182542
B23: Depreciation | C23: =IFERROR('Data Sheet'!B26,0) -> 2441.65 | D23: =IFERROR('Data Sheet'!C26,0) -> 2812.72 | E23: =IFERROR('Data Sheet'!D26,0) -> 3279.9 | F23: =IFERROR('Data Sheet'!E26,0) -> 3990.77 | G23: =IFERROR('Data Sheet'!F26,0) -> 3366.68 | H23: =IFERROR('Data Sheet'!G26,0) -> 3378.11 | I23: =IFERROR('Data Sheet'!H26,0) -> 3507.5 | J23: =IFERROR('Data Sheet'!I26,0) -> 4356.81 | ... L23: =IFERROR('Data Sheet'!K26,0) -> 6073.65 | M23: =IFERROR(SUM('Data Sheet'!H26:K26),0) -> 18661.74
B24: Depreciation % sales | C24: =C23/C6 -> 0.032194149 | D24: =D23/D6 -> 0.033575476 | E24: =E23/E6 -> 0.035614717 | F24: =F23/F6 -> 0.03810871 | G24: =G23/G6 -> 0.044661632 | H24: =H23/H6 -> 0.045479415 | I24: =I23/I6 -> 0.038898501 | J24: =J23/J6 -> 0.035926957 | ... M24: =M23/M6 -> 0.045724758
B26: Earning before Tax | C26: =IFERROR(C17-SUM(C20,C23),0) -> 4273.2 | D26: =IFERROR(D17-SUM(D20,D23),0) -> 4273.65 | E26: =IFERROR(E17-SUM(E20,E23),0) -> 5959.11 | F26: =IFERROR(F17-SUM(F20,F23),0) -> 6194.39 | G26: =IFERROR(G17-SUM(G20,G23),0) -> 769.92 | H26: =IFERROR(H17-SUM(H20,H23),0) -> 2006.69 | I26: =IFERROR(I17-SUM(I20,I23),0) -> 6157.3 | J26: =IFERROR(J17-SUM(J20,J23),0) -> 10098.78 | ... L26: =IFERROR(L17-SUM(L20,L23),0) -> 15361.15 | N26: =_xlfn.FORMULATEXT(L26) -> =IFERROR(L17-SUM(L20,L23),0)
B27: EBT % sales | C27: =C26/C6 -> 0.056343882 | D27: =D26/D6 -> 0.051014616 | E27: =E26/E6 -> 0.064706856 | F27: =F26/F6 -> 0.059151545 | G27: =G26/G6 -> 0.010213588 | H27: =H26/H6 -> 0.02701602 | I27: =I26/I6 -> 0.068285029 | J27: =J26/J6 -> 0.083276167 | ... M27: =M26/M6 -> 0
B29: Tax | C29: =IFERROR('Data Sheet'!B29,0) -> 2117.53 | D29: =IFERROR('Data Sheet'!C29,0) -> 2299.73 | E29: =IFERROR('Data Sheet'!D29,0) -> 2367.73 | F29: =IFERROR('Data Sheet'!E29,0) -> 2853.99 | G29: =IFERROR('Data Sheet'!F29,0) -> 1975.61 | H29: =IFERROR('Data Sheet'!G29,0) -> 1645.81 | I29: =IFERROR('Data Sheet'!H29,0) -> 2108.76 | J29: =IFERROR('Data Sheet'!I29,0) -> 2685.75 | ... L29: =IFERROR('Data Sheet'!K29,0) -> 5006.45 | M29: =IFERROR(SUM('Data Sheet'!H29:K29),0) -> 13508.93
B30: effective tax rate | C30: =C29/C6 -> 0.027920495 | D30: =D29/D6 -> 0.027451907 | E30: =E29/E6 -> 0.025709941 | F30: =F29/F6 -> 0.027253356 | G30: =G29/G6 -> 0.026208005 | H30: =H29/H6 -> 0.022157501 | I30: =I29/I6 -> 0.023386344 | J30: =J29/J6 -> 0.022147127 | ... M30: =M29/M6 -> 0.033099408
B32: Net profit | C32: =C26-C29 -> 2155.67 | D32: =D26-D29 -> 1973.92 | E32: =E26-E29 -> 3591.38 | F32: =F26-F29 -> 3340.4 | G32: =G26-G29 -> -1205.69 | H32: =H26-H29 -> 360.88 | I32: =I26-I29 -> 4048.54 | J32: =J26-J29 -> 7413.03 | ... L32: =L26-L29 -> 10354.7
B33: Net margin | C33: =C32/C6 -> 0.028423387 | D33: =D32/D6 -> 0.023562709 | E33: =E32/E6 -> 0.038996916 | F33: =F32/F6 -> 0.031898189 | G33: =G32/G6 -> -0.015994417 | H33: =H32/H6 -> 0.0048585189 | I33: =I32/I6 -> 0.044898685 | J33: =J32/J6 -> 0.06112904 | ... L33: =L32/L6 -> 0.065037665
B35: No. of equity shares | C35: =IFERROR('Data Sheet'!B93,0) -> 124.22 | D35: =IFERROR('Data Sheet'!C93,0) -> 124.22 | E35: =IFERROR('Data Sheet'!D93,0) -> 124.32 | F35: =IFERROR('Data Sheet'!E93,0) -> 124.32 | G35: =IFERROR('Data Sheet'!F93,0) -> 124.32 | H35: =IFERROR('Data Sheet'!G93,0) -> 124.32 | I35: =IFERROR('Data Sheet'!H93,0) -> 124.32 | J35: =IFERROR('Data Sheet'!I93,0) -> 124.35 | ... M35: =IFERROR('Data Sheet'!L93,0) -> 0
B37: Earnings Per Shares | C37: =IFERROR(C32/C35,0) -> 17.353647 | D37: =IFERROR(D32/D35,0) -> 15.890517 | E37: =IFERROR(E32/E35,0) -> 28.888192 | F37: =IFERROR(F32/F35,0) -> 26.869369 | G37: =IFERROR(G32/G35,0) -> -9.6982786 | H37: =IFERROR(H32/H35,0) -> 2.9028314 | I37: =IFERROR(I32/I35,0) -> 32.565476 | J37: =IFERROR(J32/J35,0) -> 59.614234 | ... M37: =IFERROR(M32/M35,0) -> 0
B38: EPS Growh | D38: =D37/C37-1 -> -0.084312534 | E38: =E37/D37-1 -> 0.81795168 | F38: =F37/E37-1 -> -0.069884 | G38: =G37/F37-1 -> -1.3609418 | H38: =H37/G37-1 -> -1.2993141 | I38: =I37/H37-1 -> 10.218521 | J38: =J37/I37-1 -> 0.83059611 | K38: =K37/J37-1 -> 0.21029727 | L38: =L37/K37-1 -> 0.15411665
B40: dividend per share | C40: =IFERROR('Data Sheet'!B31/'historical sf '!C35,0) -> 5.2242795 | D40: =IFERROR('Data Sheet'!C31/'historical sf '!D35,0) -> 6.5 | E40: =IFERROR('Data Sheet'!D31/'historical sf '!E35,0) -> 6.5532497 | F40: =IFERROR('Data Sheet'!E31/'historical sf '!F35,0) -> 7.4383044 | G40: =IFERROR('Data Sheet'!F31/'historical sf '!G35,0) -> 2.0954794 | H40: =IFERROR('Data Sheet'!G31/'historical sf '!H35,0) -> 7.8145914 | I40: =IFERROR('Data Sheet'!H31/'historical sf '!I35,0) -> 10.332207 | J40: =IFERROR('Data Sheet'!I31/'historical sf '!J35,0) -> 14.552955 | ... M40: =IFERROR('Data Sheet'!L31/'historical sf '!M35,0) -> 0 | N40: =_xlfn.FORMULATEXT(L40) -> =IFERROR('Data Sheet'!K31/'historical sf '!L35,0)
B41: dividend payout ratio | C41: =C40/C37 -> 0.30104793 | D41: =D40/D37 -> 0.409049 | E41: =E40/E37 -> 0.22684873 | F41: =F40/F37 -> 0.27683212 | G41: =G40/G37 -> -0.21606715 | H41: =H40/H37 -> 2.6920583 | I41: =I40/I37 -> 0.31727487 | J41: =J40/J37 -> 0.2441188 | ... L41: =L40/L37 -> 0.27274957
B43: Retained Earning | C43: =IFERROR(IF(C37>C40,1-C41,0),0) -> 0.69895207 | D43: =IFERROR(IF(D37>D40,1-D41,0),0) -> 0.590951 | E43: =IFERROR(IF(E37>E40,1-E41,0),0) -> 0.77315127 | F43: =IFERROR(IF(F37>F40,1-F41,0),0) -> 0.72316788 | G43: =IFERROR(IF(G37>G40,1-G41,0),0) -> 0 | H43: =IFERROR(IF(H37>H40,1-H41,0),0) -> 0 | I43: =IFERROR(IF(I37>I40,1-I41,0),0) -> 0.68272513 | J43: =IFERROR(IF(J37>J40,1-J41,0),0) -> 0.7558812 | ... M43: =IFERROR(IF(M37>M40,1-M41,0),0) -> 0 | N43: =_xlfn.FORMULATEXT(L43) -> =IFERROR(IF(L37>L40,1-L41,0),0)
A47: # | B47: Balance Sheet as on
B49: Equity Share Capital | C49: =IFERROR('Data Sheet'!B57,0) -> 270.4 | D49: =IFERROR('Data Sheet'!C57,0) -> 310.55 | E49: =IFERROR('Data Sheet'!D57,0) -> 543.13 | F49: =IFERROR('Data Sheet'!E57,0) -> 543.96 | G49: =IFERROR('Data Sheet'!F57,0) -> 554.28 | H49: =IFERROR('Data Sheet'!G57,0) -> 555.15 | I49: =IFERROR('Data Sheet'!H57,0) -> 556.06 | J49: =IFERROR('Data Sheet'!I57,0) -> 556.82 | ... L49: =IFERROR('Data Sheet'!K57,0) -> 558.15
B50: Reserves | C50: =IFERROR('Data Sheet'!B58,0) -> 26222.25 | D50: =IFERROR('Data Sheet'!C58,0) -> 29467.1 | E50: =IFERROR('Data Sheet'!D58,0) -> 36232.06 | F50: =IFERROR('Data Sheet'!E58,0) -> 39439.45 | G50: =IFERROR('Data Sheet'!F58,0) -> 39415.03 | H50: =IFERROR('Data Sheet'!G58,0) -> 41026.77 | I50: =IFERROR('Data Sheet'!H58,0) -> 46566.58 | J50: =IFERROR('Data Sheet'!I58,0) -> 55808.97 | ... L50: =IFERROR('Data Sheet'!K58,0) -> 76480.71
B51: Borrowings | C51: =IFERROR('Data Sheet'!B59,0) -> 41552.93 | D51: =IFERROR('Data Sheet'!C59,0) -> 48761.91 | E51: =IFERROR('Data Sheet'!D59,0) -> 55897.92 | F51: =IFERROR('Data Sheet'!E59,0) -> 70848.3 | G51: =IFERROR('Data Sheet'!F59,0) -> 82092.28 | H51: =IFERROR('Data Sheet'!G59,0) -> 80624.83 | I51: =IFERROR('Data Sheet'!H59,0) -> 77605.21 | J51: =IFERROR('Data Sheet'!I59,0) -> 92246.85 | ... L51: =IFERROR('Data Sheet'!K59,0) -> 129024.58
B52: Other Liabilities | C52: =IFERROR('Data Sheet'!B60,0) -> 31806.24 | D52: =IFERROR('Data Sheet'!C60,0) -> 35295.92 | E52: =IFERROR('Data Sheet'!D60,0) -> 43696.2 | F52: =IFERROR('Data Sheet'!E60,0) -> 51056.95 | G52: =IFERROR('Data Sheet'!F60,0) -> 43654.54 | H52: =IFERROR('Data Sheet'!G60,0) -> 42761.58 | I52: =IFERROR('Data Sheet'!H60,0) -> 47660.64 | J52: =IFERROR('Data Sheet'!I60,0) -> 55670.49 | ... L52: =IFERROR('Data Sheet'!K60,0) -> 69949.72
B53: Total Liabilities | C53: =IFERROR('Data Sheet'!B61,0) -> 99851.82 | D53: =IFERROR('Data Sheet'!C61,0) -> 113835.48 | E53: =IFERROR('Data Sheet'!D61,0) -> 136369.31 | F53: =IFERROR('Data Sheet'!E61,0) -> 161888.66 | G53: =IFERROR('Data Sheet'!F61,0) -> 165716.13 | H53: =IFERROR('Data Sheet'!G61,0) -> 164968.33 | I53: =IFERROR('Data Sheet'!H61,0) -> 172388.49 | J53: =IFERROR('Data Sheet'!I61,0) -> 204283.13 | ... L53: =IFERROR('Data Sheet'!K61,0) -> 276013.16
B55: Net Assets | C55: =IFERROR('Data Sheet'!B62,0) -> 20584.71 | D55: =IFERROR('Data Sheet'!C62,0) -> 20989.01 | E55: =IFERROR('Data Sheet'!D62,0) -> 26181.9 | F55: =IFERROR('Data Sheet'!E62,0) -> 28982.74 | G55: =IFERROR('Data Sheet'!F62,0) -> 29689.27 | H55: =IFERROR('Data Sheet'!G62,0) -> 21379.68 | I55: =IFERROR('Data Sheet'!H62,0) -> 26018.49 | J55: =IFERROR('Data Sheet'!I62,0) -> 27139.98 | ... L55: =IFERROR('Data Sheet'!K62,0) -> 34636.36
B56: Capital Work in Progress | C56: =IFERROR('Data Sheet'!B63,0) -> 2371.35 | D56: =IFERROR('Data Sheet'!C63,0) -> 4278.94 | E56: =IFERROR('Data Sheet'!D63,0) -> 4269.47 | F56: =IFERROR('Data Sheet'!E63,0) -> 4759.84 | G56: =IFERROR('Data Sheet'!F63,0) -> 6856.48 | H56: =IFERROR('Data Sheet'!G63,0) -> 7872.61 | I56: =IFERROR('Data Sheet'!H63,0) -> 6702.81 | J56: =IFERROR('Data Sheet'!I63,0) -> 3968.58 | ... L56: =IFERROR('Data Sheet'!K63,0) -> 8297.64
B57: Investments | C57: =IFERROR('Data Sheet'!B64,0) -> 11602.58 | D57: =IFERROR('Data Sheet'!C64,0) -> 14662.44 | E57: =IFERROR('Data Sheet'!D64,0) -> 16017.61 | F57: =IFERROR('Data Sheet'!E64,0) -> 18268.1 | G57: =IFERROR('Data Sheet'!F64,0) -> 19210.34 | H57: =IFERROR('Data Sheet'!G64,0) -> 28777.66 | I57: =IFERROR('Data Sheet'!H64,0) -> 30060.43 | J57: =IFERROR('Data Sheet'!I64,0) -> 35272.42 | ... L57: =IFERROR('Data Sheet'!K64,0) -> 41308.57
B58: Other Assets | C58: =IFERROR('Data Sheet'!B65-SUM('Data Sheet'!B67:B69),0) -> 45831.91 | D58: =IFERROR('Data Sheet'!C65-SUM('Data Sheet'!C67:C69),0) -> 53165.79 | E58: =IFERROR('Data Sheet'!D65-SUM('Data Sheet'!D67:D69),0) -> 65527.34 | F58: =IFERROR('Data Sheet'!E65-SUM('Data Sheet'!E67:E69),0) -> 80265.02 | G58: =IFERROR('Data Sheet'!F65-SUM('Data Sheet'!F67:F69),0) -> 84009 | H58: =IFERROR('Data Sheet'!G65-SUM('Data Sheet'!G67:G69),0) -> 78463.22 | I58: =IFERROR('Data Sheet'!H65-SUM('Data Sheet'!H67:H69),0) -> 80519.38 | J58: =IFERROR('Data Sheet'!I65-SUM('Data Sheet'!I67:I69),0) -> 102745.73 | ... L58: =IFERROR('Data Sheet'!K65-SUM('Data Sheet'!K67:K69),0) -> 142545.12 | N58: =_xlfn.FORMULATEXT(L58) -> =IFERROR('Data Sheet'!K65-SUM('Data Sheet'!K67:K69),0)
B59: Total Non Current Assets | C59: =SUM(C55:C58) -> 80390.55 | D59: =SUM(D55:D58) -> 93096.18 | E59: =SUM(E55:E58) -> 111996.32 | F59: =SUM(F55:F58) -> 132275.7 | G59: =SUM(G55:G58) -> 139765.09 | H59: =SUM(H55:H58) -> 136493.17 | I59: =SUM(I55:I58) -> 143301.11 | J59: =SUM(J55:J58) -> 169126.71 | ... L59: =SUM(L55:L58) -> 226787.69
B61: Receivables | C61: =IFERROR('Data Sheet'!B67,0) -> 5817.6 | D61: =IFERROR('Data Sheet'!C67,0) -> 7199.26 | E61: =IFERROR('Data Sheet'!D67,0) -> 8489.82 | F61: =IFERROR('Data Sheet'!E67,0) -> 8677.89 | G61: =IFERROR('Data Sheet'!F67,0) -> 6928.28 | H61: =IFERROR('Data Sheet'!G67,0) -> 6007.76 | I61: =IFERROR('Data Sheet'!H67,0) -> 6373.95 | J61: =IFERROR('Data Sheet'!I67,0) -> 7028.02 | ... L61: =IFERROR('Data Sheet'!K67,0) -> 8279.7
B62: Inventory | C62: =IFERROR('Data Sheet'!B68,0) -> 9116.12 | D62: =IFERROR('Data Sheet'!C68,0) -> 8886.01 | E62: =IFERROR('Data Sheet'!D68,0) -> 9335.57 | F62: =IFERROR('Data Sheet'!E68,0) -> 12200.16 | G62: =IFERROR('Data Sheet'!F68,0) -> 11111.86 | H62: =IFERROR('Data Sheet'!G68,0) -> 9615.41 | I62: =IFERROR('Data Sheet'!H68,0) -> 11595.82 | J62: =IFERROR('Data Sheet'!I68,0) -> 16854.97 | ... L62: =IFERROR('Data Sheet'!K68,0) -> 20330.93
B63: Cash & Bank | C63: =IFERROR('Data Sheet'!B69,0) -> 4527.55 | D63: =IFERROR('Data Sheet'!C69,0) -> 4654.03 | E63: =IFERROR('Data Sheet'!D69,0) -> 6547.6 | F63: =IFERROR('Data Sheet'!E69,0) -> 8734.91 | G63: =IFERROR('Data Sheet'!F69,0) -> 7910.9 | H63: =IFERROR('Data Sheet'!G69,0) -> 12851.99 | I63: =IFERROR('Data Sheet'!H69,0) -> 11117.61 | J63: =IFERROR('Data Sheet'!I69,0) -> 11273.43 | ... L63: =IFERROR('Data Sheet'!K69,0) -> 20614.84
B64: Total Current Asstes | C64: =SUM(C61:C63) -> 19461.27 | D64: =SUM(D61:D63) -> 20739.3 | E64: =SUM(E61:E63) -> 24372.99 | F64: =SUM(F61:F63) -> 29612.96 | G64: =SUM(G61:G63) -> 25951.04 | H64: =SUM(H61:H63) -> 28475.16 | I64: =SUM(I61:I63) -> 29087.38 | J64: =SUM(J61:J63) -> 35156.42 | ... L64: =SUM(L61:L63) -> 49225.47
B66: Total asstes | C66: =IFERROR(C59+C64,0) -> 99851.82 | D66: =IFERROR(D59+D64,0) -> 113835.48 | E66: =IFERROR(E59+E64,0) -> 136369.31 | F66: =IFERROR(F59+F64,0) -> 161888.66 | G66: =IFERROR(G59+G64,0) -> 165716.13 | H66: =IFERROR(H59+H64,0) -> 164968.33 | I66: =IFERROR(I59+I64,0) -> 172388.49 | J66: =IFERROR(J59+J64,0) -> 204283.13 | ... L66: =IFERROR(L59+L64,0) -> 276013.16 | N66: =_xlfn.FORMULATEXT(L66) -> =IFERROR(L59+L64,0)
B68: check | C68: =C53=C66 -> TRUE | D68: =D53=D66 -> TRUE | E68: =E53=E66 -> TRUE | F68: =F53=F66 -> TRUE | G68: =G53=G66 -> TRUE | H68: =H53=H66 -> TRUE | I68: =I53=I66 -> TRUE | J68: =J53=J66 -> TRUE | ... L68: =L53=L66 -> TRUE
A71: # | B71: cash flow from operating activity
B72: Operating Activity -
B73: Profit from operations | C73: =IFERROR('cash flow '!D4,0) -> 7595 | D73: =IFERROR('cash flow '!E4,0) -> 7911 | E73: =IFERROR('cash flow '!F4,0) -> 10159 | F73: =IFERROR('cash flow '!G4,0) -> 11112 | G73: =IFERROR('cash flow '!H4,0) -> 7774 | H73: =IFERROR('cash flow '!I4,0) -> 7588 | I73: =IFERROR('cash flow '!J4,0) -> 10515 | J73: =IFERROR('cash flow '!K4,0) -> 15642 | ... L73: =IFERROR('cash flow '!M4,0) -> 22050
B74: Receivables | C74: =IFERROR('cash flow '!D5,0) -> 177 | D74: =IFERROR('cash flow '!E5,0) -> -8609 | E74: =IFERROR('cash flow '!F5,0) -> -11918 | F74: =IFERROR('cash flow '!G5,0) -> -13712 | G74: =IFERROR('cash flow '!H5,0) -> -1516 | H74: =IFERROR('cash flow '!I5,0) -> 4896 | I74: =IFERROR('cash flow '!J5,0) -> -2506 | J74: =IFERROR('cash flow '!K5,0) -> -21702 | ... L74: =IFERROR('cash flow '!M5,0) -> -20952
B75: Inventory | C75: =IFERROR('cash flow '!D6,0) -> -1113 | D75: =IFERROR('cash flow '!E6,0) -> 241 | E75: =IFERROR('cash flow '!F6,0) -> -256 | F75: =IFERROR('cash flow '!G6,0) -> -2276 | G75: =IFERROR('cash flow '!H6,0) -> 1316 | H75: =IFERROR('cash flow '!I6,0) -> 226 | I75: =IFERROR('cash flow '!J6,0) -> -2173 | J75: =IFERROR('cash flow '!K6,0) -> -5252 | ... L75: =IFERROR('cash flow '!M6,0) -> -1646
B76: Payables | C76: =IFERROR('cash flow '!D7,0) -> 1939 | D76: =IFERROR('cash flow '!E7,0) -> 2645 | E76: =IFERROR('cash flow '!F7,0) -> 5361 | F76: =IFERROR('cash flow '!G7,0) -> 3466 | G76: =IFERROR('cash flow '!H7,0) -> -6775 | H76: =IFERROR('cash flow '!I7,0) -> 7049 | I76: =IFERROR('cash flow '!J7,0) -> 4972 | J76: =IFERROR('cash flow '!K7,0) -> 7013 | ... L76: =IFERROR('cash flow '!M7,0) -> 8485
B77: Loans Advances | C77: =IFERROR('cash flow '!D8,0) -> 0 | D77: =IFERROR('cash flow '!E8,0) -> 0 | E77: =IFERROR('cash flow '!F8,0) -> 0 | F77: =IFERROR('cash flow '!G8,0) -> 0 | G77: =IFERROR('cash flow '!H8,0) -> 0 | H77: =IFERROR('cash flow '!I8,0) -> 0 | I77: =IFERROR('cash flow '!J8,0) -> 0 | J77: =IFERROR('cash flow '!K8,0) -> 0 | ... L77: =IFERROR('cash flow '!M8,0) -> 0
B78: Other WC items | C78: =IFERROR('cash flow '!D9,0) -> -4241 | D78: =IFERROR('cash flow '!E9,0) -> 0 | E78: =IFERROR('cash flow '!F9,0) -> 0 | F78: =IFERROR('cash flow '!G9,0) -> 0 | G78: =IFERROR('cash flow '!H9,0) -> 0 | H78: =IFERROR('cash flow '!I9,0) -> 0 | I78: =IFERROR('cash flow '!J9,0) -> 0 | J78: =IFERROR('cash flow '!K9,0) -> 0 | ... L78: =IFERROR('cash flow '!M9,0) -> 0
B79: Working capital changes | C79: =IFERROR('cash flow '!D10,0) -> -3238 | D79: =IFERROR('cash flow '!E10,0) -> -5724 | E79: =IFERROR('cash flow '!F10,0) -> -6813 | F79: =IFERROR('cash flow '!G10,0) -> -12522 | G79: =IFERROR('cash flow '!H10,0) -> -6974 | H79: =IFERROR('cash flow '!I10,0) -> 12171 | I79: =IFERROR('cash flow '!J10,0) -> 293 | J79: =IFERROR('cash flow '!K10,0) -> -19941 | ... L79: =IFERROR('cash flow '!M10,0) -> -14113
B80: Direct taxes | C80: =IFERROR('cash flow '!D11,0) -> -1973 | D80: =IFERROR('cash flow '!E11,0) -> -2005 | E80: =IFERROR('cash flow '!F11,0) -> -2664 | F80: =IFERROR('cash flow '!G11,0) -> -2937 | G80: =IFERROR('cash flow '!H11,0) -> -2257 | H80: =IFERROR('cash flow '!I11,0) -> -1850 | I80: =IFERROR('cash flow '!J11,0) -> -1560 | J80: =IFERROR('cash flow '!K11,0) -> -2775 | ... L80: =IFERROR('cash flow '!M11,0) -> -4761
B81: Cash from Operating Activity - | C81: =SUM(C73:C80) -> -854 | D81: =SUM(D73:D80) -> -5541 | E81: =SUM(E73:E80) -> -6131 | F81: =SUM(F73:F80) -> -16869 | G81: =SUM(G73:G80) -> -8432 | H81: =SUM(H73:H80) -> 30080 | I81: =SUM(I73:I80) -> 9541 | J81: =SUM(J73:J80) -> -27015 | ... L81: =SUM(L73:L80) -> -10937
B83: Investing Activity
B84: Fixed assets purchased | C84: =IFERROR('cash flow '!C13,0) -> -4759 | D84: =IFERROR('cash flow '!D13,0) -> -4172 | E84: =IFERROR('cash flow '!E13,0) -> -5026 | F84: =IFERROR('cash flow '!F13,0) -> -5906 | G84: =IFERROR('cash flow '!G13,0) -> -7340 | H84: =IFERROR('cash flow '!H13,0) -> -6896 | I84: =IFERROR('cash flow '!I13,0) -> -5989 | J84: =IFERROR('cash flow '!J13,0) -> -6040 | ... L84: =IFERROR('cash flow '!L13,0) -> -9946
B85: Fixed assets sold | C85: =IFERROR('cash flow '!C14,0) -> 43 | D85: =IFERROR('cash flow '!D14,0) -> 59 | E85: =IFERROR('cash flow '!E14,0) -> 63 | F85: =IFERROR('cash flow '!F14,0) -> 115 | G85: =IFERROR('cash flow '!G14,0) -> 142 | H85: =IFERROR('cash flow '!H14,0) -> 102 | I85: =IFERROR('cash flow '!I14,0) -> 1364 | J85: =IFERROR('cash flow '!J14,0) -> 120 | ... L85: =IFERROR('cash flow '!L14,0) -> 273
B86: Investments purchased | C86: =IFERROR('cash flow '!C15,0) -> -80047 | D86: =IFERROR('cash flow '!D15,0) -> -87898 | E86: =IFERROR('cash flow '!E15,0) -> -132173 | F86: =IFERROR('cash flow '!F15,0) -> -155159 | G86: =IFERROR('cash flow '!G15,0) -> -196474 | H86: =IFERROR('cash flow '!H15,0) -> -198568 | I86: =IFERROR('cash flow '!I15,0) -> -120055 | J86: =IFERROR('cash flow '!J15,0) -> -65421 | ... L86: =IFERROR('cash flow '!L15,0) -> -49927
B87: Investments sold | C87: =IFERROR('cash flow '!C16,0) -> 79778 | D87: =IFERROR('cash flow '!D16,0) -> 86436 | E87: =IFERROR('cash flow '!E16,0) -> 130940 | F87: =IFERROR('cash flow '!F16,0) -> 154631 | G87: =IFERROR('cash flow '!G16,0) -> 195898 | H87: =IFERROR('cash flow '!H16,0) -> 198132 | I87: =IFERROR('cash flow '!I16,0) -> 111749 | J87: =IFERROR('cash flow '!J16,0) -> 65127 | ... L87: =IFERROR('cash flow '!L16,0) -> 50919
B88: Interest received | C88: =IFERROR('cash flow '!C17,0) -> 356 | D88: =IFERROR('cash flow '!D17,0) -> 311 | E88: =IFERROR('cash flow '!E17,0) -> 346 | F88: =IFERROR('cash flow '!F17,0) -> 254 | G88: =IFERROR('cash flow '!G17,0) -> 314 | H88: =IFERROR('cash flow '!H17,0) -> 372 | I88: =IFERROR('cash flow '!I17,0) -> 431 | J88: =IFERROR('cash flow '!J17,0) -> 420 | ... L88: =IFERROR('cash flow '!L17,0) -> 703
B89: Dividends received | C89: =IFERROR('cash flow '!C18,0) -> 169 | D89: =IFERROR('cash flow '!D18,0) -> 208 | E89: =IFERROR('cash flow '!E18,0) -> 409 | F89: =IFERROR('cash flow '!F18,0) -> 316 | G89: =IFERROR('cash flow '!G18,0) -> 466 | H89: =IFERROR('cash flow '!H18,0) -> 722 | I89: =IFERROR('cash flow '!I18,0) -> 577 | J89: =IFERROR('cash flow '!J18,0) -> 1247 | ... L89: =IFERROR('cash flow '!L18,0) -> 1213
B90: Investment in group cos | C90: =IFERROR('cash flow '!C19,0) -> 0 | D90: =IFERROR('cash flow '!D19,0) -> -147 | E90: =IFERROR('cash flow '!E19,0) -> -647 | F90: =IFERROR('cash flow '!F19,0) -> -704 | G90: =IFERROR('cash flow '!G19,0) -> -319 | H90: =IFERROR('cash flow '!H19,0) -> -418 | I90: =IFERROR('cash flow '!I19,0) -> -359 | J90: =IFERROR('cash flow '!J19,0) -> -222 | ... L90: =IFERROR('cash flow '!L19,0) -> -249
B91: Redemp n Canc of Shares | C91: =IFERROR('cash flow '!C20,0) -> 401 | D91: =IFERROR('cash flow '!D20,0) -> 0 | E91: =IFERROR('cash flow '!E20,0) -> 88 | F91: =IFERROR('cash flow '!F20,0) -> 1677 | G91: =IFERROR('cash flow '!G20,0) -> 717 | H91: =IFERROR('cash flow '!H20,0) -> 175 | I91: =IFERROR('cash flow '!I20,0) -> 316 | J91: =IFERROR('cash flow '!J20,0) -> 617 | ... L91: =IFERROR('cash flow '!L20,0) -> 1043
B92: Acquisition of companies | C92: =IFERROR('cash flow '!C21,0) -> 0 | D92: =IFERROR('cash flow '!D21,0) -> -208 | E92: =IFERROR('cash flow '!E21,0) -> -83 | F92: =IFERROR('cash flow '!F21,0) -> -401 | G92: =IFERROR('cash flow '!G21,0) -> 0 | H92: =IFERROR('cash flow '!H21,0) -> -59 | I92: =IFERROR('cash flow '!I21,0) -> 0 | J92: =IFERROR('cash flow '!J21,0) -> -42 | ... L92: =IFERROR('cash flow '!L21,0) -> -53
B93: Inter corporate deposits | C93: =IFERROR('cash flow '!C22,0) -> -22 | D93: =IFERROR('cash flow '!D22,0) -> 0 | E93: =IFERROR('cash flow '!E22,0) -> 0 | F93: =IFERROR('cash flow '!F22,0) -> 0 | G93: =IFERROR('cash flow '!G22,0) -> 0 | H93: =IFERROR('cash flow '!H22,0) -> 6 | I93: =IFERROR('cash flow '!I22,0) -> -262 | J93: =IFERROR('cash flow '!J22,0) -> -552 | ... L93: =IFERROR('cash flow '!L22,0) -> 485
B94: Other investing items | C94: =IFERROR('cash flow '!C23,0) -> -275 | D94: =IFERROR('cash flow '!D23,0) -> -94 | E94: =IFERROR('cash flow '!E23,0) -> 209 | F94: =IFERROR('cash flow '!F23,0) -> -290 | G94: =IFERROR('cash flow '!G23,0) -> -577 | H94: =IFERROR('cash flow '!H23,0) -> -437 | I94: =IFERROR('cash flow '!I23,0) -> -7457 | J94: =IFERROR('cash flow '!J23,0) -> 1494 | ... L94: =IFERROR('cash flow '!L23,0) -> -78
B95: Cash from Investing Activity - | C95: =SUM(C84:C94) -> -4356 | D95: =SUM(D84:D94) -> -5505 | E95: =SUM(E84:E94) -> -5874 | F95: =SUM(F84:F94) -> -5467 | G95: =SUM(G84:G94) -> -7173 | H95: =SUM(H84:H94) -> -6869 | I95: =SUM(I84:I94) -> -19685 | J95: =SUM(J84:J94) -> -3252 | ... L95: =SUM(L84:L94) -> -5617
B97: Financing Activity
B98: Proceeds from shares | C98: =IFERROR('cash flow '!C25,0) -> 3 | D98: =IFERROR('cash flow '!D25,0) -> 18 | E98: =IFERROR('cash flow '!E25,0) -> 12 | F98: =IFERROR('cash flow '!F25,0) -> 4 | G98: =IFERROR('cash flow '!G25,0) -> 1 | H98: =IFERROR('cash flow '!H25,0) -> 1243 | I98: =IFERROR('cash flow '!I25,0) -> 1 | J98: =IFERROR('cash flow '!J25,0) -> 1 | ... L98: =IFERROR('cash flow '!L25,0) -> 1
B99: Proceeds from borrowings | C99: =IFERROR('cash flow '!C26,0) -> 0 | D99: =IFERROR('cash flow '!D26,0) -> 0 | E99: =IFERROR('cash flow '!E26,0) -> 0 | F99: =IFERROR('cash flow '!F26,0) -> 0 | G99: =IFERROR('cash flow '!G26,0) -> 71389 | H99: =IFERROR('cash flow '!H26,0) -> 52618 | I99: =IFERROR('cash flow '!I26,0) -> 38100 | J99: =IFERROR('cash flow '!J26,0) -> 53880 | ... L99: =IFERROR('cash flow '!L26,0) -> 61308
B100: Repayment of borrowings | C100: =IFERROR('cash flow '!C27,0) -> 0 | D100: =IFERROR('cash flow '!D27,0) -> 0 | E100: =IFERROR('cash flow '!E27,0) -> 0 | F100: =IFERROR('cash flow '!F27,0) -> 0 | G100: =IFERROR('cash flow '!G27,0) -> -56352 | H100: =IFERROR('cash flow '!H27,0) -> -44044 | I100: =IFERROR('cash flow '!I27,0) -> -37505 | J100: =IFERROR('cash flow '!J27,0) -> -57223 | ... L100: =IFERROR('cash flow '!L27,0) -> -46805
B101: Interest paid fin | C101: =IFERROR('cash flow '!C28,0) -> -489 | D101: =IFERROR('cash flow '!D28,0) -> -443 | E101: =IFERROR('cash flow '!E28,0) -> -471 | F101: =IFERROR('cash flow '!F28,0) -> -521 | G101: =IFERROR('cash flow '!G28,0) -> -723 | H101: =IFERROR('cash flow '!H28,0) -> -624 | I101: =IFERROR('cash flow '!I28,0) -> -809 | J101: =IFERROR('cash flow '!J28,0) -> -680 | ... L101: =IFERROR('cash flow '!L28,0) -> -597
B102: Dividends paid | C102: =IFERROR('cash flow '!C29,0) -> -1200 | D102: =IFERROR('cash flow '!D29,0) -> -932 | E102: =IFERROR('cash flow '!E29,0) -> -936 | F102: =IFERROR('cash flow '!F29,0) -> -963 | G102: =IFERROR('cash flow '!G29,0) -> -1134 | H102: =IFERROR('cash flow '!H29,0) -> -1398 | I102: =IFERROR('cash flow '!I29,0) -> -271 | J102: =IFERROR('cash flow '!J29,0) -> -1037 | ... L102: =IFERROR('cash flow '!L29,0) -> -2247
B103: Financial liabilities | C103: =IFERROR('cash flow '!C30,0) -> 0 | D103: =IFERROR('cash flow '!D30,0) -> 0 | E103: =IFERROR('cash flow '!E30,0) -> 0 | F103: =IFERROR('cash flow '!F30,0) -> 0 | G103: =IFERROR('cash flow '!G30,0) -> 0 | H103: =IFERROR('cash flow '!H30,0) -> -558 | I103: =IFERROR('cash flow '!I30,0) -> -553 | J103: =IFERROR('cash flow '!J30,0) -> -583 | ... L103: =IFERROR('cash flow '!L30,0) -> -786
B104: Other financing items | C104: =IFERROR('cash flow '!C31,0) -> 3355 | D104: =IFERROR('cash flow '!D31,0) -> 4324 | E104: =IFERROR('cash flow '!E31,0) -> 7503 | F104: =IFERROR('cash flow '!F31,0) -> 7794 | G104: =IFERROR('cash flow '!G31,0) -> 12 | H104: =IFERROR('cash flow '!H31,0) -> -304 | I104: =IFERROR('cash flow '!I31,0) -> 1444 | J104: =IFERROR('cash flow '!J31,0) -> -240 | ... L104: =IFERROR('cash flow '!L31,0) -> 1408
B105: Cash from Financing Activity - | C105: =SUM(C98:C104) -> 1669 | D105: =SUM(D98:D104) -> 2967 | E105: =SUM(E98:E104) -> 6108 | F105: =SUM(F98:F104) -> 6314 | G105: =SUM(G98:G104) -> 13193 | H105: =SUM(H98:H104) -> 6933 | I105: =SUM(I98:I104) -> 407 | J105: =SUM(J98:J104) -> -5882 | ... L105: =SUM(L98:L104) -> 12282
B107: Net Cash Flow | C107: =SUM(C81+C95+C105) -> -3541 | D107: =SUM(D81+D95+D105) -> -8079 | E107: =SUM(E81+E95+E105) -> -5897 | F107: =SUM(F81+F95+F105) -> -16022 | G107: =SUM(G81+G95+G105) -> -2412 | H107: =SUM(H81+H95+H105) -> 30144 | I107: =SUM(I81+I95+I105) -> -9737 | J107: =SUM(J81+J95+J105) -> -36149 | ... L107: =SUM(L81+L95+L105) -> -4272

Sheet fiancials>
